Workbook

Sheet Preço Soja ESALQ
B1: Data final | C1: =TODAY() -> 46143 | E1: 3 | F1: =+E1+1 -> 4 | G1: =+F1+1 -> 5 | H1: =+G1+1 -> 6 | I1: =+H1+1 -> 7 | J1: =+I1+1 -> 8 | K1: =+J1+1 -> 9 | L1: =+K1+1 -> 10 | M1: =+L1+1 -> 11 | ... BN1: =+BM1+1 -> 64
C2: =_xll.RDP.HistoricalPricing($A$4:$A$65,"CLOSE","START:01-Jan-2015 END:"&$C$1&" SOURCE:RFV INTERVAL:P1D",,"CH:IN RH:Timestamp TSREPEAT:NO",D4) -> #NAME? | D2: INST_DESC | E2: Soy Meal Ponta Grossa, PR | F2: Soy Meal West Parana | G2: Soy Meal North Parana | H2: Soy Meal Triangulo Mineiro MG | I2: Soy Meal Chapeco, SC | J2: Soy Meal Campinas, Sao Pau | K2: Soy Meal Passo Fundo, RS | L2: Soy Meal Campo Grande, MS | M2: Soy Meal Rondonopolis, MT | N2: Soy Meal Rio Verde, GO | O2: Soy Meal Mogiana, Sao Pau | P2: Soy Meal Ijui, RS | Q2: Soyoil Sao Paulo | R2: Soybn Grower Trian Min, MG | S2: Soybn Grower Sorriso, MT | T2: Soybn Grower Sorocabana SP | U2: Soybn Grower Rondonopolis MT | V2: Soybn Grower Rio Verde, GO | W2: Soybn Grower Ponta Grossa PR | X2: Soybn Grower Passo Fundo RS | Y2: Soybn Grower West, Parana | Z2: Soybn Grower North, Parana | AA2: Soybn Grower Mogiana, SP | AB2: Soybn Grower Ijui, RS | AC2: Soybn Grower Barreiras, BA | AD2: Soybn Grower Balsas, MA | AE2: Soybn Wholesale Passo Fundo | AF2: Soybn Wholesale Sorocabana | AG2: Soybn Wholesale Sorriso MT | AH2: Trm day Len Catle - Caceres | AI2: Trm day Len Catle - Casilandia | AJ2: Trm day Len Catle - Itamaraju | AK2: Trm day Len Cattle - Nth Goias | AL2: Trm day Len Catle - Rondonopo | AM2: Trm day Len Catle - West Bahia | AN2: BR Lean Catle Trm - Casilandia | AO2: Trm day Lean Cattle - Pantanal | AP2: BR Len Catle Cash CDI -Colider | AQ2: BR Lean Cattle Term - Caceres | AR2: BR Len Cattle Term - Itamaraju | AS2: BR Lean Catle Trm -North Goias | AT2: BR Lean Cattle Term - Pantanal | AU2: Term days Lean Cattle - Para | AV2: Trm day Len Catle - Rio Grande | AW2: BR Lean Catle Trm - Rio Grande | AX2: Soybn Wholesale Rio Verde | AY2: BR Lean Catle Trm - West Bahia | AZ2: BR Lean Catle Trm - Rondonopo | BA2: Soybn Wholesale Rondonopolis | BB2: Soybn Wholesale Ponta Grossa | BC2: Soybn Wholesale West Parana | BD2: Soybn Wholesale North Parana | BE2: Soybn-Wholesale Mogiana SP | BF2: Soybn Wholesale Triang Min | BG2: Soybn Wholesale Ijui, RS | BH2: Soybn Wholesale Barreiras BA | BI2: Soybn Grower Campos Novo | BJ2: Soybn Wholesale Campos Novo | BK2: BR Soybean - Grower Cg MS | BL2: BR Soybean - Grower Dou MS | BM2: BR Soybean - Grower Cha-MS | BN2: BR Soybean - Grower Mar MS
A3: 0#ESQ-SOY | E3: {=_xll.TR(E4,$D$2)} -> #NAME? | F3: {=_xll.TR(F4,$D$2)} -> #NAME? | G3: {=_xll.TR(G4,$D$2)} -> #NAME? | H3: {=_xll.TR(H4,$D$2)} -> #NAME? | I3: {=_xll.TR(I4,$D$2)} -> #NAME? | J3: {=_xll.TR(J4,$D$2)} -> #NAME? | K3: {=_xll.TR(K4,$D$2)} -> #NAME? | L3: {=_xll.TR(L4,$D$2)} -> #NAME? | ... BN3: {=_xll.TR(BN4,$D$2)} -> #NAME?
A4: {=_xll.TR(A3,)} -> #NAME? | C4: COD | E4: SM-POGR-BR | F4: SM-OEPR-BR | G4: SM-NOPR-BR | H4: SM-TRIM-BR | I4: SM-CHAP-BR | J4: SM-CAMP-BR | K4: SM-PASSO-BR | L4: SM-CAMGR-BR | M4: SM-RONDON-BR | N4: SM-RIOVERDE-BR | O4: SM-MOGIANA-BR | P4: SM-IJUI-BR | Q4: BO-SAOP-BR | R4: SB-GTRIM-BR | S4: SB-GSORR-BR | T4: SB-GSORO-BR | U4: SB-GROND-BR | V4: SB-GRIVE-BR | W4: SB-GPOGR-BR | X4: SB-GPAFU-BR | Y4: SB-GOEPR-BR | Z4: SB-GNOPR-BR | AA4: SB-GMOGI-BR | AB4: SB-GIJUI-BR | AC4: SB-GBARR-BR | AD4: SB-GBASL-BR | AE4: SB-WPAFU-BR | AF4: SB-WSORO-BR | AG4: SB-WSORR-BR | AH4: LEN-CACR-BR | AI4: LEN-CASS-BR | AJ4: LEN-ITRM-BR | AK4: LEN-NOGS-BR | AL4: LEN-ROND-BR | AM4: LEN-WBHAI-BR | AN4: LEAN-CASS-BR | AO4: LEN-WBATD-BR | AP4: LEAN-CCDI-BR | AQ4: LEAN-CCRS-BR | AR4: LEAN-ITRM-BR | AS4: LEAN-NOGS-BR | AT4: LEAN-PANTL-BR | AU4: LEAN-PARA-BR | AV4: LEAN-RGND-BR | AW4: LEAN-RGNDS-BR | AX4: SB-WRIVE-BR | AY4: LEAN-WOBHS-BR | AZ4: LEAN-RNDPLS-BR | BA4: SB-WROND-BR | BB4: SB-WPOGR-BR | BC4: SB-WOEPR-BR | BD4: SB-WNOPR-BR | BE4: SB-WMOGI-BR | BF4: SB-WTRIM-BR | BG4: SB-WIJUI-BR | BH4: SB-WBARR-BR | BI4: SB-GRCNR-BR | BJ4: SB-WBRCN-BR | BK4: SB-GDCGR-BR | BL4: SB-GDUMS-BR | BM4: SB-GCHAMS-BR | BN4: SB-GMRMS-BR
A5: SM-OEPR-BR | C5: =YEAR(D5)&MONTH(D5) -> 20264 | D5: 46140 | X5: 114.48 | Y5: 109.89 | AB5: 114.59 | AE5: 119.41 | BC5: 117.98 | BG5: 118.86
A6: SM-NOPR-BR | C6: =YEAR(D6)&MONTH(D6) -> 20264 | D6: 46139 | E6: 1892.51 | F6: 1842.05 | G6: 1826.98 | H6: 1743.75 | I6: 1746.04 | J6: 1713.32 | K6: 1700.51 | L6: 1649.97 | M6: 1616.05 | N6: 1597.81 | O6: 1705.37 | P6: 1733.06 | Q6: 6707.09 | R6: 108.04 | S6: 99.73 | T6: 111.54 | V6: 106.78 | W6: 112.94 | X6: 113.62 | Y6: 109.73 | Z6: 110.8 | AA6: 109.23 | AB6: 114.12 | AE6: 119.27 | AF6: 113.81 | AG6: 102.08 | AI6: 10 | AL6: 30 | AN6: 4512.15 | AO6: 45 | AP6: 4419.24 | AQ6: 4478.38 | AR6: 4346.18 | AS6: 4233.56 | AT6: 4475.84 | AU6: 4420.19 | AW6: 4386.82 | AX6: 112.69 | AY6: 4462.95 | AZ6: 4571.76 | BA6: 102.28 | BB6: 122.22 | BC6: 117.02 | BD6: 119.07 | BE6: 111.81 | BF6: 112.9 | BG6: 119.68 | BH6: 112.87 | BI6: 116.8 | BJ6: 123.52 | BK6: 104.17 | BL6: 103.93 | BN6: 104.34
A7: SM-TRIM-BR | C7: =YEAR(D7)&MONTH(D7) -> 20264 | D7: 46136 | E7: 1877.62 | F7: 1842.05 | G7: 1826.98 | H7: 1742.59 | I7: 1746.04 | J7: 1713.32 | K7: 1700.51 | L7: 1679.03 | M7: 1608.43 | N7: 1618.02 | O7: 1709.36 | P7: 1761.23 | Q7: 6792.54 | R7: 107.32 | S7: 99.67 | T7: 110.98 | V7: 106.7 | W7: 111.94 | X7: 113.73 | Y7: 109.75 | Z7: 110 | AA7: 109.24 | AB7: 114.12 | AE7: 119.27 | AF7: 114.45 | AG7: 101.6 | AI7: 10 | AL7: 30 | AN7: 4482.93 | AO7: 37.5 | AP7: 4424.54 | AQ7: 4478.38 | AR7: 4367.17 | AT7: 4519.48 | AU7: 4349 | AW7: 4371.87 | AX7: 112.6 | AY7: 4432.59 | AZ7: 4571.76 | BA7: 102.05 | BB7: 121.85 | BC7: 117.82 | BD7: 118.46 | BE7: 112.69 | BF7: 111.03 | BG7: 119.48 | BH7: 112.33 | BI7: 116.8 | BJ7: 123.52 | BK7: 104.17 | BL7: 103.93 | BN7: 104.34
A8: SM-CHAP-BR | C8: =YEAR(D8)&MONTH(D8) -> 20264 | D8: 46135 | E8: 1875.97 | F8: 1842.05 | G8: 1826.98 | H8: 1745.06 | I8: 1736.16 | J8: 1719.98 | K8: 1700.51 | L8: 1679.03 | M8: 1608.43 | N8: 1620.34 | O8: 1711.03 | P8: 1761.23 | Q8: 6681.2 | R8: 106.61 | S8: 97.06 | T8: 110.86 | V8: 106.52 | W8: 112.34 | X8: 114.73 | Y8: 108.95 | Z8: 110 | AA8: 108.06 | AB8: 115.32 | AE8: 119.7 | AF8: 113.5 | AG8: 100.48 | AI8: 10 | AN8: 4513.54 | AO8: 37.5 | AP8: 4374.45 | AR8: 4367.17 | AS8: 4422.47 | AT8: 4534.95 | AW8: 4371.87 | AX8: 112.12 | AY8: 4436.24 | BA8: 97.47 | BB8: 121.97 | BC8: 116.5 | BD8: 118.28 | BE8: 111 | BF8: 110.48 | BG8: 120.67 | BH8: 111.33 | BI8: 116.83 | BJ8: 123.5 | BK8: 103.17 | BL8: 103.43 | BN8: 103.34
A9: SM-CAMP-BR | C9: =YEAR(D9)&MONTH(D9) -> 20264 | D9: 46134 | E9: 1882.58 | F9: 1842.05 | G9: 1826.98 | I9: 1759.87 | J9: 1719.98 | K9: 1700.51 | L9: 1679.03 | M9: 1597.05 | N9: 1640.63 | O9: 1685.13 | P9: 1761.23 | Q9: 6681.2 | R9: 105.77 | S9: 97.04 | T9: 111.43 | V9: 106.79 | W9: 112.74 | X9: 115.39 | Y9: 109.73 | Z9: 110.7 | AA9: 107.58 | AB9: 115.52 | AE9: 120.13 | AF9: 114.15 | AG9: 100.98 | AI9: 12.5 | AN9: 4525.95 | AO9: 30 | AP9: 4374.45 | AR9: 4391.16 | AS9: 4422.47 | AT9: 4458.7 | AU9: 4407.29 | AW9: 4371.87 | AX9: 111.81 | AY9: 4428.61 | BA9: 97.46 | BB9: 121.62 | BC9: 116.56 | BD9: 118.33 | BE9: 110.79 | BF9: 108.12 | BG9: 120.67 | BH9: 111.33 | BI9: 116.68 | BJ9: 123.48 | BK9: 104.17 | BL9: 103.93 | BN9: 104.34
A10: SM-PASSO-BR | C10: =YEAR(D10)&MONTH(D10) -> 20264 | D10: 46132 | E10: 1851.69 | F10: 1811.97 | G10: 1810.69 | I10: 1757.87 | J10: 1725.88 | K10: 1680.51 | L10: 1655.06 | M10: 1610.26 | N10: 1641.03 | O10: 1680.38 | P10: 1749.99 | Q10: 6679.37 | R10: 105.09 | S10: 95.99 | T10: 110.97 | V10: 106.78 | W10: 111.94 | X10: 115.84 | Y10: 108.99 | Z10: 109.7 | AA10: 106.3 | AB10: 116.12 | AE10: 120.41 | AF10: 114.53 | AG10: 100.42 | AI10: 30 | AN10: 4461.42 | AO10: 30 | AP10: 4336.67 | AQ10: 4312.84 | AR10: 4445.82 | AS10: 4478.13 | AT10: 4422.69 | AU10: 4407.29 | AX10: 111.75 | AY10: 4420.6 | AZ10: 4452.83 | BA10: 94.13 | BB10: 121.67 | BC10: 116.16 | BD10: 117.94 | BE10: 110.68 | BF10: 109.15 | BG10: 120.67 | BH10: 112.23 | BI10: 116.68 | BJ10: 123.44 | BK10: 103.17 | BL10: 103.43 | BN10: 103.34
A11: SM-CAMGR-BR | C11: =YEAR(D11)&MONTH(D11) -> 20264 | D11: 46129 | E11: 1849.21 | F11: 1811.97 | G11: 1814.02 | I11: 1757.87 | J11: 1725.88 | K11: 1680.51 | L11: 1681.83 | M11: 1612.08 | N11: 1643.95 | O11: 1680.26 | P11: 1749.99 | Q11: 6812.71 | R11: 106.5 | S11: 95.85 | T11: 110.96 | V11: 106.99 | W11: 112.14 | X11: 116.73 | Y11: 109.44 | Z11: 109.9 | AA11: 106.94 | AB11: 117.02 | AE11: 120.69 | AF11: 114.53 | AG11: 100.42 | AI11: 30 | AN11: 4485.28 | AO11: 30 | AP11: 4336.67 | AQ11: 4312.84 | AR11: 4504.06 | AS11: 4508.17 | AT11: 4371.48 | AU11: 4407.29 | AV11: 30 | AW11: 4399.48 | AX11: 110.98 | AY11: 4381.58 | AZ11: 4518.61 | BA11: 96.31 | BB11: 121.86 | BC11: 115.5 | BD11: 118.45 | BE11: 110.85 | BF11: 109.02 | BG11: 120.87 | BH11: 112 | BI11: 116.68 | BJ11: 123.38 | BK11: 103.17 | BL11: 104.18 | BN11: 103.34
A12: SM-RONDON-BR | C12: =YEAR(D12)&MONTH(D12) -> 20264 | D12: 46128 | E12: 1849.21 | F12: 1803.76 | G12: 1814.02 | H12: 1746.11 | I12: 1749.97 | J12: 1725.88 | K12: 1718.44 | L12: 1654.08 | M12: 1638.41 | N12: 1643.95 | O12: 1678.95 | P12: 1757.49 | Q12: 6689.75 | R12: 107.32 | S12: 95.44 | T12: 110.96 | V12: 107.48 | W12: 112.14 | X12: 117.39 | Y12: 110.03 | Z12: 109.9 | AA12: 107.41 | AB12: 117.91 | AE12: 121.12 | AF12: 114.07 | AG12: 100.04 | AI12: 30 | AN12: 4511 | AO12: 30 | AP12: 4445.63 | AQ12: 4312.84 | AR12: 4504.06 | AS12: 4559.6 | AT12: 4371.48 | AU12: 4407.29 | AW12: 4406.76 | AX12: 110.41 | AY12: 4385.46 | AZ12: 4518.61 | BA12: 102.83 | BB12: 121.93 | BC12: 116 | BD12: 117.92 | BE12: 111.07 | BF12: 108.74 | BG12: 122.06 | BH12: 111.33 | BI12: 116.8 | BJ12: 123.34 | BK12: 104.17 | BL12: 104.93 | BN12: 104.34
A13: SM-RIOVERDE-BR | C13: =YEAR(D13)&MONTH(D13) -> 20264 | D13: 46127 | E13: 1823.33 | F13: 1770.19 | G13: 1803.46 | H13: 1743.23 | I13: 1761.97 | J13: 1725.88 | K13: 1730.44 | L13: 1654.08 | M13: 1604.23 | N13: 1642.99 | O13: 1678.95 | P13: 1762.49 | Q13: 6781.2 | R13: 106.47 | S13: 95.42 | T13: 111.35 | V13: 107.47 | W13: 112.14 | X13: 117.39 | Y13: 110.5 | Z13: 109.9 | AA13: 107.12 | AB13: 118.29 | AE13: 121.9 | AF13: 114.05 | AG13: 100.03 | AN13: 4522.27 | AO13: 30 | AP13: 4474.58 | AQ13: 4312.84 | AR13: 4485.72 | AS13: 4486.35 | AT13: 4371.48 | AU13: 4456.2 | AW13: 4373.88 | AX13: 109.5 | AY13: 4407.2 | AZ13: 4518.61 | BA13: 106.91 | BB13: 121.76 | BC13: 116.3 | BD13: 119.13 | BE13: 110.45 | BF13: 107.94 | BG13: 122.76 | BH13: 111.33 | BI13: 117.18 | BJ13: 123.34 | BK13: 105.17 | BL13: 105.43 | BN13: 105.34
A14: SM-MOGIANA-BR | C14: =YEAR(D14)&MONTH(D14) -> 20264 | D14: 46126 | E14: 1823.33 | F14: 1770.19 | G14: 1803.46 | H14: 1737.47 | I14: 1756.04 | J14: 1739.07 | K14: 1730.44 | L14: 1682.97 | M14: 1615.63 | N14: 1606.65 | O14: 1709.39 | P14: 1731.03 | Q14: 6981.2 | R14: 106.46 | S14: 95.4 | T14: 111.7 | V14: 107.41 | W14: 113.54 | X14: 118 | Y14: 111.05 | Z14: 111.7 | AA14: 107.18 | AB14: 119.41 | AE14: 122.11 | AF14: 113.53 | AG14: 100.03 | AN14: 4540.98 | AO14: 30 | AP14: 4478.21 | AR14: 4371.87 | AS14: 4514.31 | AT14: 4401.5 | AU14: 4456.2 | AV14: 30 | AW14: 4388.41 | AX14: 110.92 | AY14: 4407.2 | AZ14: 4518.61 | BA14: 106.16 | BB14: 121.59 | BC14: 116.37 | BD14: 118.31 | BE14: 110.42 | BF14: 109.24 | BG14: 124.56 | BH14: 112 | BI14: 117.93 | BJ14: 123.12 | BK14: 104.17 | BL14: 104.93 | BN14: 104.34
A15: SM-IJUI-BR | C15: =YEAR(D15)&MONTH(D15) -> 20264 | D15: 46125 | E15: 1850.09 | F15: 1774.28 | G15: 1797.88 | H15: 1716.06 | I15: 1746.04 | J15: 1753.49 | K15: 1718.44 | L15: 1682.97 | M15: 1569.36 | N15: 1588.54 | O15: 1714.59 | P15: 1762.49 | Q15: 7005.9 | R15: 108.37 | S15: 95.88 | T15: 113.34 | V15: 108.17 | W15: 114.34 | X15: 118.56 | Y15: 111.95 | Z15: 112.69 | AA15: 108.49 | AB15: 120.01 | AE15: 122.47 | AF15: 112.48 | AG15: 99.45 | AN15: 4560.76 | AP15: 4436.25 | AQ15: 4424.16 | AR15: 4338.98 | AS15: 4486.61 | AT15: 4439.34 | AU15: 4456.2 | AV15: 30 | AW15: 4411.64 | AX15: 111.08 | AY15: 4414.12 | AZ15: 4475.6 | BA15: 106.14 | BB15: 121.66 | BC15: 116.72 | BD15: 118.45 | BE15: 111.52 | BF15: 110.93 | BG15: 124.56 | BH15: 112.67 | BI15: 118.8 | BJ15: 123.1 | BK15: 106.17 | BL15: 106.43 | BN15: 106.33
A16: BO-SAOP-BR | C16: =YEAR(D16)&MONTH(D16) -> 20264 | D16: 46122 | E16: 1887.55 | F16: 1842.05 | G16: 1830.7 | H16: 1696.3 | I16: 1736.16 | J16: 1786.55 | K16: 1726.39 | L16: 1640.54 | M16: 1556.03 | N16: 1589.09 | O16: 1740.47 | P16: 1767.46 | Q16: 7005.9 | R16: 108.37 | S16: 96.57 | T16: 113.86 | V16: 108.34 | W16: 114.54 | X16: 118.45 | Y16: 111.95 | Z16: 112.89 | AA16: 108.55 | AB16: 119.41 | AE16: 122.61 | AF16: 113.69 | AG16: 102.1 | AN16: 4545.22 | AP16: 4436.25 | AQ16: 4416.3 | AR16: 4338.98 | AS16: 4436.99 | AT16: 4498.37 | AU16: 4407.29 | AV16: 30 | AW16: 4396.41 | AX16: 111.02 | AY16: 4423.99 | AZ16: 4431.74 | BA16: 107.73 | BB16: 122.36 | BC16: 116.72 | BD16: 118.88 | BE16: 112.02 | BF16: 111.77 | BG16: 124.16 | BH16: 112.67 | BI16: 118.8 | BJ16: 123.64 | BK16: 106.17 | BL16: 106.43 | BN16: 106.33
A17: SB-GTRIM-BR | C17: =YEAR(D17)&MONTH(D17) -> 20264 | D17: 46121 | E17: 1869.35 | F17: 1842.05 | G17: 1814.15 | H17: 1696.3 | I17: 1736.16 | J17: 1786.55 | K17: 1706.39 | L17: 1640.54 | M17: 1556.31 | N17: 1609.88 | O17: 1706.78 | P17: 1742.46 | Q17: 7005.9 | R17: 109.2 | S17: 97 | T17: 114.08 | V17: 108.62 | W17: 114.42 | X17: 118.56 | Y17: 111.95 | Z17: 112.89 | AA17: 108.98 | AB17: 119.41 | AE17: 122.89 | AF17: 112.5 | AG17: 102.36 | AN17: 4557.09 | AP17: 4440 | AQ17: 4416.3 | AR17: 4338.98 | AS17: 4436.99 | AT17: 4498.37 | AU17: 4407.29 | AV17: 30 | AW17: 4396.41 | AX17: 109.65 | AY17: 4423.99 | AZ17: 4431.74 | BA17: 107.1 | BB17: 122.87 | BC17: 117.15 | BD17: 120.15 | BE17: 111.83 | BF17: 111.8 | BG17: 124.16 | BH17: 113.2 | BI17: 118.8 | BJ17: 123.62 | BK17: 106.17 | BL17: 106.43 | BN17: 106.33
A18: SB-GSORR-BR | C18: =YEAR(D18)&MONTH(D18) -> 20264 | D18: 46120 | E18: 1866.04 | F18: 1842.05 | G18: 1822.98 | I18: 1736.16 | J18: 1786.55 | K18: 1706.39 | L18: 1640.54 | M18: 1543.28 | N18: 1609.88 | O18: 1757.94 | P18: 1742.46 | Q18: 7112.31 | R18: 109.86 | S18: 96.9 | T18: 113.93 | V18: 108.76 | W18: 114.67 | X18: 118.78 | Y18: 111.18 | Z18: 112.69 | AA18: 109.88 | AB18: 119.71 | AE18: 123.11 | AF18: 113.37 | AG18: 102.6 | AI18: 30 | AN18: 4587.39 | AP18: 4403 | AQ18: 4416.3 | AR18: 4339.82 | AS18: 4426.3 | AT18: 4498.37 | AU18: 4394.13 | AV18: 30 | AW18: 4412.5 | AX18: 110.33 | AY18: 4409.82 | AZ18: 4431.74 | BA18: 105.48 | BB18: 123.57 | BC18: 116.27 | BD18: 119.04 | BE18: 112.16 | BF18: 112.45 | BG18: 124.16 | BH18: 112.87 | BI18: 119.17 | BJ18: 123.4 | BK18: 106.17 | BL18: 106.43 | BN18: 106.33
A19: SB-GSORO-BR | C19: =YEAR(D19)&MONTH(D19) -> 20264 | D19: 46119 | E19: 1872.66 | F19: 1855.61 | G19: 1822.98 | I19: 1753.94 | J19: 1772.71 | K19: 1722.39 | L19: 1634.46 | M19: 1567.94 | N19: 1618.28 | O19: 1743.11 | P19: 1758.7 | Q19: 7089.24 | R19: 109.86 | S19: 97.38 | T19: 114.01 | V19: 109.17 | W19: 115.42 | X19: 119.44 | Y19: 112.95 | Z19: 113.69 | AA19: 109.88 | AB19: 120.31 | AE19: 123.39 | AF19: 115.25 | AG19: 103.01 | AI19: 30 | AN19: 4588.66 | AP19: 4378.75 | AQ19: 4416.3 | AR19: 4330.67 | AS19: 4426.3 | AT19: 4503.43 | AU19: 4394.13 | AV19: 30 | AW19: 4457.67 | AX19: 109.81 | AY19: 4409.82 | AZ19: 4431.74 | BA19: 105.45 | BB19: 124.21 | BC19: 118.19 | BD19: 120.17 | BE19: 112.99 | BF19: 113.41 | BG19: 124.16 | BH19: 115 | BI19: 119.29 | BJ19: 123.58 | BK19: 106.17 | BL19: 106.43 | BN19: 106.33
A20: SB-GROND-BR | C20: =YEAR(D20)&MONTH(D20) -> 20264 | D20: 46118 | E20: 1872.66 | F20: 1855.61 | G20: 1846.98 | H20: 1691.62 | I20: 1759.92 | J20: 1763.37 | K20: 1726.39 | L20: 1634.46 | M20: 1560.19 | N20: 1601.26 | O20: 1758.03 | P20: 1758.7 | Q20: 7028.69 | R20: 109.6 | S20: 97.49 | T20: 114.01 | V20: 108.99 | W20: 115.42 | X20: 120 | Y20: 112.83 | Z20: 113.69 | AA20: 110 | AB20: 119.9 | AE20: 123.67 | AF20: 115.26 | AG20: 102.57 | AI20: 30 | AN20: 4556.56 | AO20: 30 | AQ20: 4373.39 | AR20: 4341.51 | AS20: 4447.77 | AT20: 4439.32 | AU20: 4394.13 | AV20: 30 | AW20: 4457.53 | AX20: 108.16 | AY20: 4422.98 | AZ20: 4410.3 | BA20: 104.98 | BB20: 125.08 | BC20: 118.3 | BD20: 121.16 | BE20: 113.9 | BF20: 113.22 | BG20: 124.16 | BH20: 115 | BI20: 119.29 | BJ20: 123.56 | BK20: 106.84 | BL20: 106.68 | BN20: 107
A21: SB-GRIVE-BR | C21: =YEAR(D21)&MONTH(D21) -> 20264 | D21: 46114 | E21: 1870.93 | F21: 1855.61 | G21: 1846.98 | H21: 1695.45 | I21: 1759.92 | J21: 1770.04 | K21: 1720.99 | L21: 1613.64 | M21: 1543.9 | N21: 1601.26 | O21: 1762.03 | P21: 1754.95 | Q21: 7075.26 | R21: 109.93 | S21: 97.57 | T21: 113.99 | V21: 108.71 | W21: 115.17 | X21: 119.44 | Y21: 112.91 | Z21: 113.69 | AA21: 111.1 | AB21: 119.51 | AE21: 123.11 | AF21: 113.47 | AG21: 102.37 | AI21: 30 | AN21: 4581.1 | AO21: 19 | AR21: 4341.51 | AS21: 4394.64 | AT21: 4513.86 | AU21: 4308.62 | AV21: 30 | AW21: 4481.86 | AX21: 107.7 | AY21: 4442.71 | AZ21: 4486.56 | BA21: 105.51 | BB21: 123.82 | BC21: 118.15 | BD21: 120.18 | BE21: 112.65 | BF21: 112.28 | BG21: 124.32 | BH21: 113.67 | BI21: 119.29 | BJ21: 122.49 | BK21: 106.84 | BL21: 106.68 | BN21: 107
A22: SB-GPOGR-BR | C22: =YEAR(D22)&MONTH(D22) -> 20264 | D22: 46113 | E22: 1859.42 | F22: 1855.61 | G22: 1841.05 | H22: 1706.92 | I22: 1759.92 | J22: 1786.7 | K22: 1726.39 | L22: 1644.46 | M22: 1543.9 | N22: 1612.79 | O22: 1794.02 | P22: 1758.7 | Q22: 7055.26 | R22: 110.76 | S22: 96.85 | T22: 113.4 | V22: 108.34 | W22: 114.67 | X22: 119.84 | Y22: 112.28 | Z22: 112.69 | AA22: 112.05 | AB22: 119.4 | AE22: 122.68 | AF22: 111.95 | AG22: 102.57 | AI22: 30 | AN22: 4557.25 | AO22: 19 | AP22: 4378.75 | AQ22: 4399.7 | AR22: 4301.03 | AS22: 4412.35 | AT22: 4475.47 | AV22: 30 | AW22: 4518.88 | AX22: 107.68 | AY22: 4442.71 | AZ22: 4457.89 | BA22: 103.65 | BB22: 124.28 | BC22: 117.64 | BD22: 121.02 | BE22: 113.23 | BF22: 113.11 | BG22: 124.16 | BH22: 113.67 | BI22: 119.29 | BJ22: 122.47 | BK22: 106.5 | BL22: 105.93 | BN22: 106.67
A23: SB-GPAFU-BR | C23: =YEAR(D23)&MONTH(D23) -> 20263 | D23: 46112 | E23: 1852.8 | F23: 1878.15 | G23: 1841.05 | H23: 1741.33 | I23: 1767.83 | J23: 1807.57 | K23: 1726.39 | L23: 1686.77 | M23: 1582.1 | N23: 1624.85 | O23: 1814.98 | P23: 1758.7 | Q23: 7055.26 | R23: 110.76 | S23: 97.51 | T23: 114.29 | V23: 110.51 | W23: 116.17 | X23: 118.94 | Y23: 113.83 | Z23: 114.59 | AA23: 111.72 | AB23: 119.56 | AE23: 122.68 | AF23: 113.99 | AG23: 102.63 | AI23: 25 | AN23: 4478.72 | AO23: 15.33 | AP23: 4378.75 | AQ23: 4399.7 | AR23: 4301.03 | AS23: 4405.6 | AT23: 4453.12 | AW23: 4554.03 | AX23: 105.59 | AY23: 4366.3 | AZ23: 4462.95 | BA23: 104.4 | BB23: 125.23 | BC23: 118.51 | BD23: 120.01 | BE23: 113.7 | BF23: 114.24 | BG23: 124.16 | BH23: 116.17 | BI23: 119.17 | BJ23: 122.53 | BK23: 107.17 | BL23: 108.4 | BN23: 107.33
A24: SB-GOEPR-BR | C24: =YEAR(D24)&MONTH(D24) -> 20263 | D24: 46111 | E24: 1846.19 | F24: 1878.15 | G24: 1846.98 | H24: 1741.33 | I24: 1783.83 | J24: 1809.08 | K24: 1726.39 | L24: 1686.77 | M24: 1584.36 | N24: 1625.62 | O24: 1809.99 | P24: 1771.2 | Q24: 7055.51 | R24: 110.11 | S24: 98.69 | T24: 114.36 | V24: 110.3 | W24: 116.42 | X24: 118.39 | Y24: 114.42 | Z24: 114.79 | AA24: 111.58 | AB24: 118.86 | AE24: 122.68 | AF24: 115.11 | AG24: 102.54 | AI24: 25 | AN24: 4478.72 | AO24: 8 | AP24: 4378.75 | AQ24: 4399.7 | AR24: 4291.42 | AS24: 4375.24 | AT24: 4414.24 | AU24: 4460.42 | AW24: 4473.07 | AX24: 107.48 | AY24: 4289.9 | AZ24: 4399.7 | BA24: 103.49 | BB24: 124.66 | BC24: 118.5 | BD24: 120.65 | BE24: 114.39 | BF24: 112.87 | BG24: 124.16 | BH24: 116.33 | BI24: 119.17 | BJ24: 122.51 | BK24: 107.17 | BL24: 108.4 | BN24: 107.33
A25: SB-GNOPR-BR | C25: =YEAR(D25)&MONTH(D25) -> 20263 | D25: 46108 | E25: 1859.42 | F25: 1878.15 | G25: 1846.98 | H25: 1748.66 | I25: 1781.83 | J25: 1824.87 | K25: 1720.99 | L25: 1710.67 | M25: 1574.67 | N25: 1639.07 | O25: 1782.51 | P25: 1774.95 | Q25: 7118.4 | R25: 110.11 | S25: 98.64 | T25: 115.7 | V25: 110.21 | W25: 118.17 | X25: 117.72 | Y25: 116.81 | Z25: 116.69 | AA25: 111.66 | AB25: 118.52 | AE25: 122.68 | AF25: 114.94 | AG25: 103.26 | AI25: 15 | AN25: 4439.84 | AP25: 4378.75 | AQ25: 4399.7 | AR25: 4291.42 | AS25: 4392.11 | AT25: 4367.82 | AU25: 4460.42 | AW25: 4473.07 | AY25: 4289.9 | AZ25: 4399.7 | BA25: 102.4 | BB25: 126.39 | BC25: 120.07 | BD25: 121.68 | BE25: 114.33 | BF25: 113.75 | BG25: 125.32 | BH25: 115.33 | BI25: 118.54 | BJ25: 121.86 | BK25: 110.16 | BL25: 110.4 | BN25: 110.33
A26: SB-GMOGI-BR | C26: =YEAR(D26)&MONTH(D26) -> 20263 | D26: 46107 | E26: 1856.11 | F26: 1881.74 | G26: 1846.98 | H26: 1742.33 | I26: 1775.9 | J26: 1824.12 | K26: 1717.7 | L26: 1716.09 | M26: 1568.63 | N26: 1640.62 | O26: 1786.26 | P26: 1774.95 | Q26: 6907.49 | R26: 110.11 | S26: 98.83 | T26: 115.87 | V26: 109.94 | W26: 117.67 | X26: 118.05 | Y26: 114.77 | Z26: 116.28 | AA26: 111.65 | AB26: 117.96 | AE26: 123.49 | AF26: 115.97 | AG26: 103.07 | AI26: 15 | AN26: 4383.47 | AP26: 4378.75 | AQ26: 4399.7 | AR26: 4291.21 | AS26: 4392.11 | AT26: 4367.82 | AU26: 4460.42 | AW26: 4473.07 | AY26: 4289.9 | AZ26: 4399.7 | BA26: 102.04 | BB26: 126.01 | BC26: 119.66 | BD26: 121.14 | BE26: 114.79 | BF26: 113.36 | BG26: 125.82 | BH26: 116 | BI26: 118.54 | BJ26: 121.64 | BK26: 109.17 | BL26: 108.73 | BN26: 109.33
A27: SB-GIJUI-BR | C27: =YEAR(D27)&MONTH(D27) -> 20263 | D27: 46106 | E27: 1862.73 | F27: 1881.74 | G27: 1846.98 | H27: 1776.42 | I27: 1775.9 | J27: 1824.12 | K27: 1744.42 | L27: 1713.84 | M27: 1571.66 | N27: 1659.25 | O27: 1797 | P27: 1769.1 | Q27: 6845.12 | R27: 108.37 | S27: 98.81 | T27: 114.76 | V27: 109.79 | W27: 116.92 | X27: 117.17 | Y27: 114.55 | Z27: 115.49 | AA27: 110.88 | AB27: 117.74 | AE27: 122.25 | AF27: 115.93 | AG27: 102.21 | AI27: 15 | AN27: 4398.84 | AP27: 4400.17 | AQ27: 4399.7 | AR27: 4288.76 | AS27: 4351.63 | AT27: 4367.82 | AU27: 4460.42 | AW27: 4473.07 | AY27: 4289.9 | AZ27: 4427.53 | BA27: 99.75 | BB27: 125.6 | BC27: 118.27 | BD27: 120.06 | BE27: 113.54 | BF27: 111.38 | BG27: 125.36 | BH27: 116 | BI27: 118.54 | BJ27: 121.62 | BK27: 108.17 | BL27: 108.07 | BN27: 108.33
A28: SB-GBARR-BR | C28: =YEAR(D28)&MONTH(D28) -> 20263 | D28: 46105 | E28: 1879.28 | F28: 1881.74 | G28: 1846.98 | H28: 1772.92 | I28: 1756.14 | J28: 1789.6 | K28: 1744.42 | L28: 1721.57 | M28: 1570.1 | N28: 1688.48 | O28: 1769.01 | P28: 1775.71 | Q28: 6953.38 | R28: 108.37 | S28: 97.23 | T28: 115.76 | V28: 109.42 | W28: 116.92 | X28: 117.74 | Y28: 114.02 | Z28: 115.69 | AA28: 110.42 | AB28: 118.17 | AE28: 122.39 | AF28: 116.36 | AG28: 101.92 | AN28: 4404.57 | AO28: 30 | AP28: 4400.17 | AQ28: 4399.7 | AR28: 4297.99 | AS28: 4346.57 | AT28: 4450.63 | AU28: 4470.82 | AW28: 4432.59 | AZ28: 4424.9 | BA28: 96.67 | BB28: 124.52 | BC28: 117.85 | BD28: 120.14 | BE28: 114.15 | BF28: 111.88 | BG28: 125.76 | BH28: 115.67 | BI28: 119.39 | BJ28: 121.6 | BK28: 108.17 | BL28: 108.07 | BN28: 108.33
A29: SB-GBASL-BR | C29: =YEAR(D29)&MONTH(D29) -> 20263 | D29: 46104 | E29: 1902.44 | F29: 1881.74 | G29: 1832.98 | I29: 1760.28 | J29: 1772.87 | K29: 1740.42 | L29: 1718.1 | N29: 1688.48 | O29: 1785.21 | P29: 1770.71 | Q29: 6732.24 | R29: 108.37 | S29: 97.22 | T29: 115.63 | V29: 110.14 | W29: 117.67 | X29: 117.67 | Y29: 115.26 | Z29: 116.29 | AA29: 110.17 | AB29: 118.32 | AE29: 122.39 | AF29: 116.74 | AG29: 101.92 | AN29: 4404.57 | AO29: 30 | AP29: 4400.17 | AQ29: 4399.7 | AR29: 4290.91 | AS29: 4388.06 | AT29: 4395.52 | AU29: 4416.78 | AW29: 4283.84 | AY29: 4245.37 | AZ29: 4380.98 | BA29: 100.14 | BB29: 124.09 | BC29: 118.19 | BD29: 119.61 | BE29: 111.07 | BF29: 111.88 | BG29: 125.76 | BH29: 115.67 | BI29: 118.54 | BJ29: 121.58 | BK29: 108.17 | BL29: 108.07 | BN29: 108.33
A30: SB-WPAFU-BR | C30: =YEAR(D30)&MONTH(D30) -> 20263 | D30: 46101 | E30: 1869.5 | F30: 1845.81 | G30: 1807.29 | H30: 1700.93 | I30: 1736.64 | J30: 1789.34 | K30: 1740.42 | L30: 1705.75 | N30: 1719.6 | O30: 1785.21 | P30: 1775.71 | Q30: 6857.24 | R30: 108.78 | S30: 97.44 | T30: 115.24 | V30: 109.13 | W30: 116.67 | X30: 118.19 | Y30: 114.14 | Z30: 115.69 | AA30: 110.85 | AB30: 118.42 | AE30: 122.82 | AF30: 116.74 | AG30: 100.37 | AI30: 30 | AN30: 4434.27 | AO30: 30 | AP30: 4400.17 | AQ30: 4399.7 | AR30: 4290.91 | AS30: 4388.06 | AT30: 4375.8 | AU30: 4380.98 | AW30: 4251.87 | AY30: 4245.37 | AZ30: 4380.98 | BA30: 100.74 | BB30: 124.53 | BC30: 119.1 | BD30: 120.88 | BE30: 111.4 | BF30: 111.09 | BG30: 126.16 | BH30: 113.33 | BI30: 118.54 | BJ30: 121.72 | BK30: 108.17 | BL30: 108.07 | BN30: 108.23
A31: SB-WSORO-BR | C31: =YEAR(D31)&MONTH(D31) -> 20263 | D31: 46100 | E31: 1875.94 | F31: 1833.01 | G31: 1791.16 | H31: 1712.16 | I31: 1729.07 | J31: 1780.15 | K31: 1700.38 | L31: 1705.6 | N31: 1715.3 | O31: 1775.11 | P31: 1753.16 | Q31: 6706.8 | R31: 108.7 | S31: 96.03 | T31: 114.45 | V31: 107.62 | W31: 115.42 | X31: 117.33 | Y31: 113.88 | Z31: 114.68 | AA31: 110.03 | AB31: 117.81 | AE31: 122.38 | AF31: 116.06 | AG31: 99.49 | AI31: 30 | AN31: 4406.91 | AO31: 30 | AP31: 4400.17 | AR31: 4291.73 | AS31: 4391.26 | AT31: 4376.25 | AU31: 4381.81 | AW31: 4252.68 | AY31: 4246.18 | AZ31: 4381.81 | BA31: 100.39 | BB31: 123.33 | BC31: 118.75 | BD31: 120.29 | BE31: 111.38 | BF31: 111.08 | BG31: 125.55 | BH31: 114.33 | BI31: 118.66 | BJ31: 121.67 | BK31: 107.17 | BL31: 107.4 | BN31: 107.33
A32: SB-WSORR-BR | C32: =YEAR(D32)&MONTH(D32) -> 20263 | D32: 46099 | E32: 1836.23 | F32: 1841.99 | G32: 1781.28 | H32: 1718.15 | I32: 1740.92 | J32: 1780.15 | K32: 1700.38 | L32: 1705.6 | N32: 1671.95 | O32: 1798.09 | P32: 1753.16 | Q32: 6656.9 | R32: 105.72 | S32: 94.74 | T32: 113.74 | V32: 107.11 | W32: 114.17 | X32: 117.33 | Y32: 112.95 | Z32: 113.69 | AA32: 107.79 | AB32: 118.01 | AE32: 122.38 | AF32: 114.02 | AG32: 99.06 | AI32: 30 | AN32: 4406.91 | AO32: 30 | AP32: 4412 | AQ32: 4448.62 | AR32: 4291.73 | AS32: 4362.58 | AT32: 4376.25 | AU32: 4381.81 | AW32: 4252.68 | AY32: 4246.18 | AZ32: 4381.81 | BA32: 100.37 | BB32: 123.1 | BC32: 116.27 | BD32: 118.69 | BE32: 109.04 | BF32: 108.04 | BG32: 125.55 | BH32: 114.33 | BI32: 118.66 | BJ32: 121.65 | BK32: 106.17 | BL32: 106.4 | BN32: 106.33
A33: LEN-CACR-BR | C33: =YEAR(D33)&MONTH(D33) -> 20263 | D33: 46098 | E33: 1832.92 | F33: 1831.28 | G33: 1775.28 | H33: 1736.11 | I33: 1744.87 | J33: 1788.49 | K33: 1712.38 | L33: 1705.6 | N33: 1674.95 | O33: 1808.09 | P33: 1753.16 | Q33: 6706.9 | R33: 105.64 | S33: 94.25 | T33: 113.96 | V33: 108.78 | W33: 114.17 | X33: 118.29 | Y33: 113.35 | Z33: 113.88 | AA33: 109.51 | AB33: 118.66 | AE33: 123.52 | AF33: 112.81 | AG33: 98.4 | AI33: 30 | AN33: 4373.04 | AO33: 30 | AP33: 4412 | AQ33: 4448.62 | AR33: 4212.27 | AS33: 4401.04 | AT33: 4323.17 | AU33: 4357.42 | AW33: 4252.68 | AX33: 110.25 | AY33: 4246.18 | AZ33: 4256.3 | BA33: 96.03 | BB33: 122.18 | BC33: 116.95 | BD33: 118.74 | BE33: 108.12 | BF33: 107.68 | BG33: 125.55 | BH33: 114.33 | BI33: 119.64 | BJ33: 121.86 | BK33: 106.17 | BL33: 106.4 | BN33: 106.33
A34: LEN-CASS-BR | C34: =YEAR(D34)&MONTH(D34) -> 20263 | D34: 46097 | E34: 1856.08 | F34: 1841.99 | G34: 1775.28 | H34: 1723.83 | I34: 1764.87 | J34: 1803.86 | K34: 1720.38 | L34: 1725.96 | N34: 1637.92 | O34: 1790.07 | P34: 1766.89 | Q34: 6706.9 | R34: 106.83 | S34: 96.78 | T34: 114.74 | V34: 110.89 | W34: 115.92 | X34: 119.22 | Y34: 114.74 | Z34: 115.08 | AA34: 109.93 | AB34: 118.86 | AE34: 123.36 | AF34: 113.96 | AG34: 100.31 | AI34: 30 | AN34: 4373.04 | AP34: 4365 | AQ34: 4448.62 | AR34: 4212.65 | AS34: 4359.21 | AT34: 4352.46 | AU34: 4304.93 | AV34: 36.67 | AW34: 4276.48 | AX34: 110.25 | AY34: 4322.28 | AZ34: 4256.3 | BA34: 102.03 | BB34: 122.38 | BC34: 118.92 | BD34: 120.11 | BE34: 108.97 | BF34: 108.8 | BG34: 125.55 | BH34: 114.33 | BI34: 120.16 | BJ34: 121.84 | BK34: 107.17 | BL34: 107.73 | BN34: 107.33
A35: LEN-ITRM-BR | C35: =YEAR(D35)&MONTH(D35) -> 20263 | D35: 46094 | E35: 1864.33 | F35: 1833.01 | G35: 1775.28 | H35: 1723.53 | I35: 1746.9 | J35: 1808.86 | K35: 1720.33 | L35: 1725.96 | N35: 1652.34 | O35: 1810.07 | P35: 1771.86 | Q35: 6631.9 | R35: 109.03 | S35: 96.89 | T35: 115.99 | V35: 110.92 | W35: 117.17 | X35: 119.77 | Y35: 115.75 | Z35: 116.68 | AA35: 110.88 | AB35: 119.66 | AE35: 124.28 | AF35: 114.94 | AG35: 102.29 | AN35: 4365.11 | AP35: 4365 | AQ35: 4448.62 | AR35: 4212.65 | AS35: 4353.09 | AT35: 4352.46 | AU35: 4321.92 | AV35: 36.67 | AW35: 4279.14 | AX35: 109.13 | AY35: 4322.28 | AZ35: 4256.3 | BA35: 101.96 | BB35: 124.06 | BC35: 119.15 | BD35: 121.02 | BE35: 111.68 | BF35: 112.13 | BG35: 126.35 | BH35: 116 | BI35: 120.16 | BJ35: 122.57 | BK35: 109.16 | BL35: 108.73 | BN35: 109.33
A36: LEN-NOGS-BR | C36: =YEAR(D36)&MONTH(D36) -> 20263 | D36: 46093 | E36: 1867.64 | F36: 1833.01 | G36: 1781.21 | H36: 1722.61 | I36: 1746.9 | J36: 1785.53 | K36: 1720.33 | L36: 1701.26 | N36: 1650.52 | O36: 1810.07 | P36: 1771.86 | Q36: 6556.9 | R36: 110.02 | S36: 97.16 | T36: 115.63 | V36: 110.77 | W36: 115.67 | X36: 119.33 | Y36: 114.43 | Z36: 115.48 | AA36: 112.03 | AB36: 118.86 | AE36: 123.9 | AF36: 115.61 | AG36: 102.37 | AN36: 4330.19 | AP36: 4365 | AQ36: 4448.62 | AR36: 4212.65 | AS36: 4353.09 | AT36: 4352.46 | AU36: 4310.26 | AV36: 36.67 | AW36: 4279.14 | AX36: 107.03 | AY36: 4322.28 | AZ36: 4256.3 | BA36: 104.35 | BB36: 122.6 | BC36: 119.11 | BD36: 120.8 | BE36: 113.62 | BF36: 112.69 | BG36: 125.95 | BH36: 117 | BI36: 120.16 | BJ36: 122.55 | BK36: 108.5 | BL36: 108.07 | BN36: 108.67
A37: LEN-ROND-BR | C37: =YEAR(D37)&MONTH(D37) -> 20263 | D37: 46092 | E37: 1849.47 | F37: 1833.01 | G37: 1781.21 | H37: 1729.74 | I37: 1750.85 | J37: 1785.53 | K37: 1720.33 | L37: 1701.26 | N37: 1640.25 | O37: 1810.07 | P37: 1771.86 | Q37: 6556.9 | R37: 109.52 | S37: 96.86 | T37: 114.63 | V37: 110.68 | W37: 115.67 | X37: 118.83 | Y37: 113.94 | Z37: 114.68 | AA37: 111.51 | AB37: 118.66 | AE37: 123.26 | AF37: 115.57 | AG37: 100.76 | AN37: 4330.19 | AP37: 4309 | AR37: 4255.79 | AS37: 4353.09 | AT37: 4352.46 | AU37: 4317.57 | AV37: 35 | AW37: 4271.04 | AX37: 110.28 | AY37: 4322.28 | AZ37: 4256.3 | BA37: 104.33 | BB37: 122.6 | BC37: 117.95 | BD37: 120.39 | BE37: 113.59 | BF37: 111.47 | BG37: 126.14 | BH37: 117 | BI37: 120.16 | BJ37: 122.53 | BK37: 107.17 | BL37: 107.4 | BN37: 107.33
A38: LEN-WBHAI-BR | C38: =YEAR(D38)&MONTH(D38) -> 20263 | D38: 46091 | E38: 1872.75 | F38: 1842.1 | G38: 1801.21 | H38: 1729.74 | I38: 1750.85 | J38: 1819.43 | K38: 1724.33 | L38: 1711.14 | N38: 1652.96 | O38: 1826.55 | P38: 1764.36 | Q38: 6581.6 | R38: 109.45 | S38: 97.09 | T38: 114.62 | V38: 110.5 | W38: 116.39 | X38: 118.89 | Y38: 114.01 | Z38: 114.68 | AA38: 111.51 | AB38: 118.96 | AE38: 123.2 | AF38: 115.45 | AG38: 100.79 | AN38: 4283.63 | AP38: 4300 | AR38: 4251.24 | AS38: 4324.26 | AT38: 4327.15 | AU38: 4303.74 | AV38: 35 | AW38: 4271.04 | AX38: 111.23 | AY38: 4322.28 | BA38: 105.22 | BB38: 123.9 | BC38: 118.14 | BD38: 119.15 | BE38: 113.57 | BF38: 111.47 | BG38: 125.74 | BH38: 115.67 | BI38: 119.79 | BJ38: 122.51 | BK38: 107.17 | BL38: 107.4 | BN38: 107.33
A39: LEAN-CASS-BR | C39: =YEAR(D39)&MONTH(D39) -> 20263 | D39: 46090 | E39: 1872.75 | F39: 1842.1 | G39: 1801.21 | H39: 1746.47 | I39: 1750.85 | J39: 1825.6 | K39: 1717.66 | L39: 1729.86 | N39: 1661.7 | O39: 1829.84 | P39: 1754.9 | Q39: 6565.43 | R39: 111.26 | S39: 98.79 | T39: 114.79 | V39: 110.62 | W39: 116.22 | X39: 119.5 | Y39: 115.94 | Z39: 115.28 | AA39: 112.68 | AB39: 118.85 | AE39: 123.66 | AF39: 115.45 | AG39: 102.62 | AN39: 4306.26 | AP39: 4300 | AR39: 4251.24 | AS39: 4324.26 | AT39: 4347.44 | AU39: 4304.88 | AV39: 30 | AW39: 4278.51 | AX39: 111.53 | AY39: 4331.58 | AZ39: 4268.78 | BA39: 105.18 | BB39: 123.5 | BC39: 119.02 | BD39: 120.01 | BE39: 114.47 | BF39: 111.92 | BG39: 126.06 | BH39: 110.6 | BI39: 118.91 | BJ39: 122.49 | BK39: 107.17 | BL39: 107.4 | BN39: 107.33
A40: LEN-WBATD-BR | C40: =YEAR(D40)&MONTH(D40) -> 20263 | D40: 46087 | E40: 1851.24 | F40: 1851.08 | G40: 1811.21 | H40: 1723.05 | I40: 1770.75 | J40: 1825.6 | K40: 1754.18 | L40: 1729.86 | N40: 1665.02 | O40: 1791.45 | P40: 1754.38 | Q40: 6425.19 | R40: 111.66 | S40: 97.01 | T40: 115.68 | V40: 110.45 | W40: 117.22 | X40: 118.22 | Y40: 115.68 | Z40: 116.58 | AA40: 113.73 | AB40: 118.12 | AE40: 123.16 | AF40: 115.16 | AG40: 101.63 | AH40: 30 | AN40: 4317.04 | AP40: 4300 | AQ40: 4355.08 | AR40: 4251.24 | AT40: 4347.44 | AU40: 4301 | AV40: 30 | AW40: 4278.51 | AX40: 111.78 | AY40: 4331.58 | AZ40: 4308.68 | BA40: 105.13 | BB40: 124.12 | BC40: 118.89 | BD40: 120.86 | BE40: 114.47 | BF40: 114.24 | BG40: 125.81 | BH40: 114.17 | BI40: 118.41 | BJ40: 121.84 | BK40: 108.83 | BL40: 108.4 | BN40: 109
A41: LEAN-CCDI-BR | C41: =YEAR(D41)&MONTH(D41) -> 20263 | D41: 46086 | E41: 1846.28 | F41: 1833.28 | G41: 1811.21 | H41: 1687.08 | I41: 1770.75 | J41: 1828.06 | K41: 1746.25 | L41: 1732.33 | N41: 1657.49 | O41: 1768.6 | P41: 1749.37 | Q41: 6445.73 | R41: 111.43 | S41: 96.63 | T41: 112.79 | V41: 109.8 | W41: 115.56 | X41: 117.5 | Y41: 114.08 | Z41: 114.68 | AA41: 112.49 | AB41: 116.92 | AE41: 122.03 | AF41: 114.25 | AG41: 101.22 | AH41: 30 | AN41: 4317.04 | AP41: 4302.86 | AQ41: 4355.08 | AR41: 4251.24 | AS41: 4291.73 | AT41: 4347.44 | AU41: 4301.85 | AV41: 30 | AW41: 4278.51 | AX41: 107.92 | AY41: 4331.52 | AZ41: 4308.68 | BA41: 104.51 | BB41: 122.6 | BC41: 117.63 | BD41: 119.23 | BE41: 113.46 | BF41: 114.45 | BG41: 124.35 | BH41: 113.67 | BI41: 118.29 | BJ41: 121.82 | BK41: 108.17 | BL41: 108.06 | BN41: 108.33
A42: LEAN-CCRS-BR | C42: =YEAR(D42)&MONTH(D42) -> 20263 | D42: 46085 | E42: 1849.59 | F42: 1833.28 | G42: 1811.21 | H42: 1694.32 | I42: 1770.75 | J42: 1828.06 | K42: 1750.25 | L42: 1732.33 | N42: 1660.15 | O42: 1791.45 | P42: 1761.87 | Q42: 6434.75 | R42: 111.93 | S42: 96.87 | T42: 114.73 | V42: 109.85 | W42: 115.89 | X42: 117.17 | Y42: 115.01 | Z42: 115.08 | AA42: 113.66 | AB42: 116.82 | AC42: 110.85 | AE42: 122.24 | AF42: 114.12 | AG42: 101.34 | AH42: 30 | AN42: 4320.58 | AP42: 4300.8 | AQ42: 4361.22 | AS42: 4291.73 | AT42: 4360.96 | AU42: 4301.85 | AW42: 4365.11 | AX42: 108.47 | AY42: 4331.52 | AZ42: 4308.68 | BA42: 102.7 | BB42: 122.07 | BC42: 117.42 | BD42: 118.71 | BE42: 115.3 | BF42: 114.09 | BG42: 124.35 | BH42: 108.72 | BI42: 118.29 | BJ42: 121.4 | BK42: 107.17 | BL42: 107.07 | BN42: 107.33
A43: LEAN-ITRM-BR | C43: =YEAR(D43)&MONTH(D43) -> 20263 | D43: 46084 | E43: 1851.24 | F43: 1833.28 | G43: 1811.21 | H43: 1723.9 | I43: 1770.75 | J43: 1834.72 | K43: 1722.33 | L43: 1739.74 | N43: 1654.65 | O43: 1768.6 | P43: 1759.37 | Q43: 6397.77 | R43: 112.59 | S43: 96.97 | T43: 115.33 | V43: 110.35 | W43: 116.19 | X43: 116.72 | Y43: 114.26 | Z43: 115.88 | AA43: 113.89 | AB43: 116.32 | AC43: 110.56 | AE43: 121.6 | AF43: 114.49 | AG43: 101.08 | AH43: 30 | AN43: 4324.31 | AP43: 4302 | AQ43: 4368.44 | AR43: 4287.51 | AS43: 4291.73 | AT43: 4314.53 | AU43: 4301.85 | AX43: 107.92 | AY43: 4331.52 | AZ43: 4308.68 | BA43: 104.54 | BB43: 122.17 | BC43: 117.11 | BD43: 119.53 | BE43: 115.7 | BF43: 114.56 | BG43: 123.55 | BH43: 113.17 | BI43: 118.29 | BJ43: 121.58 | BK43: 107.83 | BL43: 107.73 | BN43: 108
A44: LEAN-NOGS-BR | C44: =YEAR(D44)&MONTH(D44) -> 20263 | D44: 46083 | E44: 1849.59 | F44: 1833.28 | G44: 1811.21 | H44: 1723.9 | I44: 1758.9 | J44: 1823.28 | K44: 1722.33 | L44: 1716.35 | N44: 1648.4 | O44: 1808.65 | P44: 1759.37 | Q44: 6393.92 | R44: 110.59 | S44: 96.46 | T44: 114.91 | V44: 109.28 | W44: 115.51 | X44: 116.22 | Y44: 113.84 | Z44: 114.68 | AA44: 112.74 | AB44: 116.12 | AC44: 110.17 | AE44: 121.18 | AF44: 113.44 | AG44: 99.07 | AN44: 4315.87 | AP44: 4302 | AQ44: 4381.81 | AR44: 4287.51 | AS44: 4283.05 | AT44: 4261.36 | AU44: 4288.35 | AW44: 4303.87 | AX44: 107.24 | AY44: 4302.35 | BA44: 103.97 | BB44: 121.49 | BC44: 117.05 | BD44: 118.48 | BE44: 115.46 | BF44: 112.35 | BG44: 123.55 | BH44: 107.29 | BI44: 118.29 | BJ44: 121.56 | BK44: 107.17 | BL44: 107.4 | BN44: 107.33
A45: LEAN-PANTL-BR | C45: =YEAR(D45)&MONTH(D45) -> 20262 | D45: 46080 | E45: 1856.71 | F45: 1844.65 | G45: 1782.48 | H45: 1724.52 | I45: 1742.41 | J45: 1824.36 | K45: 1700.06 | L45: 1730.52 | N45: 1669.62 | O45: 1790.35 | P45: 1773.54 | Q45: 6397.57 | R45: 111.46 | S45: 97.72 | T45: 113.83 | V45: 108.89 | W45: 114.54 | X45: 116.29 | Y45: 113.74 | Z45: 113.61 | AA45: 112.96 | AB45: 115.93 | AC45: 110 | AE45: 121.1 | AF45: 113.51 | AG45: 99.93 | AN45: 4296.58 | AP45: 4320 | AQ45: 4376.98 | AR45: 4282.78 | AS45: 4278.33 | AT45: 4256.66 | AU45: 4276.89 | AW45: 4299.13 | AX45: 104.89 | AY45: 4297.61 | AZ45: 4265.26 | BA45: 103.27 | BB45: 122.39 | BC45: 116.82 | BD45: 117.84 | BE45: 115.56 | BF45: 113.35 | BG45: 123.21 | BH45: 112.75 | BI45: 117.76 | BJ45: 121.43 | BK45: 107.18 | BL45: 107.41 | BN45: 107.34
A46: LEAN-PARA-BR | C46: =YEAR(D46)&MONTH(D46) -> 20262 | D46: 46079 | E46: 1864.66 | F46: 1844.65 | G46: 1782.48 | H46: 1709.01 | I46: 1742.41 | J46: 1856.86 | K46: 1700.06 | L46: 1720.65 | N46: 1675.78 | O46: 1803.31 | P46: 1771.05 | Q46: 6437.27 | R46: 111.46 | S46: 96.26 | T46: 113.86 | V46: 108.59 | W46: 115.34 | X46: 116.59 | Y46: 112.68 | Z46: 113.61 | AA46: 112.81 | AB46: 115.93 | AC46: 110 | AE46: 121.31 | AF46: 113.54 | AG46: 99.69 | AN46: 4296.58 | AP46: 4320 | AQ46: 4376.98 | AR46: 4282.78 | AS46: 4298.23 | AT46: 4256.66 | AU46: 4291.42 | AW46: 4299.13 | AX46: 110.89 | AY46: 4326.81 | AZ46: 4265.26 | BA46: 96.21 | BB46: 122.52 | BC46: 116.03 | BD46: 117.53 | BE46: 115.03 | BF46: 113.35 | BG46: 123.21 | BH46: 112.75 | BI46: 117.88 | BJ46: 121.4 | BK46: 105.51 | BL46: 106.08 | BN46: 105.68
A47: LEAN-RGND-BR | C47: =YEAR(D47)&MONTH(D47) -> 20262 | D47: 46078 | E47: 1848.77 | F47: 1844.65 | G47: 1794.98 | H47: 1678.47 | I47: 1752.41 | J47: 1856.86 | K47: 1725.06 | L47: 1730.6 | N47: 1689.18 | O47: 1812.48 | P47: 1786.04 | Q47: 6431.09 | R47: 109.77 | S47: 96.15 | T47: 113.86 | V47: 108.73 | W47: 115.14 | X47: 116.79 | Y47: 111.85 | Z47: 112.72 | AA47: 112.27 | AB47: 115.83 | AE47: 121.6 | AF47: 112.49 | AG47: 98.93 | AN47: 4286.36 | AP47: 4332 | AR47: 4266.78 | AS47: 4315.08 | AT47: 4226.33 | AU47: 4300.48 | AW47: 4299.13 | AX47: 109.63 | AY47: 4299.21 | AZ47: 4266.17 | BA47: 100.65 | BB47: 122.17 | BC47: 115.69 | BD47: 117.26 | BE47: 113.6 | BF47: 112.16 | BG47: 123.21 | BH47: 111.8 | BI47: 117.7 | BJ47: 121.4 | BK47: 105.18 | BL47: 105.4 | BN47: 105.34
A48: LEAN-RGNDS-BR | C48: =YEAR(D48)&MONTH(D48) -> 20262 | D48: 46077 | E48: 1870.43 | F48: 1858.65 | G48: 1835.71 | H48: 1678.47 | I48: 1756.37 | J48: 1885.71 | K48: 1725.06 | L48: 1760.45 | N48: 1696.34 | O48: 1822.38 | P48: 1786.04 | Q48: 6389.26 | R48: 109.77 | S48: 96.28 | T48: 113.73 | V48: 109.07 | W48: 115.72 | X48: 116.79 | Y48: 111.39 | Z48: 112.72 | AA48: 111.86 | AB48: 115.93 | AE48: 121.6 | AF48: 112.7 | AG48: 98.93 | AP48: 4332 | AR48: 4262.98 | AS48: 4319.17 | AU48: 4299.8 | AW48: 4276.89 | AX48: 107.52 | AY48: 4312.09 | AZ48: 4266.17 | BA48: 103.13 | BB48: 121.62 | BC48: 115.7 | BD48: 118.23 | BE48: 113.34 | BF48: 112.34 | BG48: 123.21 | BH48: 112.6 | BI48: 117.7 | BJ48: 121.38 | BK48: 105.39 | BN48: 105.45
A49: SB-WRIVE-BR | C49: =YEAR(D49)&MONTH(D49) -> 20262 | D49: 46076 | E49: 1860.49 | F49: 1858.65 | G49: 1864.63 | H49: 1696.79 | I49: 1772.37 | J49: 1878.33 | K49: 1790.06 | L49: 1760.45 | N49: 1705.27 | P49: 1793.54 | Q49: 6389.26 | R49: 110.14 | S49: 98.84 | T49: 113.86 | V49: 109 | W49: 116.11 | X49: 116.99 | Y49: 110.39 | Z49: 112.32 | AA49: 111.25 | AB49: 116.03 | AE49: 121.6 | AF49: 112.43 | AG49: 100.72 | AP49: 4320 | AR49: 4262.98 | AS49: 4337.55 | AU49: 4315.08 | AX49: 107.16 | AY49: 4333.06 | AZ49: 4266.78 | BA49: 104.56 | BB49: 121.83 | BC49: 115.73 | BD49: 117.67 | BE49: 113.37 | BF49: 112.16 | BG49: 123.21 | BH49: 112.6 | BI49: 117.32 | BJ49: 121.51 | BK49: 105.18 | BL49: 105.06 | BN49: 105.34
A50: LEAN-WOBHS-BR | C50: =YEAR(D50)&MONTH(D50) -> 20262 | D50: 46073 | E50: 1877.05 | F50: 1858.65 | G50: 1864.63 | H50: 1722.38 | I50: 1772.37 | J50: 1878.33 | K50: 1790.06 | L50: 1708.88 | M50: 1585.38 | N50: 1730.44 | O50: 1786.33 | P50: 1793.54 | Q50: 6432.12 | R50: 111.41 | S50: 98.85 | T50: 113.7 | V50: 109.81 | W50: 115.85 | X50: 117.39 | Y50: 112.03 | Z50: 112.52 | AA50: 112.25 | AB50: 116.53 | AC50: 109.21 | AE50: 121.88 | AF50: 114.63 | AG50: 99.96 | AH50: 30 | AI50: 30 | AL50: 30 | AN50: 4003.89 | AO50: 7 | AP50: 4320 | AQ50: 4428.55 | AR50: 4244.03 | AS50: 4374.71 | AT50: 4305.19 | AU50: 4315.08 | AV50: 30 | AW50: 4297.11 | AX50: 107.24 | AY50: 4300.14 | AZ50: 4266.78 | BA50: 103.96 | BB50: 122.74 | BC50: 116.44 | BD50: 118.98 | BE50: 114.52 | BF50: 114.43 | BG50: 123.41 | BH50: 113.67 | BI50: 117.32 | BJ50: 120.9 | BK50: 105.18 | BL50: 105.73 | BN50: 105.34
A51: LEAN-RNDPLS-BR | C51: =YEAR(D51)&MONTH(D51) -> 20262 | D51: 46072 | E51: 1883.6 | F51: 1872.21 | G51: 1841.6 | I51: 1811.93 | J51: 1881.66 | K51: 1790.06 | N51: 1730.44 | P51: 1782.3 | Q51: 6420.58 | R51: 111.41 | S51: 98.54 | T51: 114.55 | V51: 109.47 | W51: 116.44 | X51: 117.39 | Y51: 112.85 | Z51: 113.91 | AA51: 112.4 | AB51: 116.43 | AE51: 122.85 | AF51: 114.48 | AG51: 100.26 | AN51: 4003.89 | AP51: 4320 | AQ51: 4428.55 | AR51: 4244.03 | AS51: 4374.71 | AU51: 4309.39 | AW51: 4297.11 | AX51: 108.91 | AY51: 4300.14 | AZ51: 4266.78 | BA51: 104.52 | BB51: 122.42 | BC51: 116 | BD51: 118.7 | BE51: 114.35 | BF51: 114.73 | BG51: 124.61 | BH51: 113.33 | BI51: 117.2 | BJ51: 120.88 | BK51: 106.84 | BL51: 107.06 | BN51: 107.01
A52: SB-WROND-BR | C52: =YEAR(D52)&MONTH(D52) -> 20262 | D52: 46071 | E52: 1886.91 | F52: 1872.21 | G52: 1861.38 | I52: 1837.64 | J52: 1831.25 | K52: 1740.06 | N52: 1712.31 | P52: 1757.3 | Q52: 6433.86 | R52: 111.77 | S52: 98.53 | T52: 114.55 | V52: 109.4 | W52: 116.42 | X52: 117.39 | Y52: 112.38 | Z52: 113.91 | AA52: 112.55 | AB52: 116.33 | AE52: 122.98 | AF52: 114.89 | AG52: 100.32 | AO52: 7 | AP52: 4250 | AR52: 4203.11 | AS52: 4387.09 | AT52: 4305.19 | AU52: 4297.11 | AW52: 4297.11 | AX52: 111.53 | AY52: 4254.31 | BA52: 104.95 | BB52: 122.07 | BC52: 116.95 | BD52: 118.8 | BE52: 113.57 | BF52: 114.68 | BG52: 124.81 | BH52: 112.2 | BI52: 117.2 | BJ52: 120.86 | BK52: 106.84 | BL52: 107.06 | BN52: 107.01
A53: SB-WPOGR-BR | C53: =YEAR(D53)&MONTH(D53) -> 20262 | D53: 46066 | E53: 1873.67 | F53: 1881.4 | G53: 1881.36 | I53: 1837.64 | J53: 1831.25 | K53: 1727.62 | N53: 1724.23 | P53: 1751.08 | Q53: 6382.52 | R53: 111.77 | S53: 97.99 | T53: 114.1 | V53: 109.2 | W53: 115.93 | X53: 117.49 | Y53: 112.79 | Z53: 113.21 | AA53: 113.01 | AB53: 116.43 | AE53: 122.92 | AF53: 115.03 | AG53: 100.01 | AN53: 4292.86 | AO53: 7 | AP53: 4241.23 | AQ53: 4295.09 | AR53: 4217.95 | AS53: 4281.94 | AT53: 4305.19 | AU53: 4303.68 | AV53: 30 | AW53: 4241.68 | AX53: 112.56 | AY53: 4206.11 | AZ53: 4206.11 | BA53: 101.32 | BB53: 122.34 | BC53: 116.39 | BD53: 118.45 | BE53: 114.22 | BF53: 113.81 | BG53: 124.01 | BH53: 112.8 | BI53: 117.2 | BJ53: 121.72 | BK53: 107.18 | BL53: 107.39 | BN53: 107.34
A54: SB-WOEPR-BR | C54: =YEAR(D54)&MONTH(D54) -> 20262 | D54: 46065 | E54: 1890.15 | F54: 1931.2 | G54: 1891.25 | I54: 1837.64 | J54: 1841.14 | K54: 1727.62 | N54: 1738.26 | P54: 1758.57 | Q54: 6471.4 | R54: 110.63 | S54: 97.98 | T54: 113.29 | V54: 108.75 | W54: 115.52 | X54: 117.09 | Y54: 112.68 | Z54: 113.02 | AA54: 112.79 | AB54: 116.13 | AC54: 109.21 | AE54: 122.17 | AF54: 115.01 | AG54: 100.01 | AN54: 4292.86 | AO54: 7 | AP54: 4241.23 | AQ54: 4295.09 | AR54: 4217.95 | AS54: 4281.94 | AT54: 4281.05 | AU54: 4303.68 | AV54: 30 | AW54: 4255.7 | AX54: 111.09 | AY54: 4206.11 | AZ54: 4206.11 | BA54: 101.3 | BB54: 122.24 | BC54: 115.38 | BD54: 118.07 | BE54: 113.98 | BF54: 113.24 | BG54: 123.61 | BH54: 113.04 | BI54: 117.2 | BJ54: 121.69 | BK54: 107.18 | BL54: 107.39 | BN54: 107.34
A55: SB-WNOPR-BR | C55: =YEAR(D55)&MONTH(D55) -> 20262 | D55: 46064 | E55: 1890.15 | F55: 1931.2 | G55: 1926.45 | I55: 1831.71 | J55: 1841.14 | K55: 1727.62 | N55: 1716.02 | P55: 1758.57 | Q55: 6471.4 | R55: 109.63 | S55: 96.6 | T55: 112.46 | V55: 108.55 | W55: 115.5 | X55: 116.59 | Y55: 112.38 | Z55: 112.62 | AA55: 112.39 | AB55: 115.63 | AC55: 109.03 | AE55: 121.8 | AF55: 114.04 | AG55: 99.17 | AN55: 4292.86 | AP55: 4263.28 | AQ55: 4295.09 | AR55: 4234.42 | AS55: 4281.94 | AT55: 4208.64 | AU55: 4313.36 | AV55: 30 | AW55: 4255.7 | AX55: 111.48 | AY55: 4243.52 | AZ55: 4206.11 | BA55: 107.23 | BB55: 120.98 | BC55: 114.03 | BD55: 116.68 | BE55: 114.25 | BF55: 113.05 | BG55: 123.61 | BH55: 113.04 | BI55: 117.2 | BJ55: 121.49 | BK55: 105.84 | BL55: 106.23 | BN55: 106.01
A56: SB-WMOGI-BR | C56: =YEAR(D56)&MONTH(D56) -> 20262 | D56: 46063 | E56: 1903.39 | F56: 1931.2 | G56: 1938.81 | I56: 1831.71 | J56: 1834.47 | K56: 1727.62 | N56: 1681.79 | P56: 1758.57 | Q56: 6496.4 | R56: 110.49 | S56: 96.71 | T56: 113.28 | V56: 108.54 | W56: 115.29 | X56: 116.39 | Y56: 112.33 | Z56: 112.82 | AA56: 113.78 | AB56: 115.53 | AC56: 108.72 | AE56: 121.55 | AF56: 113.8 | AG56: 99.24 | AN56: 4165.67 | AP56: 4261.72 | AQ56: 4295.09 | AR56: 4128.59 | AS56: 4230.67 | AT56: 4208.64 | AU56: 4332.73 | AW56: 4279.16 | AX56: 112.06 | AY56: 4173.25 | BA56: 109.68 | BB56: 121.03 | BC56: 115.14 | BD56: 116.3 | BE56: 114.25 | BF56: 113.05 | BG56: 123.41 | BH56: 112.4 | BI56: 117.2 | BJ56: 121.27 | BK56: 106.51 | BL56: 107.06 | BN56: 106.67
A57: SB-WTRIM-BR | C57: =YEAR(D57)&MONTH(D57) -> 20262 | D57: 46062 | E57: 1903.39 | F57: 1931.2 | G57: 1938.81 | I57: 1831.71 | J57: 1820.32 | K57: 1707.7 | N57: 1701.74 | P57: 1748.61 | Q57: 6449.38 | R57: 110.49 | S57: 96.46 | T57: 112.45 | V57: 108.54 | W57: 115.27 | X57: 116.54 | Y57: 112.57 | Z57: 112.22 | AA57: 113.78 | AB57: 116.23 | AC57: 109.17 | AE57: 122.23 | AF57: 112.94 | AG57: 98.8 | AN57: 4071.3 | AP57: 4252.9 | AR57: 4128.59 | AS57: 4230.67 | AT57: 4208.64 | AU57: 4356.93 | AW57: 4279.16 | AX57: 112.05 | AY57: 4173.25 | AZ57: 4335.02 | BA57: 110.28 | BB57: 121.28 | BC57: 115.32 | BD57: 116.68 | BE57: 113.85 | BF57: 112.38 | BG57: 124.2 | BH57: 112.7 | BI57: 117.2 | BJ57: 121.25 | BK57: 106.18 | BL57: 106.73 | BN57: 106.34
A58: SB-WIJUI-BR | C58: =YEAR(D58)&MONTH(D58) -> 20262 | D58: 46059 | E58: 1929.81 | F58: 1921.73 | G58: 1951.17 | I58: 1831.71 | J58: 1818.65 | K58: 1683.06 | N58: 1696.28 | P58: 1720.59 | Q58: 6461.6 | R58: 111.13 | S58: 96.43 | T58: 113.98 | V58: 109.3 | W58: 116.14 | X58: 117.41 | Y58: 113.15 | Z58: 113.61 | AA58: 113.08 | AB58: 116.66 | AC58: 110.83 | AE58: 123.03 | AF58: 115.32 | AG58: 99.52 | AN58: 4071.3 | AP58: 4263 | AQ58: 4307.22 | AR58: 4132.3 | AS58: 4208.13 | AT58: 4207.37 | AU58: 4319.5 | AW58: 4299.64 | AX58: 113.43 | AY58: 4191.79 | AZ58: 4335.02 | BA58: 110.23 | BB58: 121.86 | BC58: 116.3 | BD58: 119.14 | BE58: 115.62 | BF58: 114.26 | BG58: 124.34 | BH58: 113.3 | BI58: 117.2 | BJ58: 121.4 | BK58: 108.17 | BL58: 108.39 | BN58: 108.34
A59: SB-WBARR-BR | C59: =YEAR(D59)&MONTH(D59) -> 20262 | D59: 46058 | E59: 1926.5 | F59: 1921.73 | G59: 1951.17 | I59: 1831.71 | J59: 1796.66 | K59: 1661.51 | N59: 1668.68 | P59: 1739.21 | Q59: 6520.11 | R59: 110.77 | S59: 96.11 | T59: 111.95 | V59: 109.13 | W59: 114.92 | X59: 117.41 | Y59: 112.15 | Z59: 111.88 | AA59: 113.18 | AB59: 116.61 | AC59: 110.83 | AE59: 121.82 | AF59: 113.05 | AG59: 99.79 | AN59: 4071.3 | AP59: 4263 | AQ59: 4307.22 | AR59: 4155.92 | AS59: 4175.78 | AT59: 4152.19 | AU59: 4321.75 | AW59: 4299.64 | AX59: 113.41 | AY59: 4191.79 | AZ59: 4335.02 | BA59: 104.71 | BB59: 121.41 | BC59: 115.1 | BD59: 117.55 | BE59: 113.97 | BF59: 113.98 | BG59: 123.75 | BH59: 113.3 | BI59: 117.2 | BJ59: 121.38 | BK59: 107.18 | BL59: 107.39 | BN59: 107.34
A60: SB-GRCNR-BR | C60: =YEAR(D60)&MONTH(D60) -> 20262 | D60: 46057 | E60: 1906.63 | F60: 1930.72 | G60: 1951.17 | I60: 1831.71 | J60: 1831.39 | K60: 1694.84 | N60: 1681.16 | P60: 1784.68 | Q60: 6528.55 | R60: 108.63 | S60: 95.48 | T60: 111.91 | V60: 108.68 | W60: 115.24 | X60: 116.94 | Y60: 111.27 | Z60: 111.52 | AA60: 111.51 | AB60: 116.59 | AE60: 121.49 | AF60: 112.95 | AG60: 97.4 | AN60: 4071.3 | AO60: 7 | AP60: 4200 | AQ60: 4307.22 | AR60: 4158.5 | AS60: 4175.78 | AT60: 4148.96 | AU60: 4316.49 | AW60: 4276.84 | AX60: 112.15 | AY60: 4210.32 | AZ60: 4335.02 | BA60: 102.64 | BB60: 120.98 | BC60: 114.4 | BD60: 115.67 | BE60: 112.91 | BF60: 110.96 | BG60: 124.85 | BH60: 113.17 | BI60: 117.07 | BJ60: 120.77 | BK60: 105.51 | BL60: 106.06 | BN60: 105.68
A61: SB-WBRCN-BR | C61: =YEAR(D61)&MONTH(D61) -> 20262 | D61: 46056 | E61: 1913.26 | F61: 1930.72 | G61: 1946.23 | I61: 1831.71 | J61: 1839.72 | K61: 1694.84 | N61: 1682.82 | P61: 1765.19 | Q61: 6702.34 | R61: 109.64 | S61: 96.09 | T61: 111.63 | V61: 108.4 | W61: 114.81 | X61: 116.24 | Y61: 111.44 | Z61: 111.12 | AA61: 112.37 | AB61: 116.14 | AE61: 121.49 | AF61: 111.9 | AG61: 97.78 | AO61: 7 | AP61: 4200 | AQ61: 4307.22 | AR61: 4176.41 | AS61: 4128.59 | AT61: 4148.96 | AU61: 4216.22 | AW61: 4284.94 | AX61: 111.8 | AY61: 4210.32 | AZ61: 4335.02 | BA61: 102.81 | BB61: 120.48 | BC61: 114.55 | BD61: 116.02 | BE61: 113.23 | BF61: 112.28 | BG61: 124.85 | BH61: 113.17 | BI61: 117.07 | BJ61: 121.15 | BK61: 105.18 | BL61: 105.4 | BN61: 105.34
A62: SB-GDCGR-BR | C62: =YEAR(D62)&MONTH(D62) -> 20262 | D62: 46055 | E62: 1896.68 | F62: 1921.68 | G62: 1896.64 | I62: 1831.71 | J62: 1833.26 | K62: 1694.8 | N62: 1697.24 | P62: 1784.68 | Q62: 6516.99 | R62: 110.63 | S62: 95.28 | T62: 112.47 | V62: 108.77 | W62: 115.21 | X62: 116.34 | Y62: 110.8 | Z62: 110.92 | AA62: 115.08 | AB62: 116.14 | AE62: 122.67 | AF62: 112.31 | AG62: 99.53 | AI62: 30 | AN62: 4338.78 | AO62: 7 | AP62: 4200 | AQ62: 4307.22 | AR62: 4176.41 | AS62: 4111.07 | AT62: 4148.96 | AU62: 4292.05 | AW62: 4284.94 | AX62: 108.13 | AY62: 4210.32 | AZ62: 4305.53 | BA62: 101.26 | BB62: 121.83 | BC62: 115.19 | BD62: 116.84 | BE62: 113.25 | BF62: 112.67 | BG62: 124.85 | BH62: 113.57 | BI62: 117.45 | BJ62: 122.94 | BK62: 105.18 | BL62: 105.4 | BN62: 105.34
A63: SB-GDUMS-BR | C63: =YEAR(D63)&MONTH(D63) -> 20261 | D63: 46052 | E63: 1924.73 | F63: 1920.08 | G63: 1919.8 | I63: 1830.13 | J63: 1832.34 | K63: 1694.66 | N63: 1712.68 | P63: 1784.38 | Q63: 6527.23 | R63: 110.66 | S63: 95.2 | T63: 112.74 | V63: 109.67 | W63: 115.14 | X63: 117.12 | Y63: 110.37 | Z63: 110.69 | AA63: 115.67 | AB63: 116.68 | AE63: 122.3 | AF63: 113.88 | AG63: 99.48 | AI63: 30 | AN63: 4341.5 | AO63: 7 | AP63: 4200 | AQ63: 4353.47 | AR63: 4181.3 | AS63: 4137.25 | AT63: 4162.25 | AU63: 4374.39 | AW63: 4272.71 | AX63: 106.41 | AY63: 4207.71 | AZ63: 4310.28 | BA63: 101.09 | BB63: 122.03 | BC63: 115.17 | BD63: 116.58 | BE63: 113.55 | BF63: 113.71 | BG63: 128.81 | BH63: 113.57 | BI63: 117.54 | BJ63: 123.32 | BK63: 105.17 | BL63: 105.39 | BN63: 105.33
A64: SB-GCHAMS-BR | C64: =YEAR(D64)&MONTH(D64) -> 20261 | D64: 46051 | E64: 1924.73 | F64: 1929.06 | G64: 1919.8 | I64: 1830.13 | J64: 1864.81 | K64: 1795.4 | N64: 1706.11 | P64: 1784.38 | Q64: 6527.23 | R64: 110.6 | S64: 94.82 | T64: 112.73 | V64: 109.69 | W64: 115.12 | X64: 117.91 | Y64: 110.9 | Z64: 110.89 | AA64: 115.05 | AB64: 117.79 | AE64: 123.79 | AF64: 113.87 | AG64: 98.07 | AI64: 30 | AN64: 4324.78 | AO64: 7 | AP64: 4200 | AQ64: 4353.47 | AR64: 4159.42 | AS64: 4157.05 | AT64: 4179.49 | AU64: 4390.41 | AW64: 4272.71 | AX64: 104.35 | AY64: 4207.71 | AZ64: 4262.2 | BA64: 101.06 | BB64: 121.81 | BC64: 115.82 | BD64: 116.94 | BE64: 113.81 | BF64: 113.4 | BG64: 128.81 | BH64: 113.57 | BI64: 117.54 | BJ64: 123.3 | BK64: 105.17 | BL64: 105.39 | BN64: 105.33
A65: SB-GMRMS-BR | C65: =YEAR(D65)&MONTH(D65) -> 20261 | D65: 46050 | E65: 1924.73 | F65: 1929.06 | G65: 1919.8 | I65: 1832.66 | J65: 1864.81 | K65: 1786.21 | L65: 1752.26 | N65: 1680.11 | P65: 1802.38 | Q65: 6531.49 | R65: 110.88 | S65: 94.95 | T65: 113.84 | V65: 110.19 | W65: 115.4 | X65: 118.81 | Y65: 111.19 | Z65: 111.16 | AA65: 115.65 | AB65: 118.39 | AE65: 126.78 | AF65: 114.96 | AG65: 99.65 | AI65: 25 | AN65: 4281.95 | AP65: 4200 | AQ65: 4353.47 | AR65: 4162.44 | AS65: 4148.81 | AT65: 4244.29 | AU65: 4390.41 | AW65: 4284.98 | AX65: 111.01 | AY65: 4207.71 | AZ65: 4262.2 | BA65: 104.23 | BB65: 122.38 | BC65: 113.89 | BD65: 116.01 | BE65: 114.28 | BF65: 113.45 | BG65: 128.81 | BH65: 113.57 | BI65: 117.67 | BJ65: 123.28 | BK65: 105.17 | BL65: 105.39 | BN65: 105.33
A66: SB-GCPMT-BR | C66: =YEAR(D66)&MONTH(D66) -> 20261 | D66: 46049 | E66: 1900.04 | F66: 1925.09 | G66: 1907.45 | I66: 1818.22 | J66: 1845.67 | K66: 1786.21 | L66: 1748.22 | N66: 1680.11 | O66: 1785.92 | P66: 1764.92 | Q66: 6672.16 | R66: 111.08 | S66: 96.18 | T66: 114.59 | V66: 110.29 | W66: 116.88 | X66: 119.46 | Y66: 112.66 | Z66: 112.16 | AA66: 116.28 | AB66: 118.76 | AE66: 126.21 | AF66: 115.45 | AG66: 98.78 | AI66: 25 | AN66: 4264.49 | AP66: 4200 | AQ66: 4315.13 | AR66: 4144.96 | AS66: 4159.3 | AT66: 4208.21 | AU66: 4314.5 | AV66: 30 | AW66: 4309.09 | AX66: 111.27 | AY66: 4207.71 | AZ66: 4245.97 | BA66: 104.21 | BB66: 123.58 | BC66: 115.58 | BD66: 116.5 | BE66: 115.85 | BF66: 113.86 | BG66: 129.05 | BH66: 113.33 | BI66: 119.16 | BJ66: 123.26 | BK66: 106.83 | BL66: 107.05 | BN66: 107
A67: SB-GPRMMT-BR | C67: =YEAR(D67)&MONTH(D67) -> 20261 | D67: 46048 | E67: 1900.04 | F67: 1902.12 | G67: 1907.45 | I67: 1806.37 | J67: 1867.64 | K67: 1758.64 | L67: 1736.09 | N67: 1664.88 | O67: 1803 | P67: 1789.37 | Q67: 6603.58 | R67: 111.08 | S67: 95.67 | T67: 115.24 | V67: 110.51 | W67: 117.46 | X67: 120.44 | Y67: 113.64 | Z67: 113.36 | AA67: 116.28 | AB67: 119.14 | AE67: 128.45 | AF67: 115.95 | AG67: 99.99 | AI67: 10 | AN67: 4198.58 | AP67: 4209.79 | AQ67: 4315.13 | AR67: 4144.96 | AS67: 4198.54 | AT67: 4208.21 | AU67: 4314.5 | AV67: 30 | AW67: 4309.09 | AX67: 109.79 | AY67: 4227.74 | AZ67: 4218.41 | BA67: 108.3 | BB67: 123.48 | BC67: 117.12 | BD67: 117.74 | BE67: 118.41 | BF67: 114.65 | BG67: 129.05 | BH67: 113.83 | BI67: 119.79 | BJ67: 126.2 | BK67: 107.17 | BL67: 107.72 | BN67: 107.33
A68: SB-GSRRS-BR | C68: =YEAR(D68)&MONTH(D68) -> 20261 | D68: 46045 | E68: 1875.34 | F68: 1884.15 | G68: 1895.1 | H68: 1665.92 | I68: 1806.37 | J68: 1863.34 | K68: 1775.91 | L68: 1699.72 | N68: 1681.88 | O68: 1794.93 | P68: 1789.37 | Q68: 6665.58 | R68: 111.83 | S68: 96.29 | T68: 115.6 | V68: 112.14 | W68: 118.2 | X68: 121.04 | Y68: 114.01 | Z68: 114.29 | AA68: 116.74 | AB68: 119.51 | AE68: 127.38 | AF68: 123.34 | AG68: 101.34 | AI68: 10 | AN68: 4198.58 | AP68: 4197.94 | AQ68: 4281.6 | AR68: 4134.83 | AS68: 4178.36 | AT68: 4187.55 | AU68: 4238.58 | AV68: 30 | AW68: 4298.38 | AX68: 114.8 | AY68: 4277.81 | AZ68: 4218.41 | BA68: 108.07 | BB68: 124.22 | BC68: 119.05 | BD68: 120.09 | BE68: 120.74 | BF68: 114.98 | BG68: 131.03 | BH68: 115.33 | BI68: 121.78 | BJ68: 127.72 | BK68: 108.5 | BL68: 108.72 | BN68: 108.66
A69: SB-GSDPR-BR | C69: =YEAR(D69)&MONTH(D69) -> 20261 | D69: 46044 | E69: 1900.04 | F69: 1902.12 | G69: 1895.1 | H69: 1678.23 | I69: 1806.37 | J69: 1835.22 | K69: 1661.33 | L69: 1699.72 | N69: 1637.78 | O69: 1770.72 | P69: 1789.37 | Q69: 6667.58 | R69: 112.87 | S69: 96.28 | T69: 116.21 | V69: 112.03 | W69: 117.89 | X69: 120.81 | Y69: 114.9 | Z69: 114.88 | AA69: 116.92 | AB69: 119.75 | AE69: 127.27 | AF69: 125.07 | AG69: 101.33 | AI69: 10 | AN69: 4226.24 | AP69: 4197.94 | AQ69: 4297.25 | AR69: 4171.18 | AS69: 4178.36 | AT69: 4118.01 | AU69: 4238.58 | AV69: 30 | AW69: 4298.38 | AX69: 113.55 | AY69: 4251.66 | AZ69: 4261.02 | BA69: 109.4 | BB69: 124.46 | BC69: 119.94 | BD69: 120.41 | BE69: 121.07 | BF69: 115.64 | BG69: 131.53 | BH69: 115.15 | BI69: 121.78 | BJ69: 127.7 | BK69: 109.7 | BL69: 109.66 | BN69: 109.8
A70: SB-WBALMA-BR | C70: =YEAR(D70)&MONTH(D70) -> 20261 | D70: 46043 | E70: 1900.04 | F70: 1902.12 | G70: 1895.1 | H70: 1715.16 | I70: 1807.96 | J70: 1835.22 | K70: 1782.07 | L70: 1699.72 | M70: 1476 | N70: 1628.91 | O70: 1771.58 | P70: 1835.05 | Q70: 6632.7 | R70: 112.87 | S70: 98.26 | T70: 116.07 | V70: 113.43 | W70: 119.4 | X70: 121.32 | Y70: 115.23 | Z70: 115.18 | AA70: 117.06 | AB70: 119.79 | AE70: 128.65 | AF70: 124.32 | AG70: 102.77 | AN70: 4266.18 | AP70: 4199.68 | AQ70: 4297.25 | AR70: 4132.94 | AS70: 4226.49 | AT70: 4128.68 | AU70: 4238.58 | AV70: 30 | AW70: 4316.95 | AX70: 111.98 | AY70: 4251.66 | AZ70: 4261.02 | BA70: 109.33 | BB70: 126.44 | BC70: 121.03 | BD70: 121.23 | BE70: 120.25 | BF70: 115.64 | BG70: 132.53 | BH70: 118.83 | BI70: 121.91 | BJ70: 128.07 | BK70: 109.7 | BL70: 109.91 | BN70: 109.8
A71: SB-WCHSGO-BR | C71: =YEAR(D71)&MONTH(D71) -> 20261 | D71: 46042 | E71: 1871.76 | F71: 1902.12 | G71: 1892.63 | H71: 1756.8 | I71: 1810.37 | J71: 1835.22 | K71: 1782.07 | L71: 1689.84 | M71: 1463.62 | N71: 1638.63 | O71: 1773.29 | P71: 1800.04 | Q71: 6634.73 | R71: 112.87 | S71: 98.66 | T71: 117.06 | V71: 112.06 | W71: 118.22 | X71: 121.32 | Y71: 114.84 | Z71: 114.98 | AA71: 117.01 | AB71: 119.9 | AE71: 128.31 | AF71: 124.53 | AG71: 105.27 | AN71: 4249.25 | AO71: 7 | AP71: 4199.68 | AQ71: 4314.5 | AR71: 4140.32 | AS71: 4244.15 | AT71: 4139.2 | AU71: 4238.58 | AW71: 4308.53 | AX71: 114.21 | AY71: 4212.77 | AZ71: 4339.8 | BA71: 109.36 | BB71: 125.85 | BC71: 120.03 | BD71: 119.95 | BE71: 116.55 | BF71: 116.45 | BG71: 133.03 | BH71: 118.83 | BI71: 122.28 | BJ71: 128.45 | BK71: 109.16 | BL71: 109.38 | BN71: 109.33
A72: SB-WCGMS-BR | C72: =YEAR(D72)&MONTH(D72) -> 20261 | D72: 46041 | E72: 1868.16 | F72: 1902.12 | G72: 1892.63 | H72: 1752.85 | I72: 1810.37 | J72: 1832.87 | K72: 1786.2 | L72: 1689.84 | M72: 1438.87 | N72: 1673.56 | O72: 1788.95 | P72: 1800.04 | Q72: 6646.97 | R72: 112.83 | S72: 98.65 | T72: 117.62 | V72: 112.49 | W72: 119.95 | X72: 122.21 | Y72: 114.84 | Z72: 114.98 | AA72: 117.91 | AB72: 120.45 | AE72: 129.5 | AF72: 124.63 | AG72: 103.88 | AN72: 4274.98 | AO72: 7 | AP72: 4203 | AQ72: 4314.5 | AR72: 4140.32 | AS72: 4244.15 | AT72: 4139.2 | AU72: 4238.58 | AW72: 4313.61 | AX72: 114.43 | AY72: 4212.77 | AZ72: 4339.8 | BA72: 109.77 | BB72: 128.11 | BC72: 121.96 | BD72: 120.96 | BE72: 118.23 | BF72: 116.45 | BG72: 133.03 | BH72: 118.99 | BI72: 122.78 | BJ72: 128.43 | BK72: 109.16 | BL72: 109.38 | BN72: 109.33
A73: SB-WCPMT-BR | C73: =YEAR(D73)&MONTH(D73) -> 20261 | D73: 46038 | E73: 1857.36 | F73: 1902.12 | G73: 1892.63 | H73: 1752.85 | I73: 1810.37 | J73: 1831.45 | K73: 1798.6 | L73: 1666.62 | M73: 1443.72 | N73: 1675.93 | O73: 1788.95 | P73: 1776.13 | Q73: 6625.55 | R73: 112.83 | S73: 98.61 | T73: 118.49 | V73: 112.18 | W73: 119.9 | X73: 121.91 | Y73: 114.84 | Z73: 115.26 | AA73: 117.91 | AB73: 120.16 | AE73: 129.14 | AF73: 124.63 | AG73: 103.86 | AN73: 4274.98 | AO73: 7 | AP73: 4173.75 | AQ73: 4316.02 | AR73: 4125.49 | AS73: 4273.7 | AT73: 4180.08 | AU73: 4285.65 | AW73: 4348.66 | AX73: 114.43 | AY73: 4212.77 | AZ73: 4284.72 | BA73: 109.71 | BB73: 128.07 | BC73: 121.65 | BD73: 120.35 | BE73: 118.23 | BF73: 116.45 | BG73: 131.7 | BH73: 118.99 | BI73: 122.78 | BJ73: 128.37 | BK73: 109.16 | BL73: 109.38 | BN73: 109.33
A74: SB-WDUMT-BR | C74: =YEAR(D74)&MONTH(D74) -> 20261 | D74: 46037 | E74: 1857.36 | F74: 1902.12 | G74: 1892.63 | H74: 1752.85 | I74: 1812.34 | J74: 1821.45 | K74: 1798.6 | L74: 1696.43 | M74: 1454.43 | N74: 1664.81 | O74: 1788.95 | P74: 1776.13 | Q74: 6419.28 | R74: 112.83 | S74: 98.53 | T74: 119.26 | V74: 112.17 | W74: 119.88 | X74: 122.01 | Y74: 114.84 | Z74: 115.26 | AA74: 117.08 | AB74: 120.39 | AE74: 129.47 | AF74: 123.86 | AG74: 103.72 | AN74: 4239.09 | AO74: 7 | AP74: 4173.75 | AR74: 4103.38 | AS74: 4273.7 | AT74: 4180.08 | AU74: 4285.65 | AW74: 4348.66 | AX74: 114.43 | AY74: 4195.57 | AZ74: 4274.7 | BA74: 109.69 | BB74: 128.24 | BC74: 120.84 | BD74: 119.83 | BE74: 118.23 | BF74: 116.45 | BG74: 132.1 | BH74: 118.49 | BI74: 122.78 | BJ74: 128.35 | BK74: 109.23 | BL74: 109.22 | BN74: 109.23
A75: SB-WMRMST-BR | C75: =YEAR(D75)&MONTH(D75) -> 20261 | D75: 46036 | E75: 1857.36 | F75: 1902.12 | G75: 1892.63 | H75: 1758.56 | I75: 1812.34 | J75: 1803.35 | K75: 1812.89 | L75: 1696.43 | M75: 1474.84 | N75: 1657.01 | O75: 1755.05 | P75: 1790.42 | Q75: 6406.46 | R75: 112.08 | S75: 98.83 | T75: 119.83 | V75: 114.03 | W75: 119.46 | X75: 122.01 | Y75: 114.84 | Z75: 115.36 | AA75: 117.73 | AB75: 120.39 | AE75: 129.55 | AF75: 121.16 | AG75: 104.61 | AN75: 4239.09 | AO75: 7 | AP75: 4162.5 | AR75: 4132.3 | AS75: 4284.82 | AT75: 4230.58 | AU75: 4285.65 | AW75: 4322.09 | AY75: 4195.57 | AZ75: 4274.7 | BA75: 109.68 | BB75: 128.88 | BC75: 119.47 | BD75: 120.64 | BE75: 115.85 | BF75: 115.31 | BG75: 132.1 | BH75: 118.49 | BI75: 122.78 | BJ75: 127.14 | BK75: 109.76 | BL75: 109.62 | BN75: 109.78
A76: SB-WDIAMT-BR | C76: =YEAR(D76)&MONTH(D76) -> 20261 | D76: 46035 | E76: 1854.88 | F76: 1911.1 | G76: 1892.63 | H76: 1761.85 | I76: 1812.34 | J76: 1832.05 | K76: 1812.89 | L76: 1716.19 | M76: 1502.91 | N76: 1657.25 | O76: 1771.16 | P76: 1732.39 | Q76: 6406.46 | R76: 111.08 | S76: 101 | T76: 120.74 | V76: 114.86 | W76: 119.64 | X76: 122.31 | Y76: 115.01 | Z76: 115.36 | AA76: 116.11 | AB76: 120.8 | AE76: 130.13 | AF76: 122.99 | AG76: 105.01 | AN76: 4250.22 | AP76: 4217.73 | AQ76: 4401.55 | AR76: 4118.39 | AS76: 4311.25 | AT76: 4210.75 | AU76: 4317.03 | AW76: 4387.88 | AY76: 4223.4 | AZ76: 4274.7 | BA76: 110.48 | BB76: 129.28 | BC76: 122.28 | BD76: 120.39 | BE76: 116.87 | BF76: 114.65 | BG76: 132.7 | BH76: 120.63 | BI76: 122.65 | BJ76: 128.31 | BK76: 110.28 | BL76: 109.89 | BN76: 110.33
A77: SB-WPRMMT-BR | C77: =YEAR(D77)&MONTH(D77) -> 20261 | D77: 46034 | E77: 1864.81 | F77: 1942.61 | G77: 1900.04 | H77: 1737.55 | I77: 1812.34 | J77: 1822.87 | K77: 1793.98 | L77: 1712.9 | M77: 1493.85 | N77: 1675.04 | O77: 1768.53 | P77: 1735.14 | Q77: 6348.23 | R77: 113.33 | S77: 101.28 | T77: 120.73 | V77: 116.35 | W77: 120.82 | X77: 123.88 | Y77: 115.31 | Z77: 116.76 | AA77: 117.91 | AB77: 121.88 | AE77: 130.84 | AF77: 123.96 | AG77: 104.77 | AN77: 4250.22 | AP77: 4224.38 | AQ77: 4401.55 | AR77: 4192.91 | AS77: 4311.25 | AT77: 4210.75 | AU77: 4207.59 | AW77: 4372.7 | AY77: 4227.38 | AZ77: 4274.7 | BA77: 111.04 | BB77: 132.61 | BC77: 123.01 | BD77: 124.06 | BE77: 117.53 | BF77: 115.31 | BG77: 133.27 | BH77: 120.6 | BI77: 123.65 | BJ77: 128.29 | BK77: 109.83 | BL77: 109.72 | BN77: 110
A78: SB-WRSPRT-BR | C78: =YEAR(D78)&MONTH(D78) -> 20261 | D78: 46031 | E78: 1864.81 | F78: 1942.61 | G78: 1900.04 | H78: 1744.94 | I78: 1812.34 | J78: 1822.87 | K78: 1801.93 | L78: 1712.9 | M78: 1468.51 | N78: 1679.57 | O78: 1769.78 | P78: 1754.82 | Q78: 6348.23 | R78: 113.33 | S78: 101.24 | T78: 120.71 | V78: 115.52 | W78: 121.16 | X78: 123.99 | Y78: 114.94 | Z78: 115.98 | AA78: 117.46 | AB78: 123 | AE78: 131.32 | AF78: 125.65 | AG78: 104.76 | AN78: 4250.22 | AP78: 4278.33 | AQ78: 4347.19 | AR78: 4222.47 | AT78: 4190.51 | AU78: 4186.46 | AW78: 4372.7 | AY78: 4227.38 | AZ78: 4225.93 | BA78: 110.98 | BB78: 133.64 | BC78: 125.14 | BD78: 126.06 | BE78: 119.74 | BF78: 115.31 | BG78: 134.49 | BH78: 122.24 | BI78: 123.77 | BK78: 109.16 | BL78: 109.38 | BN78: 109.33
A79: SB-WSRRS-BR | C79: =YEAR(D79)&MONTH(D79) -> 20261 | D79: 46030 | E79: 1859.84 | F79: 1933.63 | G79: 1900.04 | H79: 1732.1 | I79: 1832.1 | J79: 1820.05 | K79: 1801.93 | L79: 1709.6 | M79: 1468.51 | N79: 1679.08 | O79: 1762.44 | P79: 1730.57 | Q79: 6403.96 | R79: 113.33 | S79: 101.23 | T79: 120.71 | V79: 116.27 | W79: 120.64 | X79: 124.21 | Y79: 114.6 | Z79: 115.73 | AA79: 118.73 | AB79: 123.22 | AE79: 131.81 | AF79: 127.23 | AG79: 106.14 | AN79: 4250.22 | AP79: 4270.75 | AQ79: 4347.19 | AR79: 4222.47 | AT79: 4190.51 | AU79: 4207.45 | AW79: 4372.7 | AY79: 4227.38 | AZ79: 4225.93 | BA79: 110.96 | BB79: 131.83 | BC79: 122.85 | BD79: 124.89 | BE79: 115.35 | BF79: 117.94 | BG79: 135.09 | BH79: 122.24 | BI79: 123.77 | BK79: 108.5 | BL79: 108.72 | BN79: 108.66
A80: SB-WSDPR-BR | C80: =YEAR(D80)&MONTH(D80) -> 20261 | D80: 46029 | E80: 1854.88 | F80: 1920.08 | G80: 1900.04 | H80: 1732.1 | I80: 1819.26 | J80: 1799.78 | K80: 1801.93 | L80: 1709.6 | M80: 1513.24 | N80: 1677.79 | O80: 1753.43 | P80: 1730.57 | Q80: 6398.04 | R80: 113.33 | S80: 101.01 | T80: 121.4 | V80: 116.4 | W80: 122.76 | X80: 124.21 | Y80: 113.95 | Z80: 118.07 | AA80: 118.02 | AB80: 123.34 | AE80: 131.81 | AF80: 126.8 | AG80: 104.7 | AN80: 4250.22 | AP80: 4270.75 | AQ80: 4347.19 | AR80: 4238.19 | AT80: 4190.51 | AU80: 4207.45 | AW80: 4372.7 | AY80: 4227.38 | AZ80: 4225.93 | BA80: 111.43 | BB80: 133.03 | BC80: 124.39 | BD80: 128.14 | BE80: 119.31 | BF80: 116.23 | BG80: 135.09 | BH80: 122.53 | BI80: 123.77 | BJ80: 128.53 | BK80: 108.5 | BL80: 108.72 | BN80: 108.66
A81: SB-WSGOGD-BR | C81: =YEAR(D81)&MONTH(D81) -> 20261 | D81: 46028 | E81: 1854.88 | F81: 1920.08 | G81: 1900.04 | H81: 1734.02 | I81: 1819.07 | J81: 1803.12 | K81: 1841.93 | L81: 1709.6 | M81: 1540.13 | N81: 1676.24 | O81: 1776.01 | P81: 1635.27 | Q81: 6547.86 | S81: 101.47 | T81: 122.18 | V81: 116.78 | W81: 120.55 | X81: 124.98 | Y81: 113.95 | Z81: 117.82 | AA81: 117.64 | AB81: 124 | AE81: 133.31 | AF81: 128.04 | AG81: 105.62 | AP81: 4261.29 | AQ81: 4310.96 | AR81: 4238.19 | AT81: 4190.51 | AU81: 4207.45 | AY81: 4251.24 | AZ81: 4225.93 | BA81: 115.54 | BB81: 133.21 | BC81: 125.67 | BD81: 129.87 | BE81: 125.2 | BF81: 115.56 | BG81: 134.71 | BH81: 119.53 | BI81: 123.77 | BJ81: 128.82 | BK81: 108.17 | BL81: 108.38 | BN81: 108.62
A82: SB-WUNMG-BR | C82: =YEAR(D82)&MONTH(D82) -> 20261 | D82: 46027 | E82: 1859.84 | F82: 1920.08 | G82: 1907.68 | H82: 1757.79 | I82: 1819.07 | J82: 1815.95 | K82: 1841.93 | L82: 1705.27 | M82: 1582.41 | N82: 1657.88 | O82: 1776.01 | P82: 1694.8 | Q82: 6531.37 | S82: 104.18 | T82: 122.18 | V82: 116.56 | W82: 121.71 | X82: 125.28 | Y82: 113.33 | Z82: 118.23 | AA82: 120.35 | AB82: 124.93 | AE82: 132.39 | AF82: 132.87 | AG82: 113.12 | AI82: 30 | AN82: 4347.68 | AP82: 4257.9 | AQ82: 4310.96 | AR82: 4238.19 | AS82: 4187.13 | AT82: 4190.51 | AU82: 4230.85 | AW82: 4309.44 | AY82: 4190.51 | AZ82: 4225.93 | BA82: 115.56 | BB82: 136 | BC82: 122.04 | BD82: 125.51 | BE82: 126.78 | BF82: 121.93 | BG82: 135.91 | BH82: 119.53 | BI82: 124.77 | BJ82: 129.96 | BK82: 108.94 | BL82: 109.82 | BN82: 108.86
C83: =YEAR(D83)&MONTH(D83) -> 20261 | D83: 46024 | E83: 1869.77 | F83: 1911.1 | G83: 1887.69 | H83: 1722.38 | I83: 1794.44 | J83: 1853.14 | K83: 1841.93 | L83: 1708.88 | M83: 1585.38 | N83: 1685.99 | O83: 1786.33 | P83: 1733.61 | Q83: 6437.74 | R83: 114.92 | S83: 106.96 | T83: 123.32 | V83: 118.72 | W83: 124.51 | X83: 126.4 | Y83: 116.13 | Z83: 118.57 | AA83: 118.24 | AB83: 125.01 | AE83: 134.14 | AF83: 132.37 | AG83: 114.23 | AI83: 30 | AN83: 4347.68 | AP83: 4249 | AR83: 4238.19 | AS83: 4187.13 | AT83: 4190.51 | AU83: 4247.97 | AW83: 4272.02 | AX83: 115.15 | AY83: 4190.51 | BA83: 120.65 | BB83: 136.56 | BC83: 131.27 | BD83: 134.14 | BE83: 125.45 | BF83: 124.68 | BG83: 134.89 | BH83: 126.23 | BI83: 126.14 | BJ83: 134.54 | BK83: 109.82 | BL83: 111.14 | BN83: 109.58
C84: =YEAR(D84)&MONTH(D84) -> 202512 | D84: 46021 | E84: 1869.17 | F84: 1910.26 | G84: 1886.88 | H84: 1721.39 | I84: 1793.6 | J84: 1852.57 | K84: 1841.67 | L84: 1708.18 | M84: 1584.66 | N84: 1685.61 | O84: 1786.06 | P84: 1733.37 | Q84: 6437.13 | R84: 114.9 | S84: 106.94 | T84: 123.3 | V84: 118.84 | W84: 124.5 | X84: 126.39 | Y84: 115.98 | Z84: 118.94 | AA84: 118.22 | AB84: 125.01 | AE84: 134.11 | AF84: 132.31 | AG84: 114.22 | AI84: 30 | AN84: 4348.64 | AP84: 4248.51 | AQ84: 4314.35 | AR84: 4240.53 | AS84: 4189.44 | AT84: 4192.82 | AU84: 4289.03 | AW84: 4274.37 | AX84: 115.1 | AY84: 4221.68 | BA84: 120.62 | BB84: 136.77 | BC84: 131.73 | BD84: 134.05 | BE84: 125.4 | BF84: 124.67 | BG84: 134.86 | BH84: 126.22 | BI84: 126.13 | BJ84: 134.47 | BK84: 111.15 | BL84: 111.8 | BN84: 110.92
C85: =YEAR(D85)&MONTH(D85) -> 202512 | D85: 46020 | E85: 1869.17 | F85: 1910.26 | G85: 1886.88 | H85: 1721.39 | I85: 1793.6 | J85: 1852.57 | K85: 1841.67 | L85: 1708.18 | M85: 1584.66 | N85: 1683.35 | O85: 1786.06 | P85: 1733.37 | Q85: 6437.13 | R85: 114.9 | S85: 108.54 | T85: 123.3 | V85: 118.84 | W85: 123.56 | X85: 126.26 | Y85: 116.18 | Z85: 119.07 | AA85: 118.22 | AB85: 125.01 | AE85: 134.11 | AF85: 132.31 | AG85: 115.22 | AO85: 11 | AP85: 4248.51 | AQ85: 4314.35 | AR85: 4260.33 | AS85: 4186.06 | AT85: 4213.25 | AU85: 4265.16 | AW85: 4224.82 | AX85: 115.07 | AY85: 4240.92 | AZ85: 4224.46 | BA85: 120.62 | BB85: 137.85 | BC85: 131.93 | BD85: 134.08 | BE85: 125.4 | BF85: 124.67 | BG85: 134.86 | BH85: 126.22 | BI85: 126.13 | BJ85: 134.47 | BK85: 111.82 | BL85: 112.13 | BN85: 111.58
C86: =YEAR(D86)&MONTH(D86) -> 202512 | D86: 46017 | E86: 1869.17 | F86: 1906.67 | G86: 1886.88 | H86: 1721.39 | I86: 1793.6 | J86: 1852.57 | K86: 1841.67 | L86: 1708.18 | M86: 1584.66 | N86: 1683.35 | O86: 1786.06 | P86: 1733.37 | Q86: 6437.13 | R86: 114.9 | S86: 108.54 | T86: 123.3 | V86: 118.84 | W86: 123.56 | X86: 126.01 | Y86: 116.83 | Z86: 119.19 | AA86: 118.32 | AB86: 125.01 | AE86: 133.77 | AF86: 132.31 | AG86: 115.22 | AO86: 11 | AP86: 4248.51 | AQ86: 4314.35 | AS86: 4186.06 | AT86: 4233.69 | AU86: 4233.33 | AW86: 4196.19 | AX86: 115.01 | AY86: 4240.92 | AZ86: 4224.46 | BA86: 120.62 | BB86: 137.94 | BC86: 131.93 | BD86: 134.08 | BE86: 125.73 | BF86: 124.67 | BG86: 134.86 | BH86: 126.22 | BI86: 126.13 | BJ86: 134.47 | BK86: 113.15 | BL86: 112.8 | BN86: 112.92
C87: =YEAR(D87)&MONTH(D87) -> 202512 | D87: 46014 | E87: 1869.17 | F87: 1906.67 | G87: 1886.88 | H87: 1721.39 | I87: 1793.6 | J87: 1852.57 | K87: 1841.67 | L87: 1708.18 | M87: 1584.66 | N87: 1683.35 | O87: 1786.06 | P87: 1733.37 | Q87: 6437.13 | R87: 114.9 | S87: 106.94 | T87: 123.3 | V87: 118.84 | W87: 123.7 | X87: 126.01 | Y87: 116.83 | Z87: 119.19 | AA87: 118.32 | AB87: 125.01 | AE87: 133.77 | AF87: 132.31 | AG87: 114.22 | AN87: 4206.11 | AO87: 9.67 | AP87: 4260 | AQ87: 4397.73 | AR87: 4281.01 | AS87: 4186.06 | AT87: 4185.65 | AU87: 4233.33 | AV87: 30 | AW87: 4181.46 | AX87: 114.89 | AY87: 4240.92 | AZ87: 4303.09 | BA87: 120.62 | BB87: 137.59 | BC87: 131.99 | BD87: 134.19 | BE87: 125.73 | BF87: 124.67 | BG87: 134.86 | BH87: 126.22 | BI87: 126.13 | BJ87: 134.47 | BK87: 113.15 | BL87: 112.8 | BN87: 112.92
C88: =YEAR(D88)&MONTH(D88) -> 202512 | D88: 46013 | E88: 1869.17 | F88: 1910.26 | G88: 1886.88 | H88: 1721.39 | I88: 1803.47 | J88: 1833.87 | K88: 1841.67 | L88: 1708.18 | M88: 1584.66 | N88: 1685.53 | O88: 1781.12 | P88: 1733.37 | Q88: 6437.13 | R88: 114.9 | S88: 108.94 | T88: 123.3 | V88: 118.84 | W88: 123.7 | X88: 125.76 | Y88: 116.52 | Z88: 119.07 | AA88: 118.32 | AB88: 125.01 | AE88: 133.77 | AF88: 132.31 | AG88: 115.47 | AN88: 4237.94 | AO88: 7 | AP88: 4246.11 | AQ88: 4397.73 | AR88: 4281.01 | AS88: 4219.82 | AT88: 4089.55 | AU88: 4151.58 | AV88: 30 | AW88: 4220.39 | AX88: 114.65 | AY88: 4268.05 | AZ88: 4303.09 | BA88: 120.62 | BB88: 137.42 | BC88: 131.99 | BD88: 134.19 | BE88: 125.73 | BF88: 124.67 | BG88: 134.86 | BH88: 126.16 | BI88: 126.13 | BJ88: 134.47 | BK88: 112.48 | BL88: 112.8 | BN88: 112.25
C89: =YEAR(D89)&MONTH(D89) -> 202512 | D89: 46010 | E89: 1844.33 | F89: 1901.22 | G89: 1862.03 | H89: 1782.3 | I89: 1803.47 | J89: 1833.87 | K89: 1841.67 | L89: 1691.62 | M89: 1584.66 | N89: 1685.53 | O89: 1781.12 | P89: 1733.37 | Q89: 6437.13 | R89: 114.9 | S89: 108.54 | T89: 122.97 | V89: 118.84 | W89: 123.51 | X89: 125.76 | Y89: 116.83 | Z89: 119.19 | AA89: 118.32 | AB89: 124.94 | AE89: 133.77 | AF89: 132.31 | AG89: 115.22 | AL89: 30 | AN89: 4237.94 | AO89: 7 | AP89: 4246.11 | AQ89: 4367.52 | AR89: 4199.78 | AS89: 4219.82 | AT89: 4089.55 | AU89: 4150.28 | AV89: 30 | AW89: 4257.29 | AX89: 114.6 | AY89: 4268.05 | AZ89: 4296.99 | BA89: 120.62 | BB89: 137.12 | BC89: 132.13 | BD89: 134.08 | BE89: 125.73 | BF89: 124.67 | BG89: 134.86 | BH89: 126.16 | BI89: 126.13 | BJ89: 134.47 | BK89: 113.15 | BL89: 112.8 | BN89: 112.92
C90: =YEAR(D90)&MONTH(D90) -> 202512 | D90: 46009 | E90: 1849.29 | F90: 1901.22 | G90: 1854.63 | H90: 1757.57 | I90: 1803.47 | J90: 1853.79 | K90: 1770.08 | L90: 1686.68 | M90: 1604.82 | N90: 1686.35 | O90: 1772.82 | P90: 1733.37 | Q90: 6542.44 | R90: 114.9 | S90: 108.52 | T90: 123 | V90: 118.84 | W90: 123.35 | X90: 125.76 | Y90: 117 | Z90: 119.57 | AA90: 118.32 | AB90: 124.81 | AE90: 133.77 | AF90: 131.32 | AG90: 115.2 | AL90: 30 | AN90: 4250.31 | AO90: 7 | AP90: 4245 | AQ90: 4367.52 | AR90: 4199.78 | AS90: 4219.82 | AT90: 4089.55 | AU90: 4150.28 | AV90: 30 | AW90: 4257.29 | AX90: 114.51 | AY90: 4268.05 | AZ90: 4296.99 | BA90: 119.68 | BB90: 137.37 | BC90: 132.52 | BD90: 134.29 | BE90: 125.4 | BF90: 124.67 | BG90: 134.46 | BH90: 126.32 | BI90: 126.13 | BJ90: 134.46 | BK90: 113.15 | BL90: 112.8 | BN90: 112.92
C91: =YEAR(D91)&MONTH(D91) -> 202512 | D91: 46008 | E91: 1857.98 | F91: 1901.22 | G91: 1854.63 | H91: 1810.3 | I91: 1811.7 | J91: 1863.25 | K91: 1704.33 | L91: 1674.94 | M91: 1602.54 | N91: 1694.01 | O91: 1778.65 | P91: 1703.4 | Q91: 6481.3 | R91: 114.9 | S91: 108.5 | T91: 123.56 | V91: 118.84 | W91: 123.2 | X91: 124.89 | Y91: 116.89 | Z91: 119.57 | AA91: 118.32 | AB91: 124.05 | AE91: 133.11 | AF91: 131.32 | AG91: 119.15 | AL91: 30 | AN91: 4264.54 | AO91: 7 | AP91: 4245 | AQ91: 4367.52 | AR91: 4188 | AS91: 4209.02 | AT91: 4089.55 | AU91: 4150.28 | AW91: 4285.99 | AX91: 115.2 | AY91: 4251.3 | AZ91: 4330.73 | BA91: 119.66 | BB91: 137.08 | BC91: 132.48 | BD91: 133.87 | BE91: 125.07 | BF91: 123.28 | BG91: 134.75 | BH91: 126.17 | BI91: 126.64 | BJ91: 134.45 | BK91: 113.15 | BL91: 112.47 | BN91: 112.48
C92: =YEAR(D92)&MONTH(D92) -> 202512 | D92: 46007 | E92: 1851.77 | F92: 1874.69 | G92: 1842.29 | H92: 1784.77 | I92: 1778.29 | J92: 1824.43 | K92: 1593.59 | L92: 1696.7 | M92: 1602.54 | N92: 1675.18 | O92: 1768.41 | P92: 1655.09 | Q92: 6497.82 | R92: 114.9 | S92: 108.48 | T92: 123.55 | V92: 118.84 | W92: 123.18 | X92: 124.64 | Y92: 116.87 | Z92: 119.44 | AA92: 118.32 | AB92: 124 | AE92: 133.52 | AF92: 131.82 | AG92: 118.54 | AL92: 30 | AN92: 4314.35 | AO92: 7 | AP92: 4241.25 | AQ92: 4349.39 | AR92: 4234.68 | AS92: 4215.32 | AT92: 4182.03 | AU92: 4150.28 | AW92: 4285.99 | AX92: 116.57 | AY92: 4253.9 | AZ92: 4290.88 | BA92: 119.65 | BB92: 135.47 | BC92: 131.34 | BD92: 132.5 | BE92: 123.92 | BF92: 123.28 | BG92: 134.86 | BH92: 126.17 | BI92: 126 | BJ92: 134.52 | BK92: 112.48 | BL92: 112.47 | BN92: 112.25
C93: =YEAR(D93)&MONTH(D93) -> 202512 | D93: 46006 | E93: 1839.37 | F93: 1874.69 | G93: 1842.29 | H93: 1755.15 | I93: 1778.29 | J93: 1815.89 | K93: 1703.46 | L93: 1698.51 | M93: 1575.38 | N93: 1674.44 | O93: 1754.61 | P93: 1707.84 | Q93: 6418.97 | R93: 114.9 | S93: 109.06 | T93: 123.44 | V93: 118.96 | W93: 123.31 | X93: 124.64 | Y93: 116.68 | Z93: 119.32 | AA93: 118.62 | AB93: 124.16 | AE93: 133.95 | AF93: 132.33 | AG93: 119.63 | AL93: 30 | AO93: 7 | AP93: 4289 | AQ93: 4349.39 | AR93: 4234.68 | AS93: 4200.41 | AT93: 4127.6 | AU93: 4147.24 | AW93: 4285.99 | AX93: 119.31 | AY93: 4256.11 | AZ93: 4290.88 | BA93: 117.87 | BB93: 136.12 | BC93: 131.7 | BD93: 131.82 | BE93: 126.69 | BF93: 123.28 | BG93: 134.6 | BH93: 126.3 | BI93: 126.38 | BJ93: 135.09 | BK93: 112.48 | BL93: 113.47 | BN93: 112.25
C94: =YEAR(D94)&MONTH(D94) -> 202512 | D94: 46003 | E94: 1824.53 | F94: 1842.76 | G94: 1837.35 | H94: 1783.97 | I94: 1765.5 | J94: 1815.89 | K94: 1742.08 | L94: 1699.25 | M94: 1552.79 | N94: 1646.83 | O94: 1746.77 | P94: 1720.88 | Q94: 6480.35 | R94: 114.9 | S94: 109.6 | T94: 124.38 | V94: 119.4 | W94: 123.41 | X94: 125.39 | Y94: 118.07 | Z94: 120.07 | AA94: 118.62 | AB94: 124.63 | AE94: 134.23 | AF94: 133.86 | AG94: 118.66 | AO94: 7 | AP94: 4308.5 | AQ94: 4404.23 | AR94: 4234.68 | AS94: 4219.82 | AT94: 4127.6 | AW94: 4225.73 | AX94: 123.92 | AY94: 4256.11 | BA94: 119.65 | BB94: 135.79 | BC94: 132.36 | BD94: 133.29 | BE94: 127.63 | BF94: 123.28 | BG94: 135.07 | BH94: 127.58 | BI94: 126.5 | BJ94: 135.22 | BK94: 113.82 | BL94: 114.47 | BN94: 113.92
C95: =YEAR(D95)&MONTH(D95) -> 202512 | D95: 46002 | E95: 1831.93 | F95: 1852.91 | G95: 1837.35 | H95: 1762.56 | I95: 1744.78 | J95: 1808.85 | K95: 1742.08 | L95: 1666.03 | M95: 1517.96 | N95: 1645.7 | O95: 1747.49 | P95: 1713.4 | Q95: 6629.09 | R95: 115.23 | S95: 110.37 | T95: 125.2 | V95: 119.4 | W95: 125.67 | X95: 126.08 | Y95: 119.37 | Z95: 120.13 | AA95: 119.32 | AB95: 125.27 | AE95: 133.94 | AF95: 133.49 | AG95: 118.93 | AI95: 5 | AN95: 4194.07 | AO95: 7 | AP95: 4308.5 | AQ95: 4404.23 | AR95: 4321.44 | AS95: 4219.82 | AT95: 4161.94 | AW95: 4225.73 | AX95: 123.76 | AY95: 4256.11 | BA95: 119.9 | BB95: 136.88 | BC95: 132.75 | BD95: 133.41 | BE95: 127.38 | BF95: 123.28 | BG95: 134.66 | BH95: 127.46 | BI95: 126.5 | BJ95: 135.19 | BK95: 114.48 | BL95: 114.8 | BN95: 114.58
C96: =YEAR(D96)&MONTH(D96) -> 202512 | D96: 46001 | E96: 1824.47 | F96: 1829.24 | G96: 1829.94 | H96: 1762.56 | I96: 1778.66 | J96: 1803.14 | K96: 1701.48 | L96: 1666.03 | M96: 1517.96 | N96: 1672.12 | O96: 1742.97 | P96: 1680.09 | Q96: 6782.05 | R96: 115.23 | S96: 110.65 | T96: 126.11 | V96: 119.4 | W96: 125.29 | X96: 125.89 | Y96: 119.15 | Z96: 120.88 | AA96: 119.32 | AB96: 125.18 | AE96: 134.07 | AF96: 132.48 | AG96: 118.8 | AI96: 5 | AN96: 4231.35 | AO96: 7 | AP96: 4308.5 | AQ96: 4404.23 | AR96: 4386.51 | AS96: 4234.25 | AT96: 4188.26 | AW96: 4267.46 | AX96: 123.72 | AY96: 4305.91 | BA96: 120.14 | BB96: 135.65 | BC96: 132.86 | BD96: 133.59 | BE96: 127.18 | BF96: 123.28 | BG96: 134.51 | BH96: 127.6 | BI96: 126.5 | BJ96: 135.17 | BK96: 115.72 | BL96: 115.13 | BN96: 115.58
C97: =YEAR(D97)&MONTH(D97) -> 202512 | D97: 46000 | E97: 1837.81 | F97: 1829.24 | G97: 1835.78 | H97: 1764.18 | I97: 1778.66 | J97: 1773.57 | K97: 1722.2 | L97: 1669.07 | M97: 1512.51 | N97: 1644.47 | O97: 1742.16 | P97: 1752.44 | Q97: 6678.55 | R97: 115.56 | S97: 110.83 | T97: 126.13 | V97: 119.21 | W97: 124.66 | X97: 125.93 | Y97: 120.06 | Z97: 121.13 | AA97: 119.32 | AB97: 124.92 | AE97: 134.47 | AF97: 133.14 | AG97: 117.1 | AI97: 5 | AN97: 4231.35 | AP97: 4279.11 | AQ97: 4404.23 | AR97: 4316.88 | AS97: 4208.16 | AT97: 4190.28 | AW97: 4267.46 | AX97: 123.41 | AY97: 4305.91 | BA97: 118.84 | BB97: 135.6 | BC97: 132.68 | BD97: 133.41 | BE97: 127.18 | BF97: 126.17 | BG97: 133.94 | BH97: 125.17 | BI97: 126.5 | BJ97: 134.35 | BK97: 116.05 | BL97: 115.47 | BN97: 115.92
C98: =YEAR(D98)&MONTH(D98) -> 202512 | D98: 45999 | E98: 1837.81 | F98: 1829.5 | G98: 1830.84 | H98: 1780.68 | I98: 1777.84 | J98: 1782.16 | K98: 1722.2 | L98: 1676.01 | M98: 1518.54 | N98: 1654.21 | O98: 1742.97 | P98: 1759.82 | Q98: 6617.11 | S98: 110.93 | T98: 126.98 | V98: 119.15 | W98: 124.64 | X98: 125.93 | Y98: 120.58 | Z98: 121.88 | AA98: 119.95 | AB98: 124.49 | AE98: 133.67 | AF98: 133.14 | AG98: 117.68 | AI98: 5 | AN98: 4231.35 | AP98: 4316 | AR98: 4339.1 | AS98: 4198.33 | AT98: 4219.82 | AU98: 4204.46 | AW98: 4309.18 | AX98: 123.25 | AY98: 4323.21 | AZ98: 4404.08 | BA98: 119.7 | BB98: 135.93 | BC98: 132.8 | BD98: 133.56 | BE98: 127.18 | BF98: 126.67 | BG98: 133.93 | BH98: 125.17 | BI98: 126.13 | BJ98: 133.14 | BK98: 116.05 | BL98: 115.8 | BN98: 115.92
C99: =YEAR(D99)&MONTH(D99) -> 202512 | D99: 45996 | E99: 1840.24 | F99: 1827.77 | G99: 1830.84 | H99: 1780.68 | I99: 1774.67 | J99: 1793.85 | K99: 1710.2 | L99: 1676.01 | M99: 1518.54 | N99: 1645.43 | O99: 1744.79 | P99: 1755.82 | Q99: 6796 | S99: 110.83 | T99: 126.2 | V99: 119.55 | W99: 123.85 | X99: 125.17 | Y99: 119.96 | Z99: 120.86 | AA99: 119.95 | AB99: 124.24 | AE99: 133.22 | AF99: 131.82 | AG99: 117.46 | AI99: 5 | AN99: 4231.35 | AP99: 4313.8 | AR99: 4339.1 | AS99: 4198.33 | AT99: 4176.16 | AU99: 4204.46 | AW99: 4309.18 | AX99: 118.74 | AY99: 4323.21 | AZ99: 4404.08 | BA99: 122.46 | BB99: 135.86 | BC99: 132.9 | BD99: 133.39 | BE99: 127.87 | BF99: 126.67 | BG99: 133.9 | BH99: 126.41 | BI99: 126.13 | BJ99: 133.67 | BK99: 116.05 | BL99: 115.8 | BN99: 115.92
C100: =YEAR(D100)&MONTH(D100) -> 202512 | D100: 45995 | E100: 1815.43 | F100: 1825.97 | G100: 1830.84 | H100: 1746.54 | I100: 1771.38 | J100: 1760.04 | K100: 1674.57 | L100: 1639.15 | M100: 1563.29 | N100: 1643.79 | O100: 1734.77 | P100: 1750.6 | Q100: 6796 | S100: 110.14 | T100: 125.74 | V100: 119.94 | W100: 123.09 | X100: 125.07 | Y100: 119.93 | Z100: 120.86 | AA100: 119.95 | AB100: 123.98 | AE100: 133.47 | AF100: 131.57 | AG100: 117.42 | AN100: 4240.67 | AP100: 4313.8 | AR100: 4301.18 | AT100: 4176.16 | AU100: 4204.46 | AW100: 4309.18 | AX100: 120.46 | AY100: 4323.21 | AZ100: 4380.94 | BA100: 125.21 | BB100: 136.61 | BC100: 131.84 | BD100: 132.92 | BE100: 127.93 | BF100: 126.67 | BG100: 134.08 | BH100: 126.41 | BI100: 126.13 | BJ100: 132.3 | BK100: 116.05 | BL100: 115.8 | BN100: 115.92
...

Sheet Modelo Crushing Margin LIQ
B1: fonte Abiove | F1: Versus Paridade de Exportação | G1: =AVERAGE(G3:G65) -> #REF! | H1: =AVERAGE(H3:H65) -> #REF! | I1: =AVERAGE(I3:I65) -> #REF! | J1: =AVERAGE(J3:J65) -> #REF! | K1: =AVERAGE(K3:K65) -> #REF! | L1: =AVERAGE(L3:L65) -> #REF! | M1: =AVERAGE(M3:M65) -> #REF! | Q1: Versus Disponivel | R1: =AVERAGE(R3:R65) -> #REF! | S1: =AVERAGE(S3:S65) -> #REF! | X1: =AVERAGE(X3:X65) -> #REF!
B2: Teor Oleo | C2: 0.208 | E2: ANO | F2: Data | G2: Sorriso | H2: Rondonopolis | I2: Cascavel | J2: Londrina | K2: Ijui | L2: Passo Fundo | M2: LRV | Q2: Data | R2: Sorriso | S2: Rondonopolis | T2: Cascavel | U2: Londrina | V2: Ijui | W2: Passo Fundo | X2: LRV | AL2: LRV
B3: Teor Farelo | C3: 0.75 | E3: =YEAR(F3) -> 2021 | F3: =+'Modelo Soja'!BA3 -> 44197 | G3: =+(('Modelo Farelo'!AB3*(1+$C$8))*$C$3+('Modelo Oleo'!AA3*(1))*$C$2)-('Modelo Soja'!AT3/60*1000)-$C$6 -> #REF! | H3: =+(('Modelo Farelo'!AC3*(1+$C$8))*$C$3+('Modelo Oleo'!AB3*(1))*$C$2)-('Modelo Soja'!AU3/60*1000)-$C$6 -> #REF! | I3: =+(('Modelo Farelo'!AD3*(1+$C$8))*$C$3+('Modelo Oleo'!AC3*(1))*$C$2)-('Modelo Soja'!AV3/60*1000)-$C$6 -> #REF! | J3: =+(('Modelo Farelo'!AE3*(1+$C$8))*($C$3+1%)+('Modelo Oleo'!AD3*(1))*($C$2-1%))-('Modelo Soja'!AW3/60*1000)-$C$6 -> #REF! | K3: =+(('Modelo Farelo'!AF3*(1+$C$8))*($C$3+1.5%)+('Modelo Oleo'!AE3*(1))*($C$2-1.5%))-('Modelo Soja'!AX3/60*1000)-$C$6 -> #REF! | L3: =+(('Modelo Farelo'!AG3*(1+$C$8))*($C$3+1.5%)+('Modelo Oleo'!AF3*(1))*($C$2-1.5%))-('Modelo Soja'!AY3/60*1000)-$C$6 -> #REF! | M3: =+(('Modelo Farelo'!AH3*(1+$C$8))*$C$3+('Modelo Oleo'!AG3*(1))*$C$2)-('Modelo Soja'!BM3/60*1000)-$C$6 -> #REF! | Q3: =+F3 -> 44197 | R3: =+(('Modelo Farelo'!AB3*(1+$C$8))*$C$3+('Modelo Oleo'!AA3*(1))*$C$2)-('Modelo Soja'!AK3/60*1000)-$C$6 -> #REF! | S3: =+(('Modelo Farelo'!AC3*(1+$C$8))*$C$3+('Modelo Oleo'!AB3*(1))*$C$2)-('Modelo Soja'!AA3/60*1000)-$C$6 -> #REF! | X3: =+(('Modelo Farelo'!AH3*(1+$C$8))*$C$3+('Modelo Oleo'!AG3*(1))*$C$2)-('Modelo Soja'!AL3/60*1000)-$C$6 -> #REF! | AK3: 2021 | AL3: =AVERAGEIF(E:E,AK3,M:M) -> #REF!
B4: Casca | C4: 0 | E4: =YEAR(F4) -> 2021 | F4: =+'Modelo Soja'!BA4 -> 44228 | G4: =+(('Modelo Farelo'!AB4*(1+$C$8))*$C$3+('Modelo Oleo'!AA4*(1))*$C$2)-('Modelo Soja'!AT4/60*1000)-$C$6 -> #REF! | H4: =+(('Modelo Farelo'!AC4*(1+$C$8))*$C$3+('Modelo Oleo'!AB4*(1))*$C$2)-('Modelo Soja'!AU4/60*1000)-$C$6 -> #REF! | I4: =+(('Modelo Farelo'!AD4*(1+$C$8))*$C$3+('Modelo Oleo'!AC4*(1))*$C$2)-('Modelo Soja'!AV4/60*1000)-$C$6 -> #REF! | J4: =+(('Modelo Farelo'!AE4*(1+$C$8))*($C$3+1%)+('Modelo Oleo'!AD4*(1))*($C$2-1%))-('Modelo Soja'!AW4/60*1000)-$C$6 -> #REF! | K4: =+(('Modelo Farelo'!AF4*(1+$C$8))*($C$3+1.5%)+('Modelo Oleo'!AE4*(1))*($C$2-1.5%))-('Modelo Soja'!AX4/60*1000)-$C$6 -> #REF! | L4: =+(('Modelo Farelo'!AG4*(1+$C$8))*($C$3+1.5%)+('Modelo Oleo'!AF4*(1))*($C$2-1.5%))-('Modelo Soja'!AY4/60*1000)-$C$6 -> #REF! | M4: =+(('Modelo Farelo'!AH4*(1+$C$8))*$C$3+('Modelo Oleo'!AG4*(1))*$C$2)-('Modelo Soja'!BM4/60*1000)-$C$6 -> #REF! | Q4: =+F4 -> 44228 | R4: =+(('Modelo Farelo'!AB4*(1+$C$8))*$C$3+('Modelo Oleo'!AA4*(1))*$C$2)-('Modelo Soja'!AK4/60*1000)-$C$6 -> #REF! | S4: =+(('Modelo Farelo'!AC4*(1+$C$8))*$C$3+('Modelo Oleo'!AB4*(1))*$C$2)-('Modelo Soja'!AA4/60*1000)-$C$6 -> #REF! | X4: =+(('Modelo Farelo'!AH4*(1+$C$8))*$C$3+('Modelo Oleo'!AG4*(1))*$C$2)-('Modelo Soja'!AL4/60*1000)-$C$6 -> #REF! | AK4: =+AK3+1 -> 2022 | AL4: =AVERAGEIF(E:E,AK4,M:M) -> #REF!
E5: =YEAR(F5) -> 2021 | F5: =+'Modelo Soja'!BA5 -> 44256 | G5: =+(('Modelo Farelo'!AB5*(1+$C$8))*$C$3+('Modelo Oleo'!AA5*(1))*$C$2)-('Modelo Soja'!AT5/60*1000)-$C$6 -> #REF! | H5: =+(('Modelo Farelo'!AC5*(1+$C$8))*$C$3+('Modelo Oleo'!AB5*(1))*$C$2)-('Modelo Soja'!AU5/60*1000)-$C$6 -> #REF! | I5: =+(('Modelo Farelo'!AD5*(1+$C$8))*$C$3+('Modelo Oleo'!AC5*(1))*$C$2)-('Modelo Soja'!AV5/60*1000)-$C$6 -> #REF! | J5: =+(('Modelo Farelo'!AE5*(1+$C$8))*($C$3+1%)+('Modelo Oleo'!AD5*(1))*($C$2-1%))-('Modelo Soja'!AW5/60*1000)-$C$6 -> #REF! | K5: =+(('Modelo Farelo'!AF5*(1+$C$8))*($C$3+1.5%)+('Modelo Oleo'!AE5*(1))*($C$2-1.5%))-('Modelo Soja'!AX5/60*1000)-$C$6 -> #REF! | L5: =+(('Modelo Farelo'!AG5*(1+$C$8))*($C$3+1.5%)+('Modelo Oleo'!AF5*(1))*($C$2-1.5%))-('Modelo Soja'!AY5/60*1000)-$C$6 -> #REF! | M5: =+(('Modelo Farelo'!AH5*(1+$C$8))*$C$3+('Modelo Oleo'!AG5*(1))*$C$2)-('Modelo Soja'!BM5/60*1000)-$C$6 -> #REF! | Q5: =+F5 -> 44256 | R5: =+(('Modelo Farelo'!AB5*(1+$C$8))*$C$3+('Modelo Oleo'!AA5*(1))*$C$2)-('Modelo Soja'!AK5/60*1000)-$C$6 -> #REF! | S5: =+(('Modelo Farelo'!AC5*(1+$C$8))*$C$3+('Modelo Oleo'!AB5*(1))*$C$2)-('Modelo Soja'!AA5/60*1000)-$C$6 -> #REF! | X5: =+(('Modelo Farelo'!AH5*(1+$C$8))*$C$3+('Modelo Oleo'!AG5*(1))*$C$2)-('Modelo Soja'!AL5/60*1000)-$C$6 -> #REF! | AK5: =+AK4+1 -> 2023 | AL5: =AVERAGEIF(E:E,AK5,M:M) -> #REF!
B6: Custo Industrial | C6: 160 | E6: =YEAR(F6) -> 2021 | F6: =+'Modelo Soja'!BA6 -> 44287 | G6: =+(('Modelo Farelo'!AB6*(1+$C$8))*$C$3+('Modelo Oleo'!AA6*(1))*$C$2)-('Modelo Soja'!AT6/60*1000)-$C$6 -> #REF! | H6: =+(('Modelo Farelo'!AC6*(1+$C$8))*$C$3+('Modelo Oleo'!AB6*(1))*$C$2)-('Modelo Soja'!AU6/60*1000)-$C$6 -> #REF! | I6: =+(('Modelo Farelo'!AD6*(1+$C$8))*$C$3+('Modelo Oleo'!AC6*(1))*$C$2)-('Modelo Soja'!AV6/60*1000)-$C$6 -> #REF! | J6: =+(('Modelo Farelo'!AE6*(1+$C$8))*($C$3+1%)+('Modelo Oleo'!AD6*(1))*($C$2-1%))-('Modelo Soja'!AW6/60*1000)-$C$6 -> #REF! | K6: =+(('Modelo Farelo'!AF6*(1+$C$8))*($C$3+1.5%)+('Modelo Oleo'!AE6*(1))*($C$2-1.5%))-('Modelo Soja'!AX6/60*1000)-$C$6 -> #REF! | L6: =+(('Modelo Farelo'!AG6*(1+$C$8))*($C$3+1.5%)+('Modelo Oleo'!AF6*(1))*($C$2-1.5%))-('Modelo Soja'!AY6/60*1000)-$C$6 -> #REF! | M6: =+(('Modelo Farelo'!AH6*(1+$C$8))*$C$3+('Modelo Oleo'!AG6*(1))*$C$2)-('Modelo Soja'!BM6/60*1000)-$C$6 -> #REF! | Q6: =+F6 -> 44287 | R6: =+(('Modelo Farelo'!AB6*(1+$C$8))*$C$3+('Modelo Oleo'!AA6*(1))*$C$2)-('Modelo Soja'!AK6/60*1000)-$C$6 -> #REF! | S6: =+(('Modelo Farelo'!AC6*(1+$C$8))*$C$3+('Modelo Oleo'!AB6*(1))*$C$2)-('Modelo Soja'!AA6/60*1000)-$C$6 -> #REF! | X6: =+(('Modelo Farelo'!AH6*(1+$C$8))*$C$3+('Modelo Oleo'!AG6*(1))*$C$2)-('Modelo Soja'!AL6/60*1000)-$C$6 -> #REF! | AK6: =+AK5+1 -> 2024 | AL6: =AVERAGEIF(E:E,AK6,M:M) -> #REF!
E7: =YEAR(F7) -> 2021 | F7: =+'Modelo Soja'!BA7 -> 44317 | G7: =+(('Modelo Farelo'!AB7*(1+$C$8))*$C$3+('Modelo Oleo'!AA7*(1))*$C$2)-('Modelo Soja'!AT7/60*1000)-$C$6 -> #REF! | H7: =+(('Modelo Farelo'!AC7*(1+$C$8))*$C$3+('Modelo Oleo'!AB7*(1))*$C$2)-('Modelo Soja'!AU7/60*1000)-$C$6 -> #REF! | I7: =+(('Modelo Farelo'!AD7*(1+$C$8))*$C$3+('Modelo Oleo'!AC7*(1))*$C$2)-('Modelo Soja'!AV7/60*1000)-$C$6 -> #REF! | J7: =+(('Modelo Farelo'!AE7*(1+$C$8))*($C$3+1%)+('Modelo Oleo'!AD7*(1))*($C$2-1%))-('Modelo Soja'!AW7/60*1000)-$C$6 -> #REF! | K7: =+(('Modelo Farelo'!AF7*(1+$C$8))*($C$3+1.5%)+('Modelo Oleo'!AE7*(1))*($C$2-1.5%))-('Modelo Soja'!AX7/60*1000)-$C$6 -> #REF! | L7: =+(('Modelo Farelo'!AG7*(1+$C$8))*($C$3+1.5%)+('Modelo Oleo'!AF7*(1))*($C$2-1.5%))-('Modelo Soja'!AY7/60*1000)-$C$6 -> #REF! | M7: =+(('Modelo Farelo'!AH7*(1+$C$8))*$C$3+('Modelo Oleo'!AG7*(1))*$C$2)-('Modelo Soja'!BM7/60*1000)-$C$6 -> #REF! | Q7: =+F7 -> 44317 | R7: =+(('Modelo Farelo'!AB7*(1+$C$8))*$C$3+('Modelo Oleo'!AA7*(1))*$C$2)-('Modelo Soja'!AK7/60*1000)-$C$6 -> #REF! | S7: =+(('Modelo Farelo'!AC7*(1+$C$8))*$C$3+('Modelo Oleo'!AB7*(1))*$C$2)-('Modelo Soja'!AA7/60*1000)-$C$6 -> #REF! | X7: =+(('Modelo Farelo'!AH7*(1+$C$8))*$C$3+('Modelo Oleo'!AG7*(1))*$C$2)-('Modelo Soja'!AL7/60*1000)-$C$6 -> #REF! | AK7: =+AK6+1 -> 2025 | AL7: =AVERAGEIF(E:E,AK7,M:M) -> #REF!
B8: Pis/Cofins | C8: 0.0225 | E8: =YEAR(F8) -> 2021 | F8: =+'Modelo Soja'!BA8 -> 44348 | G8: =+(('Modelo Farelo'!AB8*(1+$C$8))*$C$3+('Modelo Oleo'!AA8*(1))*$C$2)-('Modelo Soja'!AT8/60*1000)-$C$6 -> #REF! | H8: =+(('Modelo Farelo'!AC8*(1+$C$8))*$C$3+('Modelo Oleo'!AB8*(1))*$C$2)-('Modelo Soja'!AU8/60*1000)-$C$6 -> #REF! | I8: =+(('Modelo Farelo'!AD8*(1+$C$8))*$C$3+('Modelo Oleo'!AC8*(1))*$C$2)-('Modelo Soja'!AV8/60*1000)-$C$6 -> #REF! | J8: =+(('Modelo Farelo'!AE8*(1+$C$8))*($C$3+1%)+('Modelo Oleo'!AD8*(1))*($C$2-1%))-('Modelo Soja'!AW8/60*1000)-$C$6 -> #REF! | K8: =+(('Modelo Farelo'!AF8*(1+$C$8))*($C$3+1.5%)+('Modelo Oleo'!AE8*(1))*($C$2-1.5%))-('Modelo Soja'!AX8/60*1000)-$C$6 -> #REF! | L8: =+(('Modelo Farelo'!AG8*(1+$C$8))*($C$3+1.5%)+('Modelo Oleo'!AF8*(1))*($C$2-1.5%))-('Modelo Soja'!AY8/60*1000)-$C$6 -> #REF! | M8: =+(('Modelo Farelo'!AH8*(1+$C$8))*$C$3+('Modelo Oleo'!AG8*(1))*$C$2)-('Modelo Soja'!BM8/60*1000)-$C$6 -> #REF! | Q8: =+F8 -> 44348 | R8: =+(('Modelo Farelo'!AB8*(1+$C$8))*$C$3+('Modelo Oleo'!AA8*(1))*$C$2)-('Modelo Soja'!AK8/60*1000)-$C$6 -> #REF! | S8: =+(('Modelo Farelo'!AC8*(1+$C$8))*$C$3+('Modelo Oleo'!AB8*(1))*$C$2)-('Modelo Soja'!AA8/60*1000)-$C$6 -> #REF! | X8: =+(('Modelo Farelo'!AH8*(1+$C$8))*$C$3+('Modelo Oleo'!AG8*(1))*$C$2)-('Modelo Soja'!AL8/60*1000)-$C$6 -> #REF! | AK8: =+AK7+1 -> 2026 | AL8: =AVERAGEIF(E:E,AK8,M:M) -> #REF!
E9: =YEAR(F9) -> 2021 | F9: =+'Modelo Soja'!BA9 -> 44378 | G9: =+(('Modelo Farelo'!AB9*(1+$C$8))*$C$3+('Modelo Oleo'!AA9*(1))*$C$2)-('Modelo Soja'!AT9/60*1000)-$C$6 -> #REF! | H9: =+(('Modelo Farelo'!AC9*(1+$C$8))*$C$3+('Modelo Oleo'!AB9*(1))*$C$2)-('Modelo Soja'!AU9/60*1000)-$C$6 -> #REF! | I9: =+(('Modelo Farelo'!AD9*(1+$C$8))*$C$3+('Modelo Oleo'!AC9*(1))*$C$2)-('Modelo Soja'!AV9/60*1000)-$C$6 -> #REF! | J9: =+(('Modelo Farelo'!AE9*(1+$C$8))*($C$3+1%)+('Modelo Oleo'!AD9*(1))*($C$2-1%))-('Modelo Soja'!AW9/60*1000)-$C$6 -> #REF! | K9: =+(('Modelo Farelo'!AF9*(1+$C$8))*($C$3+1.5%)+('Modelo Oleo'!AE9*(1))*($C$2-1.5%))-('Modelo Soja'!AX9/60*1000)-$C$6 -> #REF! | L9: =+(('Modelo Farelo'!AG9*(1+$C$8))*($C$3+1.5%)+('Modelo Oleo'!AF9*(1))*($C$2-1.5%))-('Modelo Soja'!AY9/60*1000)-$C$6 -> #REF! | M9: =+(('Modelo Farelo'!AH9*(1+$C$8))*$C$3+('Modelo Oleo'!AG9*(1))*$C$2)-('Modelo Soja'!BM9/60*1000)-$C$6 -> #REF! | Q9: =+F9 -> 44378 | R9: =+(('Modelo Farelo'!AB9*(1+$C$8))*$C$3+('Modelo Oleo'!AA9*(1))*$C$2)-('Modelo Soja'!AK9/60*1000)-$C$6 -> #REF! | S9: =+(('Modelo Farelo'!AC9*(1+$C$8))*$C$3+('Modelo Oleo'!AB9*(1))*$C$2)-('Modelo Soja'!AA9/60*1000)-$C$6 -> #REF! | X9: =+(('Modelo Farelo'!AH9*(1+$C$8))*$C$3+('Modelo Oleo'!AG9*(1))*$C$2)-('Modelo Soja'!AL9/60*1000)-$C$6 -> #REF!
E10: =YEAR(F10) -> 2021 | F10: =+'Modelo Soja'!BA10 -> 44409 | G10: =+(('Modelo Farelo'!AB10*(1+$C$8))*$C$3+('Modelo Oleo'!AA10*(1))*$C$2)-('Modelo Soja'!AT10/60*1000)-$C$6 -> #REF! | H10: =+(('Modelo Farelo'!AC10*(1+$C$8))*$C$3+('Modelo Oleo'!AB10*(1))*$C$2)-('Modelo Soja'!AU10/60*1000)-$C$6 -> #REF! | I10: =+(('Modelo Farelo'!AD10*(1+$C$8))*$C$3+('Modelo Oleo'!AC10*(1))*$C$2)-('Modelo Soja'!AV10/60*1000)-$C$6 -> #REF! | J10: =+(('Modelo Farelo'!AE10*(1+$C$8))*($C$3+1%)+('Modelo Oleo'!AD10*(1))*($C$2-1%))-('Modelo Soja'!AW10/60*1000)-$C$6 -> #REF! | K10: =+(('Modelo Farelo'!AF10*(1+$C$8))*($C$3+1.5%)+('Modelo Oleo'!AE10*(1))*($C$2-1.5%))-('Modelo Soja'!AX10/60*1000)-$C$6 -> #REF! | L10: =+(('Modelo Farelo'!AG10*(1+$C$8))*($C$3+1.5%)+('Modelo Oleo'!AF10*(1))*($C$2-1.5%))-('Modelo Soja'!AY10/60*1000)-$C$6 -> #REF! | M10: =+(('Modelo Farelo'!AH10*(1+$C$8))*$C$3+('Modelo Oleo'!AG10*(1))*$C$2)-('Modelo Soja'!BM10/60*1000)-$C$6 -> #REF! | Q10: =+F10 -> 44409 | R10: =+(('Modelo Farelo'!AB10*(1+$C$8))*$C$3+('Modelo Oleo'!AA10*(1))*$C$2)-('Modelo Soja'!AK10/60*1000)-$C$6 -> #REF! | S10: =+(('Modelo Farelo'!AC10*(1+$C$8))*$C$3+('Modelo Oleo'!AB10*(1))*$C$2)-('Modelo Soja'!AA10/60*1000)-$C$6 -> #REF! | X10: =+(('Modelo Farelo'!AH10*(1+$C$8))*$C$3+('Modelo Oleo'!AG10*(1))*$C$2)-('Modelo Soja'!AL10/60*1000)-$C$6 -> #REF! | AK10: 2021 | AL10: =AVERAGEIF(E:E,AK3,X:X) -> #REF!
E11: =YEAR(F11) -> 2021 | F11: =+'Modelo Soja'!BA11 -> 44440 | G11: =+(('Modelo Farelo'!AB11*(1+$C$8))*$C$3+('Modelo Oleo'!AA11*(1))*$C$2)-('Modelo Soja'!AT11/60*1000)-$C$6 -> #REF! | H11: =+(('Modelo Farelo'!AC11*(1+$C$8))*$C$3+('Modelo Oleo'!AB11*(1))*$C$2)-('Modelo Soja'!AU11/60*1000)-$C$6 -> #REF! | I11: =+(('Modelo Farelo'!AD11*(1+$C$8))*$C$3+('Modelo Oleo'!AC11*(1))*$C$2)-('Modelo Soja'!AV11/60*1000)-$C$6 -> #REF! | J11: =+(('Modelo Farelo'!AE11*(1+$C$8))*($C$3+1%)+('Modelo Oleo'!AD11*(1))*($C$2-1%))-('Modelo Soja'!AW11/60*1000)-$C$6 -> #REF! | K11: =+(('Modelo Farelo'!AF11*(1+$C$8))*($C$3+1.5%)+('Modelo Oleo'!AE11*(1))*($C$2-1.5%))-('Modelo Soja'!AX11/60*1000)-$C$6 -> #REF! | L11: =+(('Modelo Farelo'!AG11*(1+$C$8))*($C$3+1.5%)+('Modelo Oleo'!AF11*(1))*($C$2-1.5%))-('Modelo Soja'!AY11/60*1000)-$C$6 -> #REF! | M11: =+(('Modelo Farelo'!AH11*(1+$C$8))*$C$3+('Modelo Oleo'!AG11*(1))*$C$2)-('Modelo Soja'!BM11/60*1000)-$C$6 -> #REF! | Q11: =+F11 -> 44440 | R11: =+(('Modelo Farelo'!AB11*(1+$C$8))*$C$3+('Modelo Oleo'!AA11*(1))*$C$2)-('Modelo Soja'!AK11/60*1000)-$C$6 -> #REF! | S11: =+(('Modelo Farelo'!AC11*(1+$C$8))*$C$3+('Modelo Oleo'!AB11*(1))*$C$2)-('Modelo Soja'!AA11/60*1000)-$C$6 -> #REF! | X11: =+(('Modelo Farelo'!AH11*(1+$C$8))*$C$3+('Modelo Oleo'!AG11*(1))*$C$2)-('Modelo Soja'!AL11/60*1000)-$C$6 -> #REF! | AK11: =+AK10+1 -> 2022 | AL11: =AVERAGEIF(E:E,AK4,X:X) -> #REF!
E12: =YEAR(F12) -> 2021 | F12: =+'Modelo Soja'!BA12 -> 44470 | G12: =+(('Modelo Farelo'!AB12*(1+$C$8))*$C$3+('Modelo Oleo'!AA12*(1))*$C$2)-('Modelo Soja'!AT12/60*1000)-$C$6 -> #REF! | H12: =+(('Modelo Farelo'!AC12*(1+$C$8))*$C$3+('Modelo Oleo'!AB12*(1))*$C$2)-('Modelo Soja'!AU12/60*1000)-$C$6 -> #REF! | I12: =+(('Modelo Farelo'!AD12*(1+$C$8))*$C$3+('Modelo Oleo'!AC12*(1))*$C$2)-('Modelo Soja'!AV12/60*1000)-$C$6 -> #REF! | J12: =+(('Modelo Farelo'!AE12*(1+$C$8))*($C$3+1%)+('Modelo Oleo'!AD12*(1))*($C$2-1%))-('Modelo Soja'!AW12/60*1000)-$C$6 -> #REF! | K12: =+(('Modelo Farelo'!AF12*(1+$C$8))*($C$3+1.5%)+('Modelo Oleo'!AE12*(1))*($C$2-1.5%))-('Modelo Soja'!AX12/60*1000)-$C$6 -> #REF! | L12: =+(('Modelo Farelo'!AG12*(1+$C$8))*($C$3+1.5%)+('Modelo Oleo'!AF12*(1))*($C$2-1.5%))-('Modelo Soja'!AY12/60*1000)-$C$6 -> #REF! | M12: =+(('Modelo Farelo'!AH12*(1+$C$8))*$C$3+('Modelo Oleo'!AG12*(1))*$C$2)-('Modelo Soja'!BM12/60*1000)-$C$6 -> #REF! | Q12: =+F12 -> 44470 | R12: =+(('Modelo Farelo'!AB12*(1+$C$8))*$C$3+('Modelo Oleo'!AA12*(1))*$C$2)-('Modelo Soja'!AK12/60*1000)-$C$6 -> #REF! | S12: =+(('Modelo Farelo'!AC12*(1+$C$8))*$C$3+('Modelo Oleo'!AB12*(1))*$C$2)-('Modelo Soja'!AA12/60*1000)-$C$6 -> #REF! | X12: =+(('Modelo Farelo'!AH12*(1+$C$8))*$C$3+('Modelo Oleo'!AG12*(1))*$C$2)-('Modelo Soja'!AL12/60*1000)-$C$6 -> #REF! | AK12: =+AK11+1 -> 2023 | AL12: =AVERAGEIF(E:E,AK5,X:X) -> #REF!
E13: =YEAR(F13) -> 2021 | F13: =+'Modelo Soja'!BA13 -> 44501 | G13: =+(('Modelo Farelo'!AB13*(1+$C$8))*$C$3+('Modelo Oleo'!AA13*(1))*$C$2)-('Modelo Soja'!AT13/60*1000)-$C$6 -> #REF! | H13: =+(('Modelo Farelo'!AC13*(1+$C$8))*$C$3+('Modelo Oleo'!AB13*(1))*$C$2)-('Modelo Soja'!AU13/60*1000)-$C$6 -> #REF! | I13: =+(('Modelo Farelo'!AD13*(1+$C$8))*$C$3+('Modelo Oleo'!AC13*(1))*$C$2)-('Modelo Soja'!AV13/60*1000)-$C$6 -> #REF! | J13: =+(('Modelo Farelo'!AE13*(1+$C$8))*($C$3+1%)+('Modelo Oleo'!AD13*(1))*($C$2-1%))-('Modelo Soja'!AW13/60*1000)-$C$6 -> #REF! | K13: =+(('Modelo Farelo'!AF13*(1+$C$8))*($C$3+1.5%)+('Modelo Oleo'!AE13*(1))*($C$2-1.5%))-('Modelo Soja'!AX13/60*1000)-$C$6 -> #REF! | L13: =+(('Modelo Farelo'!AG13*(1+$C$8))*($C$3+1.5%)+('Modelo Oleo'!AF13*(1))*($C$2-1.5%))-('Modelo Soja'!AY13/60*1000)-$C$6 -> #REF! | M13: =+(('Modelo Farelo'!AH13*(1+$C$8))*$C$3+('Modelo Oleo'!AG13*(1))*$C$2)-('Modelo Soja'!BM13/60*1000)-$C$6 -> #REF! | Q13: =+F13 -> 44501 | R13: =+(('Modelo Farelo'!AB13*(1+$C$8))*$C$3+('Modelo Oleo'!AA13*(1))*$C$2)-('Modelo Soja'!AK13/60*1000)-$C$6 -> #REF! | S13: =+(('Modelo Farelo'!AC13*(1+$C$8))*$C$3+('Modelo Oleo'!AB13*(1))*$C$2)-('Modelo Soja'!AA13/60*1000)-$C$6 -> #REF! | X13: =+(('Modelo Farelo'!AH13*(1+$C$8))*$C$3+('Modelo Oleo'!AG13*(1))*$C$2)-('Modelo Soja'!AL13/60*1000)-$C$6 -> #REF! | AK13: =+AK12+1 -> 2024 | AL13: =AVERAGEIF(E:E,AK6,X:X) -> #REF!
E14: =YEAR(F14) -> 2021 | F14: =+'Modelo Soja'!BA14 -> 44531 | G14: =+(('Modelo Farelo'!AB14*(1+$C$8))*$C$3+('Modelo Oleo'!AA14*(1))*$C$2)-('Modelo Soja'!AT14/60*1000)-$C$6 -> #REF! | H14: =+(('Modelo Farelo'!AC14*(1+$C$8))*$C$3+('Modelo Oleo'!AB14*(1))*$C$2)-('Modelo Soja'!AU14/60*1000)-$C$6 -> #REF! | I14: =+(('Modelo Farelo'!AD14*(1+$C$8))*$C$3+('Modelo Oleo'!AC14*(1))*$C$2)-('Modelo Soja'!AV14/60*1000)-$C$6 -> #REF! | J14: =+(('Modelo Farelo'!AE14*(1+$C$8))*($C$3+1%)+('Modelo Oleo'!AD14*(1))*($C$2-1%))-('Modelo Soja'!AW14/60*1000)-$C$6 -> #REF! | K14: =+(('Modelo Farelo'!AF14*(1+$C$8))*($C$3+1.5%)+('Modelo Oleo'!AE14*(1))*($C$2-1.5%))-('Modelo Soja'!AX14/60*1000)-$C$6 -> #REF! | L14: =+(('Modelo Farelo'!AG14*(1+$C$8))*($C$3+1.5%)+('Modelo Oleo'!AF14*(1))*($C$2-1.5%))-('Modelo Soja'!AY14/60*1000)-$C$6 -> #REF! | M14: =+(('Modelo Farelo'!AH14*(1+$C$8))*$C$3+('Modelo Oleo'!AG14*(1))*$C$2)-('Modelo Soja'!BM14/60*1000)-$C$6 -> #REF! | Q14: =+F14 -> 44531 | R14: =+(('Modelo Farelo'!AB14*(1+$C$8))*$C$3+('Modelo Oleo'!AA14*(1))*$C$2)-('Modelo Soja'!AK14/60*1000)-$C$6 -> #REF! | S14: =+(('Modelo Farelo'!AC14*(1+$C$8))*$C$3+('Modelo Oleo'!AB14*(1))*$C$2)-('Modelo Soja'!AA14/60*1000)-$C$6 -> #REF! | X14: =+(('Modelo Farelo'!AH14*(1+$C$8))*$C$3+('Modelo Oleo'!AG14*(1))*$C$2)-('Modelo Soja'!AL14/60*1000)-$C$6 -> #REF! | AK14: =+AK13+1 -> 2025 | AL14: =AVERAGEIF(E:E,AK7,X:X) -> #REF!
E15: =YEAR(F15) -> 2022 | F15: =+'Modelo Soja'!BA15 -> 44562 | G15: =+(('Modelo Farelo'!AB15*(1+$C$8))*$C$3+('Modelo Oleo'!AA15*(1))*$C$2)-('Modelo Soja'!AT15/60*1000)-$C$6 -> #REF! | H15: =+(('Modelo Farelo'!AC15*(1+$C$8))*$C$3+('Modelo Oleo'!AB15*(1))*$C$2)-('Modelo Soja'!AU15/60*1000)-$C$6 -> #REF! | I15: =+(('Modelo Farelo'!AD15*(1+$C$8))*$C$3+('Modelo Oleo'!AC15*(1))*$C$2)-('Modelo Soja'!AV15/60*1000)-$C$6 -> #REF! | J15: =+(('Modelo Farelo'!AE15*(1+$C$8))*($C$3+1%)+('Modelo Oleo'!AD15*(1))*($C$2-1%))-('Modelo Soja'!AW15/60*1000)-$C$6 -> #REF! | K15: =+(('Modelo Farelo'!AF15*(1+$C$8))*($C$3+1.5%)+('Modelo Oleo'!AE15*(1))*($C$2-1.5%))-('Modelo Soja'!AX15/60*1000)-$C$6 -> #REF! | L15: =+(('Modelo Farelo'!AG15*(1+$C$8))*($C$3+1.5%)+('Modelo Oleo'!AF15*(1))*($C$2-1.5%))-('Modelo Soja'!AY15/60*1000)-$C$6 -> #REF! | M15: =+(('Modelo Farelo'!AH15*(1+$C$8))*$C$3+('Modelo Oleo'!AG15*(1))*$C$2)-('Modelo Soja'!BM15/60*1000)-$C$6 -> #REF! | Q15: =+F15 -> 44562 | R15: =+(('Modelo Farelo'!AB15*(1+$C$8))*$C$3+('Modelo Oleo'!AA15*(1))*$C$2)-('Modelo Soja'!AK15/60*1000)-$C$6 -> #REF! | S15: =+(('Modelo Farelo'!AC15*(1+$C$8))*$C$3+('Modelo Oleo'!AB15*(1))*$C$2)-('Modelo Soja'!AA15/60*1000)-$C$6 -> #REF! | X15: =+(('Modelo Farelo'!AH15*(1+$C$8))*$C$3+('Modelo Oleo'!AG15*(1))*$C$2)-('Modelo Soja'!AL15/60*1000)-$C$6 -> #REF! | AK15: =+AK14+1 -> 2026 | AL15: =AVERAGEIF(E:E,AK8,X:X) -> #REF!
E16: =YEAR(F16) -> 2022 | F16: =+'Modelo Soja'!BA16 -> 44593 | G16: =+(('Modelo Farelo'!AB16*(1+$C$8))*$C$3+('Modelo Oleo'!AA16*(1))*$C$2)-('Modelo Soja'!AT16/60*1000)-$C$6 -> #REF! | H16: =+(('Modelo Farelo'!AC16*(1+$C$8))*$C$3+('Modelo Oleo'!AB16*(1))*$C$2)-('Modelo Soja'!AU16/60*1000)-$C$6 -> #REF! | I16: =+(('Modelo Farelo'!AD16*(1+$C$8))*$C$3+('Modelo Oleo'!AC16*(1))*$C$2)-('Modelo Soja'!AV16/60*1000)-$C$6 -> #REF! | J16: =+(('Modelo Farelo'!AE16*(1+$C$8))*($C$3+1%)+('Modelo Oleo'!AD16*(1))*($C$2-1%))-('Modelo Soja'!AW16/60*1000)-$C$6 -> #REF! | K16: =+(('Modelo Farelo'!AF16*(1+$C$8))*($C$3+1.5%)+('Modelo Oleo'!AE16*(1))*($C$2-1.5%))-('Modelo Soja'!AX16/60*1000)-$C$6 -> #REF! | L16: =+(('Modelo Farelo'!AG16*(1+$C$8))*($C$3+1.5%)+('Modelo Oleo'!AF16*(1))*($C$2-1.5%))-('Modelo Soja'!AY16/60*1000)-$C$6 -> #REF! | M16: =+(('Modelo Farelo'!AH16*(1+$C$8))*$C$3+('Modelo Oleo'!AG16*(1))*$C$2)-('Modelo Soja'!BM16/60*1000)-$C$6 -> #REF! | Q16: =+F16 -> 44593 | R16: =+(('Modelo Farelo'!AB16*(1+$C$8))*$C$3+('Modelo Oleo'!AA16*(1))*$C$2)-('Modelo Soja'!AK16/60*1000)-$C$6 -> #REF! | S16: =+(('Modelo Farelo'!AC16*(1+$C$8))*$C$3+('Modelo Oleo'!AB16*(1))*$C$2)-('Modelo Soja'!AA16/60*1000)-$C$6 -> #REF! | X16: =+(('Modelo Farelo'!AH16*(1+$C$8))*$C$3+('Modelo Oleo'!AG16*(1))*$C$2)-('Modelo Soja'!AL16/60*1000)-$C$6 -> #REF!
E17: =YEAR(F17) -> 2022 | F17: =+'Modelo Soja'!BA17 -> 44621 | G17: =+(('Modelo Farelo'!AB17*(1+$C$8))*$C$3+('Modelo Oleo'!AA17*(1))*$C$2)-('Modelo Soja'!AT17/60*1000)-$C$6 -> #REF! | H17: =+(('Modelo Farelo'!AC17*(1+$C$8))*$C$3+('Modelo Oleo'!AB17*(1))*$C$2)-('Modelo Soja'!AU17/60*1000)-$C$6 -> #REF! | I17: =+(('Modelo Farelo'!AD17*(1+$C$8))*$C$3+('Modelo Oleo'!AC17*(1))*$C$2)-('Modelo Soja'!AV17/60*1000)-$C$6 -> #REF! | J17: =+(('Modelo Farelo'!AE17*(1+$C$8))*($C$3+1%)+('Modelo Oleo'!AD17*(1))*($C$2-1%))-('Modelo Soja'!AW17/60*1000)-$C$6 -> #REF! | K17: =+(('Modelo Farelo'!AF17*(1+$C$8))*($C$3+1.5%)+('Modelo Oleo'!AE17*(1))*($C$2-1.5%))-('Modelo Soja'!AX17/60*1000)-$C$6 -> #REF! | L17: =+(('Modelo Farelo'!AG17*(1+$C$8))*($C$3+1.5%)+('Modelo Oleo'!AF17*(1))*($C$2-1.5%))-('Modelo Soja'!AY17/60*1000)-$C$6 -> #REF! | M17: =+(('Modelo Farelo'!AH17*(1+$C$8))*$C$3+('Modelo Oleo'!AG17*(1))*$C$2)-('Modelo Soja'!BM17/60*1000)-$C$6 -> #REF! | Q17: =+F17 -> 44621 | R17: =+(('Modelo Farelo'!AB17*(1+$C$8))*$C$3+('Modelo Oleo'!AA17*(1))*$C$2)-('Modelo Soja'!AK17/60*1000)-$C$6 -> #REF! | S17: =+(('Modelo Farelo'!AC17*(1+$C$8))*$C$3+('Modelo Oleo'!AB17*(1))*$C$2)-('Modelo Soja'!AA17/60*1000)-$C$6 -> #REF! | X17: =+(('Modelo Farelo'!AH17*(1+$C$8))*$C$3+('Modelo Oleo'!AG17*(1))*$C$2)-('Modelo Soja'!AL17/60*1000)-$C$6 -> #REF!
E18: =YEAR(F18) -> 2022 | F18: =+'Modelo Soja'!BA18 -> 44652 | G18: =+(('Modelo Farelo'!AB18*(1+$C$8))*$C$3+('Modelo Oleo'!AA18*(1))*$C$2)-('Modelo Soja'!AT18/60*1000)-$C$6 -> #REF! | H18: =+(('Modelo Farelo'!AC18*(1+$C$8))*$C$3+('Modelo Oleo'!AB18*(1))*$C$2)-('Modelo Soja'!AU18/60*1000)-$C$6 -> #REF! | I18: =+(('Modelo Farelo'!AD18*(1+$C$8))*$C$3+('Modelo Oleo'!AC18*(1))*$C$2)-('Modelo Soja'!AV18/60*1000)-$C$6 -> #REF! | J18: =+(('Modelo Farelo'!AE18*(1+$C$8))*($C$3+1%)+('Modelo Oleo'!AD18*(1))*($C$2-1%))-('Modelo Soja'!AW18/60*1000)-$C$6 -> #REF! | K18: =+(('Modelo Farelo'!AF18*(1+$C$8))*($C$3+1.5%)+('Modelo Oleo'!AE18*(1))*($C$2-1.5%))-('Modelo Soja'!AX18/60*1000)-$C$6 -> #REF! | L18: =+(('Modelo Farelo'!AG18*(1+$C$8))*($C$3+1.5%)+('Modelo Oleo'!AF18*(1))*($C$2-1.5%))-('Modelo Soja'!AY18/60*1000)-$C$6 -> #REF! | M18: =+(('Modelo Farelo'!AH18*(1+$C$8))*$C$3+('Modelo Oleo'!AG18*(1))*$C$2)-('Modelo Soja'!BM18/60*1000)-$C$6 -> #REF! | Q18: =+F18 -> 44652 | R18: =+(('Modelo Farelo'!AB18*(1+$C$8))*$C$3+('Modelo Oleo'!AA18*(1))*$C$2)-('Modelo Soja'!AK18/60*1000)-$C$6 -> #REF! | S18: =+(('Modelo Farelo'!AC18*(1+$C$8))*$C$3+('Modelo Oleo'!AB18*(1))*$C$2)-('Modelo Soja'!AA18/60*1000)-$C$6 -> #REF! | X18: =+(('Modelo Farelo'!AH18*(1+$C$8))*$C$3+('Modelo Oleo'!AG18*(1))*$C$2)-('Modelo Soja'!AL18/60*1000)-$C$6 -> #REF!
E19: =YEAR(F19) -> 2022 | F19: =+'Modelo Soja'!BA19 -> 44682 | G19: =+(('Modelo Farelo'!AB19*(1+$C$8))*$C$3+('Modelo Oleo'!AA19*(1))*$C$2)-('Modelo Soja'!AT19/60*1000)-$C$6 -> #REF! | H19: =+(('Modelo Farelo'!AC19*(1+$C$8))*$C$3+('Modelo Oleo'!AB19*(1))*$C$2)-('Modelo Soja'!AU19/60*1000)-$C$6 -> #REF! | I19: =+(('Modelo Farelo'!AD19*(1+$C$8))*$C$3+('Modelo Oleo'!AC19*(1))*$C$2)-('Modelo Soja'!AV19/60*1000)-$C$6 -> #REF! | J19: =+(('Modelo Farelo'!AE19*(1+$C$8))*($C$3+1%)+('Modelo Oleo'!AD19*(1))*($C$2-1%))-('Modelo Soja'!AW19/60*1000)-$C$6 -> #REF! | K19: =+(('Modelo Farelo'!AF19*(1+$C$8))*($C$3+1.5%)+('Modelo Oleo'!AE19*(1))*($C$2-1.5%))-('Modelo Soja'!AX19/60*1000)-$C$6 -> #REF! | L19: =+(('Modelo Farelo'!AG19*(1+$C$8))*($C$3+1.5%)+('Modelo Oleo'!AF19*(1))*($C$2-1.5%))-('Modelo Soja'!AY19/60*1000)-$C$6 -> #REF! | M19: =+(('Modelo Farelo'!AH19*(1+$C$8))*$C$3+('Modelo Oleo'!AG19*(1))*$C$2)-('Modelo Soja'!BM19/60*1000)-$C$6 -> #REF! | Q19: =+F19 -> 44682 | R19: =+(('Modelo Farelo'!AB19*(1+$C$8))*$C$3+('Modelo Oleo'!AA19*(1))*$C$2)-('Modelo Soja'!AK19/60*1000)-$C$6 -> #REF! | S19: =+(('Modelo Farelo'!AC19*(1+$C$8))*$C$3+('Modelo Oleo'!AB19*(1))*$C$2)-('Modelo Soja'!AA19/60*1000)-$C$6 -> #REF! | X19: =+(('Modelo Farelo'!AH19*(1+$C$8))*$C$3+('Modelo Oleo'!AG19*(1))*$C$2)-('Modelo Soja'!AL19/60*1000)-$C$6 -> #REF!
E20: =YEAR(F20) -> 2022 | F20: =+'Modelo Soja'!BA20 -> 44713 | G20: =+(('Modelo Farelo'!AB20*(1+$C$8))*$C$3+('Modelo Oleo'!AA20*(1))*$C$2)-('Modelo Soja'!AT20/60*1000)-$C$6 -> #REF! | H20: =+(('Modelo Farelo'!AC20*(1+$C$8))*$C$3+('Modelo Oleo'!AB20*(1))*$C$2)-('Modelo Soja'!AU20/60*1000)-$C$6 -> #REF! | I20: =+(('Modelo Farelo'!AD20*(1+$C$8))*$C$3+('Modelo Oleo'!AC20*(1))*$C$2)-('Modelo Soja'!AV20/60*1000)-$C$6 -> #REF! | J20: =+(('Modelo Farelo'!AE20*(1+$C$8))*($C$3+1%)+('Modelo Oleo'!AD20*(1))*($C$2-1%))-('Modelo Soja'!AW20/60*1000)-$C$6 -> #REF! | K20: =+(('Modelo Farelo'!AF20*(1+$C$8))*($C$3+1.5%)+('Modelo Oleo'!AE20*(1))*($C$2-1.5%))-('Modelo Soja'!AX20/60*1000)-$C$6 -> #REF! | L20: =+(('Modelo Farelo'!AG20*(1+$C$8))*($C$3+1.5%)+('Modelo Oleo'!AF20*(1))*($C$2-1.5%))-('Modelo Soja'!AY20/60*1000)-$C$6 -> #REF! | M20: =+(('Modelo Farelo'!AH20*(1+$C$8))*$C$3+('Modelo Oleo'!AG20*(1))*$C$2)-('Modelo Soja'!BM20/60*1000)-$C$6 -> #REF! | Q20: =+F20 -> 44713 | R20: =+(('Modelo Farelo'!AB20*(1+$C$8))*$C$3+('Modelo Oleo'!AA20*(1))*$C$2)-('Modelo Soja'!AK20/60*1000)-$C$6 -> #REF! | S20: =+(('Modelo Farelo'!AC20*(1+$C$8))*$C$3+('Modelo Oleo'!AB20*(1))*$C$2)-('Modelo Soja'!AA20/60*1000)-$C$6 -> #REF! | X20: =+(('Modelo Farelo'!AH20*(1+$C$8))*$C$3+('Modelo Oleo'!AG20*(1))*$C$2)-('Modelo Soja'!AL20/60*1000)-$C$6 -> #REF!
E21: =YEAR(F21) -> 2022 | F21: =+'Modelo Soja'!BA21 -> 44743 | G21: =+(('Modelo Farelo'!AB21*(1+$C$8))*$C$3+('Modelo Oleo'!AA21*(1))*$C$2)-('Modelo Soja'!AT21/60*1000)-$C$6 -> #REF! | H21: =+(('Modelo Farelo'!AC21*(1+$C$8))*$C$3+('Modelo Oleo'!AB21*(1))*$C$2)-('Modelo Soja'!AU21/60*1000)-$C$6 -> #REF! | I21: =+(('Modelo Farelo'!AD21*(1+$C$8))*$C$3+('Modelo Oleo'!AC21*(1))*$C$2)-('Modelo Soja'!AV21/60*1000)-$C$6 -> #REF! | J21: =+(('Modelo Farelo'!AE21*(1+$C$8))*($C$3+1%)+('Modelo Oleo'!AD21*(1))*($C$2-1%))-('Modelo Soja'!AW21/60*1000)-$C$6 -> #REF! | K21: =+(('Modelo Farelo'!AF21*(1+$C$8))*($C$3+1.5%)+('Modelo Oleo'!AE21*(1))*($C$2-1.5%))-('Modelo Soja'!AX21/60*1000)-$C$6 -> #REF! | L21: =+(('Modelo Farelo'!AG21*(1+$C$8))*($C$3+1.5%)+('Modelo Oleo'!AF21*(1))*($C$2-1.5%))-('Modelo Soja'!AY21/60*1000)-$C$6 -> #REF! | M21: =+(('Modelo Farelo'!AH21*(1+$C$8))*$C$3+('Modelo Oleo'!AG21*(1))*$C$2)-('Modelo Soja'!BM21/60*1000)-$C$6 -> #REF! | Q21: =+F21 -> 44743 | R21: =+(('Modelo Farelo'!AB21*(1+$C$8))*$C$3+('Modelo Oleo'!AA21*(1))*$C$2)-('Modelo Soja'!AK21/60*1000)-$C$6 -> #REF! | S21: =+(('Modelo Farelo'!AC21*(1+$C$8))*$C$3+('Modelo Oleo'!AB21*(1))*$C$2)-('Modelo Soja'!AA21/60*1000)-$C$6 -> #REF! | X21: =+(('Modelo Farelo'!AH21*(1+$C$8))*$C$3+('Modelo Oleo'!AG21*(1))*$C$2)-('Modelo Soja'!AL21/60*1000)-$C$6 -> #REF!
E22: =YEAR(F22) -> 2022 | F22: =+'Modelo Soja'!BA22 -> 44774 | G22: =+(('Modelo Farelo'!AB22*(1+$C$8))*$C$3+('Modelo Oleo'!AA22*(1))*$C$2)-('Modelo Soja'!AT22/60*1000)-$C$6 -> #REF! | H22: =+(('Modelo Farelo'!AC22*(1+$C$8))*$C$3+('Modelo Oleo'!AB22*(1))*$C$2)-('Modelo Soja'!AU22/60*1000)-$C$6 -> #REF! | I22: =+(('Modelo Farelo'!AD22*(1+$C$8))*$C$3+('Modelo Oleo'!AC22*(1))*$C$2)-('Modelo Soja'!AV22/60*1000)-$C$6 -> #REF! | J22: =+(('Modelo Farelo'!AE22*(1+$C$8))*($C$3+1%)+('Modelo Oleo'!AD22*(1))*($C$2-1%))-('Modelo Soja'!AW22/60*1000)-$C$6 -> #REF! | K22: =+(('Modelo Farelo'!AF22*(1+$C$8))*($C$3+1.5%)+('Modelo Oleo'!AE22*(1))*($C$2-1.5%))-('Modelo Soja'!AX22/60*1000)-$C$6 -> #REF! | L22: =+(('Modelo Farelo'!AG22*(1+$C$8))*($C$3+1.5%)+('Modelo Oleo'!AF22*(1))*($C$2-1.5%))-('Modelo Soja'!AY22/60*1000)-$C$6 -> #REF! | M22: =+(('Modelo Farelo'!AH22*(1+$C$8))*$C$3+('Modelo Oleo'!AG22*(1))*$C$2)-('Modelo Soja'!BM22/60*1000)-$C$6 -> #REF! | Q22: =+F22 -> 44774 | R22: =+(('Modelo Farelo'!AB22*(1+$C$8))*$C$3+('Modelo Oleo'!AA22*(1))*$C$2)-('Modelo Soja'!AK22/60*1000)-$C$6 -> #REF! | S22: =+(('Modelo Farelo'!AC22*(1+$C$8))*$C$3+('Modelo Oleo'!AB22*(1))*$C$2)-('Modelo Soja'!AA22/60*1000)-$C$6 -> #REF! | X22: =+(('Modelo Farelo'!AH22*(1+$C$8))*$C$3+('Modelo Oleo'!AG22*(1))*$C$2)-('Modelo Soja'!AL22/60*1000)-$C$6 -> #REF!
E23: =YEAR(F23) -> 2022 | F23: =+'Modelo Soja'!BA23 -> 44805 | G23: =+(('Modelo Farelo'!AB23*(1+$C$8))*$C$3+('Modelo Oleo'!AA23*(1))*$C$2)-('Modelo Soja'!AT23/60*1000)-$C$6 -> #REF! | H23: =+(('Modelo Farelo'!AC23*(1+$C$8))*$C$3+('Modelo Oleo'!AB23*(1))*$C$2)-('Modelo Soja'!AU23/60*1000)-$C$6 -> #REF! | I23: =+(('Modelo Farelo'!AD23*(1+$C$8))*$C$3+('Modelo Oleo'!AC23*(1))*$C$2)-('Modelo Soja'!AV23/60*1000)-$C$6 -> #REF! | J23: =+(('Modelo Farelo'!AE23*(1+$C$8))*($C$3+1%)+('Modelo Oleo'!AD23*(1))*($C$2-1%))-('Modelo Soja'!AW23/60*1000)-$C$6 -> #REF! | K23: =+(('Modelo Farelo'!AF23*(1+$C$8))*($C$3+1.5%)+('Modelo Oleo'!AE23*(1))*($C$2-1.5%))-('Modelo Soja'!AX23/60*1000)-$C$6 -> #REF! | L23: =+(('Modelo Farelo'!AG23*(1+$C$8))*($C$3+1.5%)+('Modelo Oleo'!AF23*(1))*($C$2-1.5%))-('Modelo Soja'!AY23/60*1000)-$C$6 -> #REF! | M23: =+(('Modelo Farelo'!AH23*(1+$C$8))*$C$3+('Modelo Oleo'!AG23*(1))*$C$2)-('Modelo Soja'!BM23/60*1000)-$C$6 -> #REF! | Q23: =+F23 -> 44805 | R23: =+(('Modelo Farelo'!AB23*(1+$C$8))*$C$3+('Modelo Oleo'!AA23*(1))*$C$2)-('Modelo Soja'!AK23/60*1000)-$C$6 -> #REF! | S23: =+(('Modelo Farelo'!AC23*(1+$C$8))*$C$3+('Modelo Oleo'!AB23*(1))*$C$2)-('Modelo Soja'!AA23/60*1000)-$C$6 -> #REF! | X23: =+(('Modelo Farelo'!AH23*(1+$C$8))*$C$3+('Modelo Oleo'!AG23*(1))*$C$2)-('Modelo Soja'!AL23/60*1000)-$C$6 -> #REF!
E24: =YEAR(F24) -> 2022 | F24: =+'Modelo Soja'!BA24 -> 44835 | G24: =+(('Modelo Farelo'!AB24*(1+$C$8))*$C$3+('Modelo Oleo'!AA24*(1))*$C$2)-('Modelo Soja'!AT24/60*1000)-$C$6 -> #REF! | H24: =+(('Modelo Farelo'!AC24*(1+$C$8))*$C$3+('Modelo Oleo'!AB24*(1))*$C$2)-('Modelo Soja'!AU24/60*1000)-$C$6 -> #REF! | I24: =+(('Modelo Farelo'!AD24*(1+$C$8))*$C$3+('Modelo Oleo'!AC24*(1))*$C$2)-('Modelo Soja'!AV24/60*1000)-$C$6 -> #REF! | J24: =+(('Modelo Farelo'!AE24*(1+$C$8))*($C$3+1%)+('Modelo Oleo'!AD24*(1))*($C$2-1%))-('Modelo Soja'!AW24/60*1000)-$C$6 -> #REF! | K24: =+(('Modelo Farelo'!AF24*(1+$C$8))*($C$3+1.5%)+('Modelo Oleo'!AE24*(1))*($C$2-1.5%))-('Modelo Soja'!AX24/60*1000)-$C$6 -> #REF! | L24: =+(('Modelo Farelo'!AG24*(1+$C$8))*($C$3+1.5%)+('Modelo Oleo'!AF24*(1))*($C$2-1.5%))-('Modelo Soja'!AY24/60*1000)-$C$6 -> #REF! | M24: =+(('Modelo Farelo'!AH24*(1+$C$8))*$C$3+('Modelo Oleo'!AG24*(1))*$C$2)-('Modelo Soja'!BM24/60*1000)-$C$6 -> #REF! | Q24: =+F24 -> 44835 | R24: =+(('Modelo Farelo'!AB24*(1+$C$8))*$C$3+('Modelo Oleo'!AA24*(1))*$C$2)-('Modelo Soja'!AK24/60*1000)-$C$6 -> #REF! | S24: =+(('Modelo Farelo'!AC24*(1+$C$8))*$C$3+('Modelo Oleo'!AB24*(1))*$C$2)-('Modelo Soja'!AA24/60*1000)-$C$6 -> #REF! | X24: =+(('Modelo Farelo'!AH24*(1+$C$8))*$C$3+('Modelo Oleo'!AG24*(1))*$C$2)-('Modelo Soja'!AL24/60*1000)-$C$6 -> #REF!
E25: =YEAR(F25) -> 2022 | F25: =+'Modelo Soja'!BA25 -> 44866 | G25: =+(('Modelo Farelo'!AB25*(1+$C$8))*$C$3+('Modelo Oleo'!AA25*(1))*$C$2)-('Modelo Soja'!AT25/60*1000)-$C$6 -> #REF! | H25: =+(('Modelo Farelo'!AC25*(1+$C$8))*$C$3+('Modelo Oleo'!AB25*(1))*$C$2)-('Modelo Soja'!AU25/60*1000)-$C$6 -> #REF! | I25: =+(('Modelo Farelo'!AD25*(1+$C$8))*$C$3+('Modelo Oleo'!AC25*(1))*$C$2)-('Modelo Soja'!AV25/60*1000)-$C$6 -> #REF! | J25: =+(('Modelo Farelo'!AE25*(1+$C$8))*($C$3+1%)+('Modelo Oleo'!AD25*(1))*($C$2-1%))-('Modelo Soja'!AW25/60*1000)-$C$6 -> #REF! | K25: =+(('Modelo Farelo'!AF25*(1+$C$8))*($C$3+1.5%)+('Modelo Oleo'!AE25*(1))*($C$2-1.5%))-('Modelo Soja'!AX25/60*1000)-$C$6 -> #REF! | L25: =+(('Modelo Farelo'!AG25*(1+$C$8))*($C$3+1.5%)+('Modelo Oleo'!AF25*(1))*($C$2-1.5%))-('Modelo Soja'!AY25/60*1000)-$C$6 -> #REF! | M25: =+(('Modelo Farelo'!AH25*(1+$C$8))*$C$3+('Modelo Oleo'!AG25*(1))*$C$2)-('Modelo Soja'!BM25/60*1000)-$C$6 -> #REF! | Q25: =+F25 -> 44866 | R25: =+(('Modelo Farelo'!AB25*(1+$C$8))*$C$3+('Modelo Oleo'!AA25*(1))*$C$2)-('Modelo Soja'!AK25/60*1000)-$C$6 -> #REF! | S25: =+(('Modelo Farelo'!AC25*(1+$C$8))*$C$3+('Modelo Oleo'!AB25*(1))*$C$2)-('Modelo Soja'!AA25/60*1000)-$C$6 -> #REF! | X25: =+(('Modelo Farelo'!AH25*(1+$C$8))*$C$3+('Modelo Oleo'!AG25*(1))*$C$2)-('Modelo Soja'!AL25/60*1000)-$C$6 -> #REF!
E26: =YEAR(F26) -> 2022 | F26: =+'Modelo Soja'!BA26 -> 44896 | G26: =+(('Modelo Farelo'!AB26*(1+$C$8))*$C$3+('Modelo Oleo'!AA26*(1))*$C$2)-('Modelo Soja'!AT26/60*1000)-$C$6 -> #REF! | H26: =+(('Modelo Farelo'!AC26*(1+$C$8))*$C$3+('Modelo Oleo'!AB26*(1))*$C$2)-('Modelo Soja'!AU26/60*1000)-$C$6 -> #REF! | I26: =+(('Modelo Farelo'!AD26*(1+$C$8))*$C$3+('Modelo Oleo'!AC26*(1))*$C$2)-('Modelo Soja'!AV26/60*1000)-$C$6 -> #REF! | J26: =+(('Modelo Farelo'!AE26*(1+$C$8))*($C$3+1%)+('Modelo Oleo'!AD26*(1))*($C$2-1%))-('Modelo Soja'!AW26/60*1000)-$C$6 -> #REF! | K26: =+(('Modelo Farelo'!AF26*(1+$C$8))*($C$3+1.5%)+('Modelo Oleo'!AE26*(1))*($C$2-1.5%))-('Modelo Soja'!AX26/60*1000)-$C$6 -> #REF! | L26: =+(('Modelo Farelo'!AG26*(1+$C$8))*($C$3+1.5%)+('Modelo Oleo'!AF26*(1))*($C$2-1.5%))-('Modelo Soja'!AY26/60*1000)-$C$6 -> #REF! | M26: =+(('Modelo Farelo'!AH26*(1+$C$8))*$C$3+('Modelo Oleo'!AG26*(1))*$C$2)-('Modelo Soja'!BM26/60*1000)-$C$6 -> #REF! | Q26: =+F26 -> 44896 | R26: =+(('Modelo Farelo'!AB26*(1+$C$8))*$C$3+('Modelo Oleo'!AA26*(1))*$C$2)-('Modelo Soja'!AK26/60*1000)-$C$6 -> #REF! | S26: =+(('Modelo Farelo'!AC26*(1+$C$8))*$C$3+('Modelo Oleo'!AB26*(1))*$C$2)-('Modelo Soja'!AA26/60*1000)-$C$6 -> #REF! | X26: =+(('Modelo Farelo'!AH26*(1+$C$8))*$C$3+('Modelo Oleo'!AG26*(1))*$C$2)-('Modelo Soja'!AL26/60*1000)-$C$6 -> #REF!
E27: =YEAR(F27) -> 2023 | F27: =+'Modelo Soja'!BA27 -> 44927 | G27: =+(('Modelo Farelo'!AB27*(1+$C$8))*$C$3+('Modelo Oleo'!AA27*(1))*$C$2)-('Modelo Soja'!AT27/60*1000)-$C$6 -> #REF! | H27: =+(('Modelo Farelo'!AC27*(1+$C$8))*$C$3+('Modelo Oleo'!AB27*(1))*$C$2)-('Modelo Soja'!AU27/60*1000)-$C$6 -> #REF! | I27: =+(('Modelo Farelo'!AD27*(1+$C$8))*$C$3+('Modelo Oleo'!AC27*(1))*$C$2)-('Modelo Soja'!AV27/60*1000)-$C$6 -> #REF! | J27: =+(('Modelo Farelo'!AE27*(1+$C$8))*($C$3+1%)+('Modelo Oleo'!AD27*(1))*($C$2-1%))-('Modelo Soja'!AW27/60*1000)-$C$6 -> #REF! | K27: =+(('Modelo Farelo'!AF27*(1+$C$8))*($C$3+1.5%)+('Modelo Oleo'!AE27*(1))*($C$2-1.5%))-('Modelo Soja'!AX27/60*1000)-$C$6 -> #REF! | L27: =+(('Modelo Farelo'!AG27*(1+$C$8))*($C$3+1.5%)+('Modelo Oleo'!AF27*(1))*($C$2-1.5%))-('Modelo Soja'!AY27/60*1000)-$C$6 -> #REF! | M27: =+(('Modelo Farelo'!AH27*(1+$C$8))*$C$3+('Modelo Oleo'!AG27*(1))*$C$2)-('Modelo Soja'!BM27/60*1000)-$C$6 -> #REF! | Q27: =+F27 -> 44927 | R27: =+(('Modelo Farelo'!AB27*(1+$C$8))*$C$3+('Modelo Oleo'!AA27*(1))*$C$2)-('Modelo Soja'!AK27/60*1000)-$C$6 -> #REF! | S27: =+(('Modelo Farelo'!AC27*(1+$C$8))*$C$3+('Modelo Oleo'!AB27*(1))*$C$2)-('Modelo Soja'!AA27/60*1000)-$C$6 -> #REF! | X27: =+(('Modelo Farelo'!AH27*(1+$C$8))*$C$3+('Modelo Oleo'!AG27*(1))*$C$2)-('Modelo Soja'!AL27/60*1000)-$C$6 -> #REF!
... E37: =YEAR(F37) -> 2023 | F37: =+'Modelo Soja'!BA37 -> 45231 | G37: =+(('Modelo Farelo'!AB37*(1+$C$8))*$C$3+('Modelo Oleo'!AA37*(1))*$C$2)-('Modelo Soja'!AT37/60*1000)-$C$6 -> #REF! | H37: =+(('Modelo Farelo'!AC37*(1+$C$8))*$C$3+('Modelo Oleo'!AB37*(1))*$C$2)-('Modelo Soja'!AU37/60*1000)-$C$6 -> #REF! | I37: =+(('Modelo Farelo'!AD37*(1+$C$8))*$C$3+('Modelo Oleo'!AC37*(1))*$C$2)-('Modelo Soja'!AV37/60*1000)-$C$6 -> #REF! | J37: =+(('Modelo Farelo'!AE37*(1+$C$8))*($C$3+1%)+('Modelo Oleo'!AD37*(1))*($C$2-1%))-('Modelo Soja'!AW37/60*1000)-$C$6 -> #REF! | K37: =+(('Modelo Farelo'!AF37*(1+$C$8))*($C$3+1.5%)+('Modelo Oleo'!AE37*(1))*($C$2-1.5%))-('Modelo Soja'!AX37/60*1000)-$C$6 -> #REF! | L37: =+(('Modelo Farelo'!AG37*(1+$C$8))*($C$3+1.5%)+('Modelo Oleo'!AF37*(1))*($C$2-1.5%))-('Modelo Soja'!AY37/60*1000)-$C$6 -> #REF! | M37: =+(('Modelo Farelo'!AH37*(1+$C$8))*$C$3+('Modelo Oleo'!AG37*(1))*$C$2)-('Modelo Soja'!BM37/60*1000)-$C$6 -> #REF! | Q37: =+F37 -> 45231 | R37: =+(('Modelo Farelo'!AB37*(1+$C$8))*$C$3+('Modelo Oleo'!AA37*(1))*$C$2)-('Modelo Soja'!AK37/60*1000)-$C$6 -> #REF! | S37: =+(('Modelo Farelo'!AC37*(1+$C$8))*$C$3+('Modelo Oleo'!AB37*(1))*$C$2)-('Modelo Soja'!AA37/60*1000)-$C$6 -> #REF! | X37: =+(('Modelo Farelo'!AH37*(1+$C$8))*$C$3+('Modelo Oleo'!AG37*(1))*$C$2)-('Modelo Soja'!AL37/60*1000)-$C$6 -> #REF!
E38: =YEAR(F38) -> 2023 | F38: =+'Modelo Soja'!BA38 -> 45261 | G38: =+(('Modelo Farelo'!AB38*(1+$C$8))*$C$3+('Modelo Oleo'!AA38*(1))*$C$2)-('Modelo Soja'!AT38/60*1000)-$C$6 -> #REF! | H38: =+(('Modelo Farelo'!AC38*(1+$C$8))*$C$3+('Modelo Oleo'!AB38*(1))*$C$2)-('Modelo Soja'!AU38/60*1000)-$C$6 -> #REF! | I38: =+(('Modelo Farelo'!AD38*(1+$C$8))*$C$3+('Modelo Oleo'!AC38*(1))*$C$2)-('Modelo Soja'!AV38/60*1000)-$C$6 -> #REF! | J38: =+(('Modelo Farelo'!AE38*(1+$C$8))*($C$3+1%)+('Modelo Oleo'!AD38*(1))*($C$2-1%))-('Modelo Soja'!AW38/60*1000)-$C$6 -> #REF! | K38: =+(('Modelo Farelo'!AF38*(1+$C$8))*($C$3+1.5%)+('Modelo Oleo'!AE38*(1))*($C$2-1.5%))-('Modelo Soja'!AX38/60*1000)-$C$6 -> #REF! | L38: =+(('Modelo Farelo'!AG38*(1+$C$8))*($C$3+1.5%)+('Modelo Oleo'!AF38*(1))*($C$2-1.5%))-('Modelo Soja'!AY38/60*1000)-$C$6 -> #REF! | M38: =+(('Modelo Farelo'!AH38*(1+$C$8))*$C$3+('Modelo Oleo'!AG38*(1))*$C$2)-('Modelo Soja'!BM38/60*1000)-$C$6 -> #REF! | Q38: =+F38 -> 45261 | R38: =+(('Modelo Farelo'!AB38*(1+$C$8))*$C$3+('Modelo Oleo'!AA38*(1))*$C$2)-('Modelo Soja'!AK38/60*1000)-$C$6 -> #REF! | S38: =+(('Modelo Farelo'!AC38*(1+$C$8))*$C$3+('Modelo Oleo'!AB38*(1))*$C$2)-('Modelo Soja'!AA38/60*1000)-$C$6 -> #REF! | V38: Stonex | X38: =+(('Modelo Farelo'!AH38*(1+$C$8))*$C$3+('Modelo Oleo'!AG38*(1))*$C$2)-('Modelo Soja'!AL38/60*1000)-$C$6 -> #REF!
E39: =YEAR(F39) -> 2024 | F39: =+'Modelo Soja'!BA39 -> 45292 | G39: =+(('Modelo Farelo'!AB39*(1+$C$8))*$C$3+('Modelo Oleo'!AA39*(1))*$C$2)-('Modelo Soja'!AT39/60*1000)-$C$6 -> #REF! | H39: =+(('Modelo Farelo'!AC39*(1+$C$8))*$C$3+('Modelo Oleo'!AB39*(1))*$C$2)-('Modelo Soja'!AU39/60*1000)-$C$6 -> #REF! | I39: =+(('Modelo Farelo'!AD39*(1+$C$8))*$C$3+('Modelo Oleo'!AC39*(1))*$C$2)-('Modelo Soja'!AV39/60*1000)-$C$6 -> #REF! | J39: =+(('Modelo Farelo'!AE39*(1+$C$8))*($C$3+1%)+('Modelo Oleo'!AD39*(1))*($C$2-1%))-('Modelo Soja'!AW39/60*1000)-$C$6 -> #REF! | K39: =+(('Modelo Farelo'!AF39*(1+$C$8))*($C$3+1.5%)+('Modelo Oleo'!AE39*(1))*($C$2-1.5%))-('Modelo Soja'!AX39/60*1000)-$C$6 -> #REF! | L39: =+(('Modelo Farelo'!AG39*(1+$C$8))*($C$3+1.5%)+('Modelo Oleo'!AF39*(1))*($C$2-1.5%))-('Modelo Soja'!AY39/60*1000)-$C$6 -> #REF! | M39: =+(('Modelo Farelo'!AH39*(1+$C$8))*$C$3+('Modelo Oleo'!AG39*(1))*$C$2)-('Modelo Soja'!BM39/60*1000)-$C$6 -> #REF! | Q39: =+F39 -> 45292 | R39: =+(('Modelo Farelo'!AB39*(1+$C$8))*$C$3+('Modelo Oleo'!AA39*(1))*$C$2)-('Modelo Soja'!AK39/60*1000)-$C$6 -> #REF! | S39: =+(('Modelo Farelo'!AC39*(1+$C$8))*$C$3+('Modelo Oleo'!AB39*(1))*$C$2)-('Modelo Soja'!AA39/60*1000)-$C$6 -> #REF! | V39: =+'[1]Margem esmagamento stonex'!L3 -> 284.70271 | X39: =+(('Modelo Farelo'!AH39*(1+$C$8))*$C$3+('Modelo Oleo'!AG39*(1))*$C$2)-('Modelo Soja'!AL39/60*1000)-$C$6 -> #REF!
E40: =YEAR(F40) -> 2024 | F40: =+'Modelo Soja'!BA40 -> 45323 | G40: =+(('Modelo Farelo'!AB40*(1+$C$8))*$C$3+('Modelo Oleo'!AA40*(1))*$C$2)-('Modelo Soja'!AT40/60*1000)-$C$6 -> #REF! | H40: =+(('Modelo Farelo'!AC40*(1+$C$8))*$C$3+('Modelo Oleo'!AB40*(1))*$C$2)-('Modelo Soja'!AU40/60*1000)-$C$6 -> #REF! | I40: =+(('Modelo Farelo'!AD40*(1+$C$8))*$C$3+('Modelo Oleo'!AC40*(1))*$C$2)-('Modelo Soja'!AV40/60*1000)-$C$6 -> #REF! | J40: =+(('Modelo Farelo'!AE40*(1+$C$8))*($C$3+1%)+('Modelo Oleo'!AD40*(1))*($C$2-1%))-('Modelo Soja'!AW40/60*1000)-$C$6 -> #REF! | K40: =+(('Modelo Farelo'!AF40*(1+$C$8))*($C$3+1.5%)+('Modelo Oleo'!AE40*(1))*($C$2-1.5%))-('Modelo Soja'!AX40/60*1000)-$C$6 -> #REF! | L40: =+(('Modelo Farelo'!AG40*(1+$C$8))*($C$3+1.5%)+('Modelo Oleo'!AF40*(1))*($C$2-1.5%))-('Modelo Soja'!AY40/60*1000)-$C$6 -> #REF! | M40: =+(('Modelo Farelo'!AH40*(1+$C$8))*$C$3+('Modelo Oleo'!AG40*(1))*$C$2)-('Modelo Soja'!BM40/60*1000)-$C$6 -> #REF! | Q40: =+F40 -> 45323 | R40: =+(('Modelo Farelo'!AB40*(1+$C$8))*$C$3+('Modelo Oleo'!AA40*(1))*$C$2)-('Modelo Soja'!AK40/60*1000)-$C$6 -> #REF! | S40: =+(('Modelo Farelo'!AC40*(1+$C$8))*$C$3+('Modelo Oleo'!AB40*(1))*$C$2)-('Modelo Soja'!AA40/60*1000)-$C$6 -> #REF! | V40: =+'[1]Margem esmagamento stonex'!L4 -> 285.9855 | X40: =+(('Modelo Farelo'!AH40*(1+$C$8))*$C$3+('Modelo Oleo'!AG40*(1))*$C$2)-('Modelo Soja'!AL40/60*1000)-$C$6 -> #REF!
E41: =YEAR(F41) -> 2024 | F41: =+'Modelo Soja'!BA41 -> 45352 | G41: =+(('Modelo Farelo'!AB41*(1+$C$8))*$C$3+('Modelo Oleo'!AA41*(1))*$C$2)-('Modelo Soja'!AT41/60*1000)-$C$6 -> #REF! | H41: =+(('Modelo Farelo'!AC41*(1+$C$8))*$C$3+('Modelo Oleo'!AB41*(1))*$C$2)-('Modelo Soja'!AU41/60*1000)-$C$6 -> #REF! | I41: =+(('Modelo Farelo'!AD41*(1+$C$8))*$C$3+('Modelo Oleo'!AC41*(1))*$C$2)-('Modelo Soja'!AV41/60*1000)-$C$6 -> #REF! | J41: =+(('Modelo Farelo'!AE41*(1+$C$8))*($C$3+1%)+('Modelo Oleo'!AD41*(1))*($C$2-1%))-('Modelo Soja'!AW41/60*1000)-$C$6 -> #REF! | K41: =+(('Modelo Farelo'!AF41*(1+$C$8))*($C$3+1.5%)+('Modelo Oleo'!AE41*(1))*($C$2-1.5%))-('Modelo Soja'!AX41/60*1000)-$C$6 -> #REF! | L41: =+(('Modelo Farelo'!AG41*(1+$C$8))*($C$3+1.5%)+('Modelo Oleo'!AF41*(1))*($C$2-1.5%))-('Modelo Soja'!AY41/60*1000)-$C$6 -> #REF! | M41: =+(('Modelo Farelo'!AH41*(1+$C$8))*$C$3+('Modelo Oleo'!AG41*(1))*$C$2)-('Modelo Soja'!BM41/60*1000)-$C$6 -> #REF! | Q41: =+F41 -> 45352 | R41: =+(('Modelo Farelo'!AB41*(1+$C$8))*$C$3+('Modelo Oleo'!AA41*(1))*$C$2)-('Modelo Soja'!AK41/60*1000)-$C$6 -> #REF! | S41: =+(('Modelo Farelo'!AC41*(1+$C$8))*$C$3+('Modelo Oleo'!AB41*(1))*$C$2)-('Modelo Soja'!AA41/60*1000)-$C$6 -> #REF! | V41: =+'[1]Margem esmagamento stonex'!L5 -> 158.97833 | X41: =+(('Modelo Farelo'!AH41*(1+$C$8))*$C$3+('Modelo Oleo'!AG41*(1))*$C$2)-('Modelo Soja'!AL41/60*1000)-$C$6 -> #REF!
E42: =YEAR(F42) -> 2024 | F42: =+'Modelo Soja'!BA42 -> 45383 | G42: =+(('Modelo Farelo'!AB42*(1+$C$8))*$C$3+('Modelo Oleo'!AA42*(1))*$C$2)-('Modelo Soja'!AT42/60*1000)-$C$6 -> #REF! | H42: =+(('Modelo Farelo'!AC42*(1+$C$8))*$C$3+('Modelo Oleo'!AB42*(1))*$C$2)-('Modelo Soja'!AU42/60*1000)-$C$6 -> #REF! | I42: =+(('Modelo Farelo'!AD42*(1+$C$8))*$C$3+('Modelo Oleo'!AC42*(1))*$C$2)-('Modelo Soja'!AV42/60*1000)-$C$6 -> #REF! | J42: =+(('Modelo Farelo'!AE42*(1+$C$8))*($C$3+1%)+('Modelo Oleo'!AD42*(1))*($C$2-1%))-('Modelo Soja'!AW42/60*1000)-$C$6 -> #REF! | K42: =+(('Modelo Farelo'!AF42*(1+$C$8))*($C$3+1.5%)+('Modelo Oleo'!AE42*(1))*($C$2-1.5%))-('Modelo Soja'!AX42/60*1000)-$C$6 -> #REF! | L42: =+(('Modelo Farelo'!AG42*(1+$C$8))*($C$3+1.5%)+('Modelo Oleo'!AF42*(1))*($C$2-1.5%))-('Modelo Soja'!AY42/60*1000)-$C$6 -> #REF! | M42: =+(('Modelo Farelo'!AH42*(1+$C$8))*$C$3+('Modelo Oleo'!AG42*(1))*$C$2)-('Modelo Soja'!BM42/60*1000)-$C$6 -> #REF! | Q42: =+F42 -> 45383 | R42: =+(('Modelo Farelo'!AB42*(1+$C$8))*$C$3+('Modelo Oleo'!AA42*(1))*$C$2)-('Modelo Soja'!AK42/60*1000)-$C$6 -> #REF! | S42: =+(('Modelo Farelo'!AC42*(1+$C$8))*$C$3+('Modelo Oleo'!AB42*(1))*$C$2)-('Modelo Soja'!AA42/60*1000)-$C$6 -> #REF! | V42: =+'[1]Margem esmagamento stonex'!L6 -> 148.00917 | X42: =+(('Modelo Farelo'!AH42*(1+$C$8))*$C$3+('Modelo Oleo'!AG42*(1))*$C$2)-('Modelo Soja'!AL42/60*1000)-$C$6 -> #REF!
E43: =YEAR(F43) -> 2024 | F43: =+'Modelo Soja'!BA43 -> 45413 | G43: =+(('Modelo Farelo'!AB43*(1+$C$8))*$C$3+('Modelo Oleo'!AA43*(1))*$C$2)-('Modelo Soja'!AT43/60*1000)-$C$6 -> #REF! | H43: =+(('Modelo Farelo'!AC43*(1+$C$8))*$C$3+('Modelo Oleo'!AB43*(1))*$C$2)-('Modelo Soja'!AU43/60*1000)-$C$6 -> #REF! | I43: =+(('Modelo Farelo'!AD43*(1+$C$8))*$C$3+('Modelo Oleo'!AC43*(1))*$C$2)-('Modelo Soja'!AV43/60*1000)-$C$6 -> #REF! | J43: =+(('Modelo Farelo'!AE43*(1+$C$8))*($C$3+1%)+('Modelo Oleo'!AD43*(1))*($C$2-1%))-('Modelo Soja'!AW43/60*1000)-$C$6 -> #REF! | K43: =+(('Modelo Farelo'!AF43*(1+$C$8))*($C$3+1.5%)+('Modelo Oleo'!AE43*(1))*($C$2-1.5%))-('Modelo Soja'!AX43/60*1000)-$C$6 -> #REF! | L43: =+(('Modelo Farelo'!AG43*(1+$C$8))*($C$3+1.5%)+('Modelo Oleo'!AF43*(1))*($C$2-1.5%))-('Modelo Soja'!AY43/60*1000)-$C$6 -> #REF! | M43: =+(('Modelo Farelo'!AH43*(1+$C$8))*$C$3+('Modelo Oleo'!AG43*(1))*$C$2)-('Modelo Soja'!BM43/60*1000)-$C$6 -> #REF! | Q43: =+F43 -> 45413 | R43: =+(('Modelo Farelo'!AB43*(1+$C$8))*$C$3+('Modelo Oleo'!AA43*(1))*$C$2)-('Modelo Soja'!AK43/60*1000)-$C$6 -> #REF! | S43: =+(('Modelo Farelo'!AC43*(1+$C$8))*$C$3+('Modelo Oleo'!AB43*(1))*$C$2)-('Modelo Soja'!AA43/60*1000)-$C$6 -> #REF! | V43: =+'[1]Margem esmagamento stonex'!L7 -> 252.65417 | X43: =+(('Modelo Farelo'!AH43*(1+$C$8))*$C$3+('Modelo Oleo'!AG43*(1))*$C$2)-('Modelo Soja'!AL43/60*1000)-$C$6 -> #REF!
E44: =YEAR(F44) -> 2024 | F44: =+'Modelo Soja'!BA44 -> 45444 | G44: =+(('Modelo Farelo'!AB44*(1+$C$8))*$C$3+('Modelo Oleo'!AA44*(1))*$C$2)-('Modelo Soja'!AT44/60*1000)-$C$6 -> #REF! | H44: =+(('Modelo Farelo'!AC44*(1+$C$8))*$C$3+('Modelo Oleo'!AB44*(1))*$C$2)-('Modelo Soja'!AU44/60*1000)-$C$6 -> #REF! | I44: =+(('Modelo Farelo'!AD44*(1+$C$8))*$C$3+('Modelo Oleo'!AC44*(1))*$C$2)-('Modelo Soja'!AV44/60*1000)-$C$6 -> #REF! | J44: =+(('Modelo Farelo'!AE44*(1+$C$8))*($C$3+1%)+('Modelo Oleo'!AD44*(1))*($C$2-1%))-('Modelo Soja'!AW44/60*1000)-$C$6 -> #REF! | K44: =+(('Modelo Farelo'!AF44*(1+$C$8))*($C$3+1.5%)+('Modelo Oleo'!AE44*(1))*($C$2-1.5%))-('Modelo Soja'!AX44/60*1000)-$C$6 -> #REF! | L44: =+(('Modelo Farelo'!AG44*(1+$C$8))*($C$3+1.5%)+('Modelo Oleo'!AF44*(1))*($C$2-1.5%))-('Modelo Soja'!AY44/60*1000)-$C$6 -> #REF! | M44: =+(('Modelo Farelo'!AH44*(1+$C$8))*$C$3+('Modelo Oleo'!AG44*(1))*$C$2)-('Modelo Soja'!BM44/60*1000)-$C$6 -> #REF! | Q44: =+F44 -> 45444 | R44: =+(('Modelo Farelo'!AB44*(1+$C$8))*$C$3+('Modelo Oleo'!AA44*(1))*$C$2)-('Modelo Soja'!AK44/60*1000)-$C$6 -> #REF! | S44: =+(('Modelo Farelo'!AC44*(1+$C$8))*$C$3+('Modelo Oleo'!AB44*(1))*$C$2)-('Modelo Soja'!AA44/60*1000)-$C$6 -> #REF! | V44: =+'[1]Margem esmagamento stonex'!L8 -> 257.44208 | X44: =+(('Modelo Farelo'!AH44*(1+$C$8))*$C$3+('Modelo Oleo'!AG44*(1))*$C$2)-('Modelo Soja'!AL44/60*1000)-$C$6 -> #REF!
E45: =YEAR(F45) -> 2024 | F45: =+'Modelo Soja'!BA45 -> 45474 | G45: =+(('Modelo Farelo'!AB45*(1+$C$8))*$C$3+('Modelo Oleo'!AA45*(1))*$C$2)-('Modelo Soja'!AT45/60*1000)-$C$6 -> #REF! | H45: =+(('Modelo Farelo'!AC45*(1+$C$8))*$C$3+('Modelo Oleo'!AB45*(1))*$C$2)-('Modelo Soja'!AU45/60*1000)-$C$6 -> #REF! | I45: =+(('Modelo Farelo'!AD45*(1+$C$8))*$C$3+('Modelo Oleo'!AC45*(1))*$C$2)-('Modelo Soja'!AV45/60*1000)-$C$6 -> #REF! | J45: =+(('Modelo Farelo'!AE45*(1+$C$8))*($C$3+1%)+('Modelo Oleo'!AD45*(1))*($C$2-1%))-('Modelo Soja'!AW45/60*1000)-$C$6 -> #REF! | K45: =+(('Modelo Farelo'!AF45*(1+$C$8))*($C$3+1.5%)+('Modelo Oleo'!AE45*(1))*($C$2-1.5%))-('Modelo Soja'!AX45/60*1000)-$C$6 -> #REF! | L45: =+(('Modelo Farelo'!AG45*(1+$C$8))*($C$3+1.5%)+('Modelo Oleo'!AF45*(1))*($C$2-1.5%))-('Modelo Soja'!AY45/60*1000)-$C$6 -> #REF! | M45: =+(('Modelo Farelo'!AH45*(1+$C$8))*$C$3+('Modelo Oleo'!AG45*(1))*$C$2)-('Modelo Soja'!BM45/60*1000)-$C$6 -> #REF! | Q45: =+F45 -> 45474 | R45: =+(('Modelo Farelo'!AB45*(1+$C$8))*$C$3+('Modelo Oleo'!AA45*(1))*$C$2)-('Modelo Soja'!AK45/60*1000)-$C$6 -> #REF! | S45: =+(('Modelo Farelo'!AC45*(1+$C$8))*$C$3+('Modelo Oleo'!AB45*(1))*$C$2)-('Modelo Soja'!AA45/60*1000)-$C$6 -> #REF! | V45: =+'[1]Margem esmagamento stonex'!L9 -> 369.95271 | X45: =+(('Modelo Farelo'!AH45*(1+$C$8))*$C$3+('Modelo Oleo'!AG45*(1))*$C$2)-('Modelo Soja'!AL45/60*1000)-$C$6 -> #REF!
E46: =YEAR(F46) -> 2024 | F46: =+'Modelo Soja'!BA46 -> 45505 | G46: =+(('Modelo Farelo'!AB46*(1+$C$8))*$C$3+('Modelo Oleo'!AA46*(1))*$C$2)-('Modelo Soja'!AT46/60*1000)-$C$6 -> #REF! | H46: =+(('Modelo Farelo'!AC46*(1+$C$8))*$C$3+('Modelo Oleo'!AB46*(1))*$C$2)-('Modelo Soja'!AU46/60*1000)-$C$6 -> #REF! | I46: =+(('Modelo Farelo'!AD46*(1+$C$8))*$C$3+('Modelo Oleo'!AC46*(1))*$C$2)-('Modelo Soja'!AV46/60*1000)-$C$6 -> #REF! | J46: =+(('Modelo Farelo'!AE46*(1+$C$8))*($C$3+1%)+('Modelo Oleo'!AD46*(1))*($C$2-1%))-('Modelo Soja'!AW46/60*1000)-$C$6 -> #REF! | K46: =+(('Modelo Farelo'!AF46*(1+$C$8))*($C$3+1.5%)+('Modelo Oleo'!AE46*(1))*($C$2-1.5%))-('Modelo Soja'!AX46/60*1000)-$C$6 -> #REF! | L46: =+(('Modelo Farelo'!AG46*(1+$C$8))*($C$3+1.5%)+('Modelo Oleo'!AF46*(1))*($C$2-1.5%))-('Modelo Soja'!AY46/60*1000)-$C$6 -> #REF! | M46: =+(('Modelo Farelo'!AH46*(1+$C$8))*$C$3+('Modelo Oleo'!AG46*(1))*$C$2)-('Modelo Soja'!BM46/60*1000)-$C$6 -> #REF! | Q46: =+F46 -> 45505 | R46: =+(('Modelo Farelo'!AB46*(1+$C$8))*$C$3+('Modelo Oleo'!AA46*(1))*$C$2)-('Modelo Soja'!AK46/60*1000)-$C$6 -> #REF! | S46: =+(('Modelo Farelo'!AC46*(1+$C$8))*$C$3+('Modelo Oleo'!AB46*(1))*$C$2)-('Modelo Soja'!AA46/60*1000)-$C$6 -> #REF! | V46: =+'[1]Margem esmagamento stonex'!L10 -> 247.76733 | X46: =+(('Modelo Farelo'!AH46*(1+$C$8))*$C$3+('Modelo Oleo'!AG46*(1))*$C$2)-('Modelo Soja'!AL46/60*1000)-$C$6 -> #REF!
E47: =YEAR(F47) -> 2024 | F47: =+'Modelo Soja'!BA47 -> 45536 | G47: =+(('Modelo Farelo'!AB47*(1+$C$8))*$C$3+('Modelo Oleo'!AA47*(1))*$C$2)-('Modelo Soja'!AT47/60*1000)-$C$6 -> #REF! | H47: =+(('Modelo Farelo'!AC47*(1+$C$8))*$C$3+('Modelo Oleo'!AB47*(1))*$C$2)-('Modelo Soja'!AU47/60*1000)-$C$6 -> #REF! | I47: =+(('Modelo Farelo'!AD47*(1+$C$8))*$C$3+('Modelo Oleo'!AC47*(1))*$C$2)-('Modelo Soja'!AV47/60*1000)-$C$6 -> #REF! | J47: =+(('Modelo Farelo'!AE47*(1+$C$8))*($C$3+1%)+('Modelo Oleo'!AD47*(1))*($C$2-1%))-('Modelo Soja'!AW47/60*1000)-$C$6 -> #REF! | K47: =+(('Modelo Farelo'!AF47*(1+$C$8))*($C$3+1.5%)+('Modelo Oleo'!AE47*(1))*($C$2-1.5%))-('Modelo Soja'!AX47/60*1000)-$C$6 -> #REF! | L47: =+(('Modelo Farelo'!AG47*(1+$C$8))*($C$3+1.5%)+('Modelo Oleo'!AF47*(1))*($C$2-1.5%))-('Modelo Soja'!AY47/60*1000)-$C$6 -> #REF! | M47: =+(('Modelo Farelo'!AH47*(1+$C$8))*$C$3+('Modelo Oleo'!AG47*(1))*$C$2)-('Modelo Soja'!BM47/60*1000)-$C$6 -> #REF! | Q47: =+F47 -> 45536 | R47: =+(('Modelo Farelo'!AB47*(1+$C$8))*$C$3+('Modelo Oleo'!AA47*(1))*$C$2)-('Modelo Soja'!AK47/60*1000)-$C$6 -> #REF! | S47: =+(('Modelo Farelo'!AC47*(1+$C$8))*$C$3+('Modelo Oleo'!AB47*(1))*$C$2)-('Modelo Soja'!AA47/60*1000)-$C$6 -> #REF! | V47: =+'[1]Margem esmagamento stonex'!L11 -> 124.125 | X47: =+(('Modelo Farelo'!AH47*(1+$C$8))*$C$3+('Modelo Oleo'!AG47*(1))*$C$2)-('Modelo Soja'!AL47/60*1000)-$C$6 -> #REF!
E48: =YEAR(F48) -> 2024 | F48: =+'Modelo Soja'!BA48 -> 45566 | G48: =+(('Modelo Farelo'!AB48*(1+$C$8))*$C$3+('Modelo Oleo'!AA48*(1))*$C$2)-('Modelo Soja'!AT48/60*1000)-$C$6 -> #REF! | H48: =+(('Modelo Farelo'!AC48*(1+$C$8))*$C$3+('Modelo Oleo'!AB48*(1))*$C$2)-('Modelo Soja'!AU48/60*1000)-$C$6 -> #REF! | I48: =+(('Modelo Farelo'!AD48*(1+$C$8))*$C$3+('Modelo Oleo'!AC48*(1))*$C$2)-('Modelo Soja'!AV48/60*1000)-$C$6 -> #REF! | J48: =+(('Modelo Farelo'!AE48*(1+$C$8))*($C$3+1%)+('Modelo Oleo'!AD48*(1))*($C$2-1%))-('Modelo Soja'!AW48/60*1000)-$C$6 -> #REF! | K48: =+(('Modelo Farelo'!AF48*(1+$C$8))*($C$3+1.5%)+('Modelo Oleo'!AE48*(1))*($C$2-1.5%))-('Modelo Soja'!AX48/60*1000)-$C$6 -> #REF! | L48: =+(('Modelo Farelo'!AG48*(1+$C$8))*($C$3+1.5%)+('Modelo Oleo'!AF48*(1))*($C$2-1.5%))-('Modelo Soja'!AY48/60*1000)-$C$6 -> #REF! | M48: =+(('Modelo Farelo'!AH48*(1+$C$8))*$C$3+('Modelo Oleo'!AG48*(1))*$C$2)-('Modelo Soja'!BM48/60*1000)-$C$6 -> #REF! | Q48: =+F48 -> 45566 | R48: =+(('Modelo Farelo'!AB48*(1+$C$8))*$C$3+('Modelo Oleo'!AA48*(1))*$C$2)-('Modelo Soja'!AK48/60*1000)-$C$6 -> #REF! | S48: =+(('Modelo Farelo'!AC48*(1+$C$8))*$C$3+('Modelo Oleo'!AB48*(1))*$C$2)-('Modelo Soja'!AA48/60*1000)-$C$6 -> #REF! | V48: =+'[1]Margem esmagamento stonex'!L12 -> -18.8 | X48: =+(('Modelo Farelo'!AH48*(1+$C$8))*$C$3+('Modelo Oleo'!AG48*(1))*$C$2)-('Modelo Soja'!AL48/60*1000)-$C$6 -> #REF!
E49: =YEAR(F49) -> 2024 | F49: =+'Modelo Soja'!BA49 -> 45597 | G49: =+(('Modelo Farelo'!AB49*(1+$C$8))*$C$3+('Modelo Oleo'!AA49*(1))*$C$2)-('Modelo Soja'!AT49/60*1000)-$C$6 -> #REF! | H49: =+(('Modelo Farelo'!AC49*(1+$C$8))*$C$3+('Modelo Oleo'!AB49*(1))*$C$2)-('Modelo Soja'!AU49/60*1000)-$C$6 -> #REF! | I49: =+(('Modelo Farelo'!AD49*(1+$C$8))*$C$3+('Modelo Oleo'!AC49*(1))*$C$2)-('Modelo Soja'!AV49/60*1000)-$C$6 -> #REF! | J49: =+(('Modelo Farelo'!AE49*(1+$C$8))*($C$3+1%)+('Modelo Oleo'!AD49*(1))*($C$2-1%))-('Modelo Soja'!AW49/60*1000)-$C$6 -> #REF! | K49: =+(('Modelo Farelo'!AF49*(1+$C$8))*($C$3+1.5%)+('Modelo Oleo'!AE49*(1))*($C$2-1.5%))-('Modelo Soja'!AX49/60*1000)-$C$6 -> #REF! | L49: =+(('Modelo Farelo'!AG49*(1+$C$8))*($C$3+1.5%)+('Modelo Oleo'!AF49*(1))*($C$2-1.5%))-('Modelo Soja'!AY49/60*1000)-$C$6 -> #REF! | M49: =+(('Modelo Farelo'!AH49*(1+$C$8))*$C$3+('Modelo Oleo'!AG49*(1))*$C$2)-('Modelo Soja'!BM49/60*1000)-$C$6 -> #REF! | Q49: =+F49 -> 45597 | R49: =+(('Modelo Farelo'!AB49*(1+$C$8))*$C$3+('Modelo Oleo'!AA49*(1))*$C$2)-('Modelo Soja'!AK49/60*1000)-$C$6 -> #REF! | S49: =+(('Modelo Farelo'!AC49*(1+$C$8))*$C$3+('Modelo Oleo'!AB49*(1))*$C$2)-('Modelo Soja'!AA49/60*1000)-$C$6 -> #REF! | V49: =+'[1]Margem esmagamento stonex'!L13 -> 29.25 | X49: =+(('Modelo Farelo'!AH49*(1+$C$8))*$C$3+('Modelo Oleo'!AG49*(1))*$C$2)-('Modelo Soja'!AL49/60*1000)-$C$6 -> #REF!
E50: =YEAR(F50) -> 2024 | F50: =+'Modelo Soja'!BA50 -> 45627 | G50: =+(('Modelo Farelo'!AB50*(1+$C$8))*$C$3+('Modelo Oleo'!AA50*(1))*$C$2)-('Modelo Soja'!AT50/60*1000)-$C$6 -> #REF! | H50: =+(('Modelo Farelo'!AC50*(1+$C$8))*$C$3+('Modelo Oleo'!AB50*(1))*$C$2)-('Modelo Soja'!AU50/60*1000)-$C$6 -> #REF! | I50: =+(('Modelo Farelo'!AD50*(1+$C$8))*$C$3+('Modelo Oleo'!AC50*(1))*$C$2)-('Modelo Soja'!AV50/60*1000)-$C$6 -> #REF! | J50: =+(('Modelo Farelo'!AE50*(1+$C$8))*($C$3+1%)+('Modelo Oleo'!AD50*(1))*($C$2-1%))-('Modelo Soja'!AW50/60*1000)-$C$6 -> #REF! | K50: =+(('Modelo Farelo'!AF50*(1+$C$8))*($C$3+1.5%)+('Modelo Oleo'!AE50*(1))*($C$2-1.5%))-('Modelo Soja'!AX50/60*1000)-$C$6 -> #REF! | L50: =+(('Modelo Farelo'!AG50*(1+$C$8))*($C$3+1.5%)+('Modelo Oleo'!AF50*(1))*($C$2-1.5%))-('Modelo Soja'!AY50/60*1000)-$C$6 -> #REF! | M50: =+(('Modelo Farelo'!AH50*(1+$C$8))*$C$3+('Modelo Oleo'!AG50*(1))*$C$2)-('Modelo Soja'!BM50/60*1000)-$C$6 -> #REF! | Q50: =+F50 -> 45627 | R50: =+(('Modelo Farelo'!AB50*(1+$C$8))*$C$3+('Modelo Oleo'!AA50*(1))*$C$2)-('Modelo Soja'!AK50/60*1000)-$C$6 -> #REF! | S50: =+(('Modelo Farelo'!AC50*(1+$C$8))*$C$3+('Modelo Oleo'!AB50*(1))*$C$2)-('Modelo Soja'!AA50/60*1000)-$C$6 -> #REF! | V50: =+'[1]Margem esmagamento stonex'!L14 -> 21.616667 | X50: =+(('Modelo Farelo'!AH50*(1+$C$8))*$C$3+('Modelo Oleo'!AG50*(1))*$C$2)-('Modelo Soja'!AL50/60*1000)-$C$6 -> #REF!
... E65: =YEAR(F65) -> 2026 | F65: =+'Modelo Soja'!BA65 -> 46082 | G65: =+(('Modelo Farelo'!AB65*(1+$C$8))*$C$3+('Modelo Oleo'!AA65*(1))*$C$2)-('Modelo Soja'!AT65/60*1000)-$C$6 -> #REF! | H65: =+(('Modelo Farelo'!AC65*(1+$C$8))*$C$3+('Modelo Oleo'!AB65*(1))*$C$2)-('Modelo Soja'!AU65/60*1000)-$C$6 -> #REF! | I65: =+(('Modelo Farelo'!AD65*(1+$C$8))*$C$3+('Modelo Oleo'!AC65*(1))*$C$2)-('Modelo Soja'!AV65/60*1000)-$C$6 -> #REF! | J65: =+(('Modelo Farelo'!AE65*(1+$C$8))*($C$3+1%)+('Modelo Oleo'!AD65*(1))*($C$2-1%))-('Modelo Soja'!AW65/60*1000)-$C$6 -> #REF! | K65: =+(('Modelo Farelo'!AF65*(1+$C$8))*($C$3+1.5%)+('Modelo Oleo'!AE65*(1))*($C$2-1.5%))-('Modelo Soja'!AX65/60*1000)-$C$6 -> #REF! | L65: =+(('Modelo Farelo'!AG65*(1+$C$8))*($C$3+1.5%)+('Modelo Oleo'!AF65*(1))*($C$2-1.5%))-('Modelo Soja'!AY65/60*1000)-$C$6 -> #REF! | M65: =+(('Modelo Farelo'!AH65*(1+$C$8))*$C$3+('Modelo Oleo'!AG65*(1))*$C$2)-('Modelo Soja'!BM65/60*1000)-$C$6 -> #REF! | Q65: =+F65 -> 46082 | R65: =+(('Modelo Farelo'!AB65*(1+$C$8))*$C$3+('Modelo Oleo'!AA65*(1))*$C$2)-('Modelo Soja'!AK65/60*1000)-$C$6 -> #REF! | S65: =+(('Modelo Farelo'!AC65*(1+$C$8))*$C$3+('Modelo Oleo'!AB65*(1))*$C$2)-('Modelo Soja'!AA65/60*1000)-$C$6 -> #REF! | V65: =+'[1]Margem esmagamento stonex'!L29 -> 324.16667 | X65: =+(('Modelo Farelo'!AH65*(1+$C$8))*$C$3+('Modelo Oleo'!AG65*(1))*$C$2)-('Modelo Soja'!AL65/60*1000)-$C$6 -> #REF!

Sheet Modelo Soja
D1: 16 | E1: 17 | F1: 18 | G1: 19 | H1: 20 | I1: 21 | J1: 22 | K1: 23 | L1: 24 | M1: 25 | N1: 26 | O1: 27 | P1: 28 | Q1: 59 | R1: 61 | S1: 62 | T1: 63 | U1: 64 | AA1: 51 | AB1: 52 | AC1: 53 | AD1: 54 | AE1: 55 | AF1: 56 | AG1: 57 | AH1: 29 | AI1: 30 | AJ1: Diponivel | AN1: Frete | AT1: Paridade Exportação | BB1: Disponível - Balcão | BI1: balcão => grower | BL1: FRETE | BM1: SOJA PAR EXP
B2: COD | C2: MÊS | D2: Soybn Grower Trian Min, MG | E2: Soybn Grower Sorriso, MT | F2: Soybn Grower Sorocabana SP | G2: Soybn Grower Rondonopolis MT | H2: Soybn Grower Rio Verde, GO | I2: Soybn Grower Ponta Grossa PR | J2: Soybn Grower Passo Fundo RS | K2: Soybn Grower West, Parana | L2: Soybn Grower North, Parana | M2: Soybn Grower Mogiana, SP | N2: Soybn Grower Ijui, RS | O2: Soybn Grower Barreiras, BA | P2: Soybn Grower Balsas, MA | Q2: Soybn Grower Campos Novo | R2: BR Soybean - Grower Cg MS | S2: BR Soybean - Grower Dou MS | T2: BR Soybean - Grower Cha-MS | U2: BR Soybean - Grower Mar MS | AA2: Soybn Wholesale Rondonopolis | AB2: Soybn Wholesale Ponta Grossa | AC2: Soybn Wholesale West Parana | AD2: Soybn Wholesale North Parana | AE2: Soybn-Wholesale Mogiana SP | AF2: Soybn Wholesale Triang Min | AG2: Soybn Wholesale Ijui, RS | AH2: Soybn Wholesale Passo Fundo | AI2: Soybn Wholesale Sorocabana | AJ2: Paranagua | AK2: Sorriso | AL2: LRV | AN2: SOR-PRG | AO2: RND-PRG | AP2: TOL-PRG | AQ2: LDN-PRG | AR2: IJI-RGN | AS2: PFD-RGN | AT2: Sorriso | AU2: Rondonopolis | AV2: West Parana | AW2: Londrina | AX2: Ijui | AY2: Passo Fundo | BB2: Ponta Grossa | BC2: West PR | BD2: Mogiana | BE2: Triangulo Min | BF2: Passo Fundo | BG2: Ijui | BH2: Media | BI2: disponivel (limpo, seco,padroniazado, - quebra tecnica) => wholesale | BL2: LRV-PRG | BM2: LRV
B3: =YEAR(C3)&MONTH(C3) -> 20211 | C3: 44197 | D3: =IFERROR(AVERAGEIF('Preço Soja ESALQ'!$C:$C,'Modelo Soja'!$B3,'Preço Soja ESALQ'!$R:$R),NA()) -> 137.83375 | E3: =IFERROR(AVERAGEIF('Preço Soja ESALQ'!$C:$C,'Modelo Soja'!$B3,'Preço Soja ESALQ'!S:S),NA()) -> 146.24917 | F3: =IFERROR(AVERAGEIF('Preço Soja ESALQ'!$C:$C,'Modelo Soja'!$B3,'Preço Soja ESALQ'!T:T),NA()) -> 153.1015 | G3: =IFERROR(AVERAGEIF('Preço Soja ESALQ'!$C:$C,'Modelo Soja'!$B3,'Preço Soja ESALQ'!U:U),NA()) -> #N/A | H3: =IFERROR(AVERAGEIF('Preço Soja ESALQ'!$C:$C,'Modelo Soja'!$B3,'Preço Soja ESALQ'!V:V),NA()) -> 149.924 | I3: =IFERROR(AVERAGEIF('Preço Soja ESALQ'!$C:$C,'Modelo Soja'!$B3,'Preço Soja ESALQ'!W:W),NA()) -> 153.1495 | J3: =IFERROR(AVERAGEIF('Preço Soja ESALQ'!$C:$C,'Modelo Soja'!$B3,'Preço Soja ESALQ'!X:X),NA()) -> 151.5605 | K3: =IFERROR(AVERAGEIF('Preço Soja ESALQ'!$C:$C,'Modelo Soja'!$B3,'Preço Soja ESALQ'!Y:Y),NA()) -> 152.3515 | L3: =IFERROR(AVERAGEIF('Preço Soja ESALQ'!$C:$C,'Modelo Soja'!$B3,'Preço Soja ESALQ'!Z:Z),NA()) -> 152.628 | M3: =IFERROR(AVERAGEIF('Preço Soja ESALQ'!$C:$C,'Modelo Soja'!$B3,'Preço Soja ESALQ'!AA:AA),NA()) -> 142.3465 | N3: =IFERROR(AVERAGEIF('Preço Soja ESALQ'!$C:$C,'Modelo Soja'!$B3,'Preço Soja ESALQ'!AB:AB),NA()) -> 151.222 | O3: =IFERROR(AVERAGEIF('Preço Soja ESALQ'!$C:$C,'Modelo Soja'!$B3,'Preço Soja ESALQ'!AC:AC),NA()) -> 129.39571 | P3: =IFERROR(AVERAGEIF('Preço Soja ESALQ'!$C:$C,'Modelo Soja'!$B3,'Preço Soja ESALQ'!AD:AD),NA()) -> #N/A | Q3: =IFERROR(AVERAGEIF('Preço Soja ESALQ'!$C:$C,'Modelo Soja'!$B3,'Preço Soja ESALQ'!BI:BI),NA()) -> 151.222 | R3: =IFERROR(AVERAGEIF('Preço Soja ESALQ'!$C:$C,'Modelo Soja'!$B3,'Preço Soja ESALQ'!BK:BK),NA()) -> #N/A | S3: =IFERROR(AVERAGEIF('Preço Soja ESALQ'!$C:$C,'Modelo Soja'!$B3,'Preço Soja ESALQ'!BL:BL),NA()) -> 149.045 | T3: =IFERROR(AVERAGEIF('Preço Soja ESALQ'!$C:$C,'Modelo Soja'!$B3,'Preço Soja ESALQ'!BM:BM),NA()) -> #N/A | U3: =IFERROR(AVERAGEIF('Preço Soja ESALQ'!$C:$C,'Modelo Soja'!$B3,'Preço Soja ESALQ'!BN:BN),NA()) -> 148.6305 | AA3: =IFERROR(AVERAGEIF('Preço Soja ESALQ'!$C:$C,'Modelo Soja'!$B3,'Preço Soja ESALQ'!BA:BA),NA()) -> 155.391 | AB3: =IFERROR(AVERAGEIF('Preço Soja ESALQ'!$C:$C,'Modelo Soja'!$B3,'Preço Soja ESALQ'!BB:BB),NA()) -> 164.9765 | AC3: =IFERROR(AVERAGEIF('Preço Soja ESALQ'!$C:$C,'Modelo Soja'!$B3,'Preço Soja ESALQ'!BC:BC),NA()) -> 163.882 | AD3: =IFERROR(AVERAGEIF('Preço Soja ESALQ'!$C:$C,'Modelo Soja'!$B3,'Preço Soja ESALQ'!BD:BD),NA()) -> 160.97 | AE3: =IFERROR(AVERAGEIF('Preço Soja ESALQ'!$C:$C,'Modelo Soja'!$B3,'Preço Soja ESALQ'!BE:BE),NA()) -> 159.8215 | AF3: =IFERROR(AVERAGEIF('Preço Soja ESALQ'!$C:$C,'Modelo Soja'!$B3,'Preço Soja ESALQ'!BF:BF),NA()) -> 160.56444 | AG3: =IFERROR(AVERAGEIF('Preço Soja ESALQ'!$C:$C,'Modelo Soja'!$B3,'Preço Soja ESALQ'!BG:BG),NA()) -> 161.0275 | AH3: =IFERROR(AVERAGEIF('Preço Soja ESALQ'!$C:$C,'Modelo Soja'!$B3,'Preço Soja ESALQ'!AE:AE),NA()) -> 159.507 | AI3: =IFERROR(AVERAGEIF('Preço Soja ESALQ'!$C:$C,'Modelo Soja'!$B3,'Preço Soja ESALQ'!AF:AF),NA()) -> 161.04714 | AJ3: =+[2]summary!C15 -> 167.865 | AK3: =+E3+BJ3 -> 154.74194 | AL3: =+AK3+0.5 -> 155.24194 | AN3: =+[3]FSORPRA!H2 -> 237.5 | AO3: =+[3]FRONPRA!H2 -> 176.25 | AP3: =VLOOKUP(B3,'Frete ESALQ'!$C$6:$AL$132,36,FALSE) -> 86.07 | AQ3: =VLOOKUP(B3,'Frete ESALQ'!$C$6:$AW$132,47,FALSE) -> 71.63 | AR3: =VLOOKUP(B3,'Frete ESALQ'!$C$6:$BH$132,58,FALSE) -> 52.83 | AS3: =VLOOKUP(B3,'Frete ESALQ'!$C$6:$BH$132,32,FALSE) -> 61.11 | AT3: =+AJ3-(AN3*0.06) -> 153.615 | AU3: =+AJ3-(AO3*0.06) -> 157.29 | AV3: =+AJ3-AP3*0.06 -> 162.7008 | AW3: =+AJ3-AQ3*0.06 -> 163.5672 | AX3: =+AG3-AR3*0.06 -> 157.8577 | AY3: =+AH3-AS3*0.06 -> 155.8404 | AZ3: =MONTH(BA3) -> 1 | BA3: =+C3 -> 44197 | BB3: =+AB3-I3 -> 11.827 | BC3: =+AC3-K3 -> 11.5305 | BD3: =+AE3-M3 -> 17.475 | BE3: =+AF3-D3 -> 22.730694 | BF3: =AH3-J3 -> 7.9465 | BG3: =+AG3-N3 -> 9.8055 | BH3: =AVERAGE(BB3:BG3) -> 13.552532 | BI3: 1 | BJ3: =AVERAGEIF($AZ$3:$AZ$64,BI3,$BH$3:$BH$64) -> 8.4927779 | BL3: =+AN3-10 -> 227.5 | BM3: =+AJ3-(BL3/1000*60) -> 154.215
B4: =YEAR(C4)&MONTH(C4) -> 20212 | C4: =EDATE(C3,1) -> 44228 | D4: =IFERROR(AVERAGEIF('Preço Soja ESALQ'!$C:$C,'Modelo Soja'!$B4,'Preço Soja ESALQ'!$R:$R),NA()) -> 147.775 | E4: =IFERROR(AVERAGEIF('Preço Soja ESALQ'!$C:$C,'Modelo Soja'!$B4,'Preço Soja ESALQ'!S:S),NA()) -> 147.96667 | F4: =IFERROR(AVERAGEIF('Preço Soja ESALQ'!$C:$C,'Modelo Soja'!$B4,'Preço Soja ESALQ'!T:T),NA()) -> 153.81056 | G4: =IFERROR(AVERAGEIF('Preço Soja ESALQ'!$C:$C,'Modelo Soja'!$B4,'Preço Soja ESALQ'!U:U),NA()) -> #N/A | H4: =IFERROR(AVERAGEIF('Preço Soja ESALQ'!$C:$C,'Modelo Soja'!$B4,'Preço Soja ESALQ'!V:V),NA()) -> 152.00111 | I4: =IFERROR(AVERAGEIF('Preço Soja ESALQ'!$C:$C,'Modelo Soja'!$B4,'Preço Soja ESALQ'!W:W),NA()) -> 155.22167 | J4: =IFERROR(AVERAGEIF('Preço Soja ESALQ'!$C:$C,'Modelo Soja'!$B4,'Preço Soja ESALQ'!X:X),NA()) -> 155.78556 | K4: =IFERROR(AVERAGEIF('Preço Soja ESALQ'!$C:$C,'Modelo Soja'!$B4,'Preço Soja ESALQ'!Y:Y),NA()) -> 153.97167 | L4: =IFERROR(AVERAGEIF('Preço Soja ESALQ'!$C:$C,'Modelo Soja'!$B4,'Preço Soja ESALQ'!Z:Z),NA()) -> 154.01222 | M4: =IFERROR(AVERAGEIF('Preço Soja ESALQ'!$C:$C,'Modelo Soja'!$B4,'Preço Soja ESALQ'!AA:AA),NA()) -> 147.15 | N4: =IFERROR(AVERAGEIF('Preço Soja ESALQ'!$C:$C,'Modelo Soja'!$B4,'Preço Soja ESALQ'!AB:AB),NA()) -> 155.75056 | O4: =IFERROR(AVERAGEIF('Preço Soja ESALQ'!$C:$C,'Modelo Soja'!$B4,'Preço Soja ESALQ'!AC:AC),NA()) -> 145.63833 | P4: =IFERROR(AVERAGEIF('Preço Soja ESALQ'!$C:$C,'Modelo Soja'!$B4,'Preço Soja ESALQ'!AD:AD),NA()) -> #N/A | Q4: =IFERROR(AVERAGEIF('Preço Soja ESALQ'!$C:$C,'Modelo Soja'!$B4,'Preço Soja ESALQ'!BI:BI),NA()) -> 155.80167 | R4: =IFERROR(AVERAGEIF('Preço Soja ESALQ'!$C:$C,'Modelo Soja'!$B4,'Preço Soja ESALQ'!BK:BK),NA()) -> #N/A | S4: =IFERROR(AVERAGEIF('Preço Soja ESALQ'!$C:$C,'Modelo Soja'!$B4,'Preço Soja ESALQ'!BL:BL),NA()) -> 150.20944 | T4: =IFERROR(AVERAGEIF('Preço Soja ESALQ'!$C:$C,'Modelo Soja'!$B4,'Preço Soja ESALQ'!BM:BM),NA()) -> #N/A | U4: =IFERROR(AVERAGEIF('Preço Soja ESALQ'!$C:$C,'Modelo Soja'!$B4,'Preço Soja ESALQ'!BN:BN),NA()) -> 149.96722 | AA4: =IFERROR(AVERAGEIF('Preço Soja ESALQ'!$C:$C,'Modelo Soja'!$B4,'Preço Soja ESALQ'!BA:BA),NA()) -> 156.51235 | AB4: =IFERROR(AVERAGEIF('Preço Soja ESALQ'!$C:$C,'Modelo Soja'!$B4,'Preço Soja ESALQ'!BB:BB),NA()) -> 162.46 | AC4: =IFERROR(AVERAGEIF('Preço Soja ESALQ'!$C:$C,'Modelo Soja'!$B4,'Preço Soja ESALQ'!BC:BC),NA()) -> 161.32667 | AD4: =IFERROR(AVERAGEIF('Preço Soja ESALQ'!$C:$C,'Modelo Soja'!$B4,'Preço Soja ESALQ'!BD:BD),NA()) -> 158.515 | AE4: =IFERROR(AVERAGEIF('Preço Soja ESALQ'!$C:$C,'Modelo Soja'!$B4,'Preço Soja ESALQ'!BE:BE),NA()) -> 156.77778 | AF4: =IFERROR(AVERAGEIF('Preço Soja ESALQ'!$C:$C,'Modelo Soja'!$B4,'Preço Soja ESALQ'!BF:BF),NA()) -> 156.10667 | AG4: =IFERROR(AVERAGEIF('Preço Soja ESALQ'!$C:$C,'Modelo Soja'!$B4,'Preço Soja ESALQ'!BG:BG),NA()) -> 163.62833 | AH4: =IFERROR(AVERAGEIF('Preço Soja ESALQ'!$C:$C,'Modelo Soja'!$B4,'Preço Soja ESALQ'!AE:AE),NA()) -> 162.62556 | AI4: =IFERROR(AVERAGEIF('Preço Soja ESALQ'!$C:$C,'Modelo Soja'!$B4,'Preço Soja ESALQ'!AF:AF),NA()) -> 156.90647 | AJ4: =+[2]summary!C16 -> 166.38333 | AK4: =+E4+BJ4 -> 153.57667 | AL4: =+AK4+0.5 -> 154.07667 | AN4: =+[3]FSORPRA!H3 -> 304.1675 | AO4: =+[3]FRONPRA!H3 -> 247.5 | AP4: =VLOOKUP(B4,'Frete ESALQ'!$C$6:$AL$132,36,FALSE) -> 131.08 | AQ4: =VLOOKUP(B4,'Frete ESALQ'!$C$6:$AW$132,47,FALSE) -> 113.68 | AR4: =VLOOKUP(B4,'Frete ESALQ'!$C$6:$BH$132,58,FALSE) -> 61.48 | AS4: =VLOOKUP(B4,'Frete ESALQ'!$C$6:$BH$132,32,FALSE) -> 69.66 | AT4: =+AJ4-(AN4*0.06) -> 148.13328 | AU4: =+AJ4-(AO4*0.06) -> 151.53333 | AV4: =+AJ4-AP4*0.06 -> 158.51853 | AW4: =+AJ4-AQ4*0.06 -> 159.56253 | AX4: =+AG4-AR4*0.06 -> 159.93953 | AY4: =+AH4-AS4*0.06 -> 158.44596 | AZ4: =MONTH(BA4) -> 2 | BA4: =+C4 -> 44228 | BB4: =+AB4-I4 -> 7.2383333 | BC4: =+AC4-K4 -> 7.355 | BD4: =+AE4-M4 -> 9.6277778 | BE4: =+AF4-D4 -> 8.3316667 | BF4: =AH4-J4 -> 6.84 | BG4: =+AG4-N4 -> 7.8777778 | BH4: =AVERAGE(BB4:BG4) -> 7.8784259 | BI4: 2 | BJ4: =AVERAGEIF($AZ$3:$AZ$64,BI4,$BH$3:$BH$64) -> 5.6099991 | BL4: =+AN4-10 -> 294.1675 | BM4: =+AJ4-(BL4/1000*60) -> 148.73328
B5: =YEAR(C5)&MONTH(C5) -> 20213 | C5: =EDATE(C4,1) -> 44256 | D5: =IFERROR(AVERAGEIF('Preço Soja ESALQ'!$C:$C,'Modelo Soja'!$B5,'Preço Soja ESALQ'!$R:$R),NA()) -> 155.89435 | E5: =IFERROR(AVERAGEIF('Preço Soja ESALQ'!$C:$C,'Modelo Soja'!$B5,'Preço Soja ESALQ'!S:S),NA()) -> 152.20304 | F5: =IFERROR(AVERAGEIF('Preço Soja ESALQ'!$C:$C,'Modelo Soja'!$B5,'Preço Soja ESALQ'!T:T),NA()) -> 157.84826 | G5: =IFERROR(AVERAGEIF('Preço Soja ESALQ'!$C:$C,'Modelo Soja'!$B5,'Preço Soja ESALQ'!U:U),NA()) -> 161.27357 | H5: =IFERROR(AVERAGEIF('Preço Soja ESALQ'!$C:$C,'Modelo Soja'!$B5,'Preço Soja ESALQ'!V:V),NA()) -> 157.1713 | I5: =IFERROR(AVERAGEIF('Preço Soja ESALQ'!$C:$C,'Modelo Soja'!$B5,'Preço Soja ESALQ'!W:W),NA()) -> 159.28609 | J5: =IFERROR(AVERAGEIF('Preço Soja ESALQ'!$C:$C,'Modelo Soja'!$B5,'Preço Soja ESALQ'!X:X),NA()) -> 161.89609 | K5: =IFERROR(AVERAGEIF('Preço Soja ESALQ'!$C:$C,'Modelo Soja'!$B5,'Preço Soja ESALQ'!Y:Y),NA()) -> 157.47696 | L5: =IFERROR(AVERAGEIF('Preço Soja ESALQ'!$C:$C,'Modelo Soja'!$B5,'Preço Soja ESALQ'!Z:Z),NA()) -> 157.63304 | M5: =IFERROR(AVERAGEIF('Preço Soja ESALQ'!$C:$C,'Modelo Soja'!$B5,'Preço Soja ESALQ'!AA:AA),NA()) -> 158.38261 | N5: =IFERROR(AVERAGEIF('Preço Soja ESALQ'!$C:$C,'Modelo Soja'!$B5,'Preço Soja ESALQ'!AB:AB),NA()) -> 162.27217 | O5: =IFERROR(AVERAGEIF('Preço Soja ESALQ'!$C:$C,'Modelo Soja'!$B5,'Preço Soja ESALQ'!AC:AC),NA()) -> #N/A | P5: =IFERROR(AVERAGEIF('Preço Soja ESALQ'!$C:$C,'Modelo Soja'!$B5,'Preço Soja ESALQ'!AD:AD),NA()) -> #N/A | Q5: =IFERROR(AVERAGEIF('Preço Soja ESALQ'!$C:$C,'Modelo Soja'!$B5,'Preço Soja ESALQ'!BI:BI),NA()) -> 161.07217 | R5: =IFERROR(AVERAGEIF('Preço Soja ESALQ'!$C:$C,'Modelo Soja'!$B5,'Preço Soja ESALQ'!BK:BK),NA()) -> #N/A | S5: =IFERROR(AVERAGEIF('Preço Soja ESALQ'!$C:$C,'Modelo Soja'!$B5,'Preço Soja ESALQ'!BL:BL),NA()) -> 153.60609 | T5: =IFERROR(AVERAGEIF('Preço Soja ESALQ'!$C:$C,'Modelo Soja'!$B5,'Preço Soja ESALQ'!BM:BM),NA()) -> #N/A | U5: =IFERROR(AVERAGEIF('Preço Soja ESALQ'!$C:$C,'Modelo Soja'!$B5,'Preço Soja ESALQ'!BN:BN),NA()) -> 153.05957 | AA5: =IFERROR(AVERAGEIF('Preço Soja ESALQ'!$C:$C,'Modelo Soja'!$B5,'Preço Soja ESALQ'!BA:BA),NA()) -> 161.85435 | AB5: =IFERROR(AVERAGEIF('Preço Soja ESALQ'!$C:$C,'Modelo Soja'!$B5,'Preço Soja ESALQ'!BB:BB),NA()) -> 165.68565 | AC5: =IFERROR(AVERAGEIF('Preço Soja ESALQ'!$C:$C,'Modelo Soja'!$B5,'Preço Soja ESALQ'!BC:BC),NA()) -> 162.08043 | AD5: =IFERROR(AVERAGEIF('Preço Soja ESALQ'!$C:$C,'Modelo Soja'!$B5,'Preço Soja ESALQ'!BD:BD),NA()) -> 160.9513 | AE5: =IFERROR(AVERAGEIF('Preço Soja ESALQ'!$C:$C,'Modelo Soja'!$B5,'Preço Soja ESALQ'!BE:BE),NA()) -> 163.00143 | AF5: =IFERROR(AVERAGEIF('Preço Soja ESALQ'!$C:$C,'Modelo Soja'!$B5,'Preço Soja ESALQ'!BF:BF),NA()) -> 158.45478 | AG5: =IFERROR(AVERAGEIF('Preço Soja ESALQ'!$C:$C,'Modelo Soja'!$B5,'Preço Soja ESALQ'!BG:BG),NA()) -> 168.34696 | AH5: =IFERROR(AVERAGEIF('Preço Soja ESALQ'!$C:$C,'Modelo Soja'!$B5,'Preço Soja ESALQ'!AE:AE),NA()) -> 167.30174 | AI5: =IFERROR(AVERAGEIF('Preço Soja ESALQ'!$C:$C,'Modelo Soja'!$B5,'Preço Soja ESALQ'!AF:AF),NA()) -> 160.39652 | AJ5: =+[2]summary!C17 -> 171.86652 | AK5: =+E5+BJ5 -> 156.93638 | AL5: =+AK5+0.5 -> 157.43638 | AN5: =+[3]FSORPRA!H4 -> 320 | AO5: =+[3]FRONPRA!H4 -> 273.75 | AP5: =VLOOKUP(B5,'Frete ESALQ'!$C$6:$AL$132,36,FALSE) -> 184.08 | AQ5: =VLOOKUP(B5,'Frete ESALQ'!$C$6:$AW$132,47,FALSE) -> 151.22 | AR5: =VLOOKUP(B5,'Frete ESALQ'!$C$6:$BH$132,58,FALSE) -> 123.2 | AS5: =VLOOKUP(B5,'Frete ESALQ'!$C$6:$BH$132,32,FALSE) -> 124.1 | AT5: =+AJ5-(AN5*0.06) -> 152.66652 | AU5: =+AJ5-(AO5*0.06) -> 155.44152 | AV5: =+AJ5-AP5*0.06 -> 160.82172 | AW5: =+AJ5-AQ5*0.06 -> 162.79332 | AX5: =+AG5-AR5*0.06 -> 160.95496 | AY5: =+AH5-AS5*0.06 -> 159.85574 | AZ5: =MONTH(BA5) -> 3 | BA5: =+C5 -> 44256 | BB5: =+AB5-I5 -> 6.3995652 | BC5: =+AC5-K5 -> 4.6034783 | BD5: =+AE5-M5 -> 4.6188199 | BE5: =+AF5-D5 -> 2.5604348 | BF5: =AH5-J5 -> 5.4056522 | BG5: =+AG5-N5 -> 6.0747826 | BH5: =AVERAGE(BB5:BG5) -> 4.9437888 | BI5: 3 | BJ5: =AVERAGEIF($AZ$3:$AZ$64,BI5,$BH$3:$BH$64) -> 4.7333335 | BL5: =+AN5-10 -> 310 | BM5: =+AJ5-(BL5/1000*60) -> 153.26652
B6: =YEAR(C6)&MONTH(C6) -> 20214 | C6: =EDATE(C5,1) -> 44287 | D6: =IFERROR(AVERAGEIF('Preço Soja ESALQ'!$C:$C,'Modelo Soja'!$B6,'Preço Soja ESALQ'!$R:$R),NA()) -> 159.9195 | E6: =IFERROR(AVERAGEIF('Preço Soja ESALQ'!$C:$C,'Modelo Soja'!$B6,'Preço Soja ESALQ'!S:S),NA()) -> 154.3615 | F6: =IFERROR(AVERAGEIF('Preço Soja ESALQ'!$C:$C,'Modelo Soja'!$B6,'Preço Soja ESALQ'!T:T),NA()) -> 162.021 | G6: =IFERROR(AVERAGEIF('Preço Soja ESALQ'!$C:$C,'Modelo Soja'!$B6,'Preço Soja ESALQ'!U:U),NA()) -> 163.056 | H6: =IFERROR(AVERAGEIF('Preço Soja ESALQ'!$C:$C,'Modelo Soja'!$B6,'Preço Soja ESALQ'!V:V),NA()) -> 161.0905 | I6: =IFERROR(AVERAGEIF('Preço Soja ESALQ'!$C:$C,'Modelo Soja'!$B6,'Preço Soja ESALQ'!W:W),NA()) -> 162.837 | J6: =IFERROR(AVERAGEIF('Preço Soja ESALQ'!$C:$C,'Modelo Soja'!$B6,'Preço Soja ESALQ'!X:X),NA()) -> 166.2215 | K6: =IFERROR(AVERAGEIF('Preço Soja ESALQ'!$C:$C,'Modelo Soja'!$B6,'Preço Soja ESALQ'!Y:Y),NA()) -> 159.7155 | L6: =IFERROR(AVERAGEIF('Preço Soja ESALQ'!$C:$C,'Modelo Soja'!$B6,'Preço Soja ESALQ'!Z:Z),NA()) -> 159.6525 | M6: =IFERROR(AVERAGEIF('Preço Soja ESALQ'!$C:$C,'Modelo Soja'!$B6,'Preço Soja ESALQ'!AA:AA),NA()) -> 160.8835 | N6: =IFERROR(AVERAGEIF('Preço Soja ESALQ'!$C:$C,'Modelo Soja'!$B6,'Preço Soja ESALQ'!AB:AB),NA()) -> 166.8875 | O6: =IFERROR(AVERAGEIF('Preço Soja ESALQ'!$C:$C,'Modelo Soja'!$B6,'Preço Soja ESALQ'!AC:AC),NA()) -> #N/A | P6: =IFERROR(AVERAGEIF('Preço Soja ESALQ'!$C:$C,'Modelo Soja'!$B6,'Preço Soja ESALQ'!AD:AD),NA()) -> 161.96 | Q6: =IFERROR(AVERAGEIF('Preço Soja ESALQ'!$C:$C,'Modelo Soja'!$B6,'Preço Soja ESALQ'!BI:BI),NA()) -> 165.3275 | R6: =IFERROR(AVERAGEIF('Preço Soja ESALQ'!$C:$C,'Modelo Soja'!$B6,'Preço Soja ESALQ'!BK:BK),NA()) -> #N/A | S6: =IFERROR(AVERAGEIF('Preço Soja ESALQ'!$C:$C,'Modelo Soja'!$B6,'Preço Soja ESALQ'!BL:BL),NA()) -> 155.8245 | T6: =IFERROR(AVERAGEIF('Preço Soja ESALQ'!$C:$C,'Modelo Soja'!$B6,'Preço Soja ESALQ'!BM:BM),NA()) -> #N/A | U6: =IFERROR(AVERAGEIF('Preço Soja ESALQ'!$C:$C,'Modelo Soja'!$B6,'Preço Soja ESALQ'!BN:BN),NA()) -> 155.29 | AA6: =IFERROR(AVERAGEIF('Preço Soja ESALQ'!$C:$C,'Modelo Soja'!$B6,'Preço Soja ESALQ'!BA:BA),NA()) -> 166.0135 | AB6: =IFERROR(AVERAGEIF('Preço Soja ESALQ'!$C:$C,'Modelo Soja'!$B6,'Preço Soja ESALQ'!BB:BB),NA()) -> 171.52 | AC6: =IFERROR(AVERAGEIF('Preço Soja ESALQ'!$C:$C,'Modelo Soja'!$B6,'Preço Soja ESALQ'!BC:BC),NA()) -> 170.177 | AD6: =IFERROR(AVERAGEIF('Preço Soja ESALQ'!$C:$C,'Modelo Soja'!$B6,'Preço Soja ESALQ'!BD:BD),NA()) -> 167.034 | AE6: =IFERROR(AVERAGEIF('Preço Soja ESALQ'!$C:$C,'Modelo Soja'!$B6,'Preço Soja ESALQ'!BE:BE),NA()) -> 165.005 | AF6: =IFERROR(AVERAGEIF('Preço Soja ESALQ'!$C:$C,'Modelo Soja'!$B6,'Preço Soja ESALQ'!BF:BF),NA()) -> 164.65 | AG6: =IFERROR(AVERAGEIF('Preço Soja ESALQ'!$C:$C,'Modelo Soja'!$B6,'Preço Soja ESALQ'!BG:BG),NA()) -> 171.3645 | AH6: =IFERROR(AVERAGEIF('Preço Soja ESALQ'!$C:$C,'Modelo Soja'!$B6,'Preço Soja ESALQ'!AE:AE),NA()) -> 171.2645 | AI6: =IFERROR(AVERAGEIF('Preço Soja ESALQ'!$C:$C,'Modelo Soja'!$B6,'Preço Soja ESALQ'!AF:AF),NA()) -> 165.327 | AJ6: =+[2]summary!C18 -> 177.098 | AK6: =+E6+BJ6 -> 159.7704 | AL6: =+AK6+0.5 -> 160.2704 | AN6: =+[3]FSORPRA!H5 -> 307 | AO6: =+[3]FRONPRA!H5 -> 263 | AP6: =VLOOKUP(B6,'Frete ESALQ'!$C$6:$AL$132,36,FALSE) -> 94.82 | AQ6: =VLOOKUP(B6,'Frete ESALQ'!$C$6:$AW$132,47,FALSE) -> 123.97 | AR6: =VLOOKUP(B6,'Frete ESALQ'!$C$6:$BH$132,58,FALSE) -> 121.3 | AS6: =VLOOKUP(B6,'Frete ESALQ'!$C$6:$BH$132,32,FALSE) -> 129.03 | AT6: =+AJ6-(AN6*0.06) -> 158.678 | AU6: =+AJ6-(AO6*0.06) -> 161.318 | AV6: =+AJ6-AP6*0.06 -> 171.4088 | AW6: =+AJ6-AQ6*0.06 -> 169.6598 | AX6: =+AG6-AR6*0.06 -> 164.0865 | AY6: =+AH6-AS6*0.06 -> 163.5227 | AZ6: =MONTH(BA6) -> 4 | BA6: =+C6 -> 44287 | BB6: =+AB6-I6 -> 8.683 | BC6: =+AC6-K6 -> 10.4615 | BD6: =+AE6-M6 -> 4.1215 | BE6: =+AF6-D6 -> 4.7305 | BF6: =AH6-J6 -> 5.043 | BG6: =+AG6-N6 -> 4.477 | BH6: =AVERAGE(BB6:BG6) -> 6.25275 | BI6: 4 | BJ6: =AVERAGEIF($AZ$3:$AZ$64,BI6,$BH$3:$BH$64) -> 5.4089011 | BL6: =+AN6-10 -> 297 | BM6: =+AJ6-(BL6/1000*60) -> 159.278
B7: =YEAR(C7)&MONTH(C7) -> 20215 | C7: =EDATE(C6,1) -> 44317 | D7: =IFERROR(AVERAGEIF('Preço Soja ESALQ'!$C:$C,'Modelo Soja'!$B7,'Preço Soja ESALQ'!$R:$R),NA()) -> 161.36619 | E7: =IFERROR(AVERAGEIF('Preço Soja ESALQ'!$C:$C,'Modelo Soja'!$B7,'Preço Soja ESALQ'!S:S),NA()) -> 156.33524 | F7: =IFERROR(AVERAGEIF('Preço Soja ESALQ'!$C:$C,'Modelo Soja'!$B7,'Preço Soja ESALQ'!T:T),NA()) -> 161.93619 | G7: =IFERROR(AVERAGEIF('Preço Soja ESALQ'!$C:$C,'Modelo Soja'!$B7,'Preço Soja ESALQ'!U:U),NA()) -> 163.99647 | H7: =IFERROR(AVERAGEIF('Preço Soja ESALQ'!$C:$C,'Modelo Soja'!$B7,'Preço Soja ESALQ'!V:V),NA()) -> 163.56952 | I7: =IFERROR(AVERAGEIF('Preço Soja ESALQ'!$C:$C,'Modelo Soja'!$B7,'Preço Soja ESALQ'!W:W),NA()) -> 163.15857 | J7: =IFERROR(AVERAGEIF('Preço Soja ESALQ'!$C:$C,'Modelo Soja'!$B7,'Preço Soja ESALQ'!X:X),NA()) -> 163.88524 | K7: =IFERROR(AVERAGEIF('Preço Soja ESALQ'!$C:$C,'Modelo Soja'!$B7,'Preço Soja ESALQ'!Y:Y),NA()) -> 159.56048 | L7: =IFERROR(AVERAGEIF('Preço Soja ESALQ'!$C:$C,'Modelo Soja'!$B7,'Preço Soja ESALQ'!Z:Z),NA()) -> 159.46286 | M7: =IFERROR(AVERAGEIF('Preço Soja ESALQ'!$C:$C,'Modelo Soja'!$B7,'Preço Soja ESALQ'!AA:AA),NA()) -> 163.64143 | N7: =IFERROR(AVERAGEIF('Preço Soja ESALQ'!$C:$C,'Modelo Soja'!$B7,'Preço Soja ESALQ'!AB:AB),NA()) -> 164.11143 | O7: =IFERROR(AVERAGEIF('Preço Soja ESALQ'!$C:$C,'Modelo Soja'!$B7,'Preço Soja ESALQ'!AC:AC),NA()) -> #N/A | P7: =IFERROR(AVERAGEIF('Preço Soja ESALQ'!$C:$C,'Modelo Soja'!$B7,'Preço Soja ESALQ'!AD:AD),NA()) -> #N/A | Q7: =IFERROR(AVERAGEIF('Preço Soja ESALQ'!$C:$C,'Modelo Soja'!$B7,'Preço Soja ESALQ'!BI:BI),NA()) -> 165.66381 | R7: =IFERROR(AVERAGEIF('Preço Soja ESALQ'!$C:$C,'Modelo Soja'!$B7,'Preço Soja ESALQ'!BK:BK),NA()) -> 154.20667 | S7: =IFERROR(AVERAGEIF('Preço Soja ESALQ'!$C:$C,'Modelo Soja'!$B7,'Preço Soja ESALQ'!BL:BL),NA()) -> 157.23562 | T7: =IFERROR(AVERAGEIF('Preço Soja ESALQ'!$C:$C,'Modelo Soja'!$B7,'Preço Soja ESALQ'!BM:BM),NA()) -> #N/A | U7: =IFERROR(AVERAGEIF('Preço Soja ESALQ'!$C:$C,'Modelo Soja'!$B7,'Preço Soja ESALQ'!BN:BN),NA()) -> 158.4175 | AA7: =IFERROR(AVERAGEIF('Preço Soja ESALQ'!$C:$C,'Modelo Soja'!$B7,'Preço Soja ESALQ'!BA:BA),NA()) -> 167.5481 | AB7: =IFERROR(AVERAGEIF('Preço Soja ESALQ'!$C:$C,'Modelo Soja'!$B7,'Preço Soja ESALQ'!BB:BB),NA()) -> 171.62571 | AC7: =IFERROR(AVERAGEIF('Preço Soja ESALQ'!$C:$C,'Modelo Soja'!$B7,'Preço Soja ESALQ'!BC:BC),NA()) -> 171.07714 | AD7: =IFERROR(AVERAGEIF('Preço Soja ESALQ'!$C:$C,'Modelo Soja'!$B7,'Preço Soja ESALQ'!BD:BD),NA()) -> 168.52667 | AE7: =IFERROR(AVERAGEIF('Preço Soja ESALQ'!$C:$C,'Modelo Soja'!$B7,'Preço Soja ESALQ'!BE:BE),NA()) -> 166.89667 | AF7: =IFERROR(AVERAGEIF('Preço Soja ESALQ'!$C:$C,'Modelo Soja'!$B7,'Preço Soja ESALQ'!BF:BF),NA()) -> 169.16952 | AG7: =IFERROR(AVERAGEIF('Preço Soja ESALQ'!$C:$C,'Modelo Soja'!$B7,'Preço Soja ESALQ'!BG:BG),NA()) -> 172.45 | AH7: =IFERROR(AVERAGEIF('Preço Soja ESALQ'!$C:$C,'Modelo Soja'!$B7,'Preço Soja ESALQ'!AE:AE),NA()) -> 171.90286 | AI7: =IFERROR(AVERAGEIF('Preço Soja ESALQ'!$C:$C,'Modelo Soja'!$B7,'Preço Soja ESALQ'!AF:AF),NA()) -> 167.49952 | AJ7: =+[2]summary!C19 -> 176.39381 | AK7: =+E7+BJ7 -> 163.45526 | AL7: =+AK7+0.5 -> 163.95526 | AN7: =+[3]FSORPRA!H6 -> 289.25 | AO7: =+[3]FRONPRA!H6 -> 265 | AP7: =VLOOKUP(B7,'Frete ESALQ'!$C$6:$AL$132,36,FALSE) -> 101.73 | AQ7: =VLOOKUP(B7,'Frete ESALQ'!$C$6:$AW$132,47,FALSE) -> 104.75 | AR7: =VLOOKUP(B7,'Frete ESALQ'!$C$6:$BH$132,58,FALSE) -> 95 | AS7: =VLOOKUP(B7,'Frete ESALQ'!$C$6:$BH$132,32,FALSE) -> 98.38 | AT7: =+AJ7-(AN7*0.06) -> 159.03881 | AU7: =+AJ7-(AO7*0.06) -> 160.49381 | AV7: =+AJ7-AP7*0.06 -> 170.29001 | AW7: =+AJ7-AQ7*0.06 -> 170.10881 | AX7: =+AG7-AR7*0.06 -> 166.75 | AY7: =+AH7-AS7*0.06 -> 166.00006 | AZ7: =MONTH(BA7) -> 5 | BA7: =+C7 -> 44317 | BB7: =+AB7-I7 -> 8.4671429 | BC7: =+AC7-K7 -> 11.516667 | BD7: =+AE7-M7 -> 3.2552381 | BE7: =+AF7-D7 -> 7.8033333 | BF7: =AH7-J7 -> 8.017619 | BG7: =+AG7-N7 -> 8.3385714 | BH7: =AVERAGE(BB7:BG7) -> 7.8997619 | BI7: 5 | BJ7: =AVERAGEIF($AZ$3:$AZ$64,BI7,$BH$3:$BH$64) -> 7.120018 | BL7: =+AN7-10 -> 279.25 | BM7: =+AJ7-(BL7/1000*60) -> 159.63881
B8: =YEAR(C8)&MONTH(C8) -> 20216 | C8: =EDATE(C7,1) -> 44348 | D8: =IFERROR(AVERAGEIF('Preço Soja ESALQ'!$C:$C,'Modelo Soja'!$B8,'Preço Soja ESALQ'!$R:$R),NA()) -> 147.84095 | E8: =IFERROR(AVERAGEIF('Preço Soja ESALQ'!$C:$C,'Modelo Soja'!$B8,'Preço Soja ESALQ'!S:S),NA()) -> 140.56714 | F8: =IFERROR(AVERAGEIF('Preço Soja ESALQ'!$C:$C,'Modelo Soja'!$B8,'Preço Soja ESALQ'!T:T),NA()) -> 150.37952 | G8: =IFERROR(AVERAGEIF('Preço Soja ESALQ'!$C:$C,'Modelo Soja'!$B8,'Preço Soja ESALQ'!U:U),NA()) -> 153.493 | H8: =IFERROR(AVERAGEIF('Preço Soja ESALQ'!$C:$C,'Modelo Soja'!$B8,'Preço Soja ESALQ'!V:V),NA()) -> 150.14952 | I8: =IFERROR(AVERAGEIF('Preço Soja ESALQ'!$C:$C,'Modelo Soja'!$B8,'Preço Soja ESALQ'!W:W),NA()) -> 149.67143 | J8: =IFERROR(AVERAGEIF('Preço Soja ESALQ'!$C:$C,'Modelo Soja'!$B8,'Preço Soja ESALQ'!X:X),NA()) -> 148.56381 | K8: =IFERROR(AVERAGEIF('Preço Soja ESALQ'!$C:$C,'Modelo Soja'!$B8,'Preço Soja ESALQ'!Y:Y),NA()) -> 145.52857 | L8: =IFERROR(AVERAGEIF('Preço Soja ESALQ'!$C:$C,'Modelo Soja'!$B8,'Preço Soja ESALQ'!Z:Z),NA()) -> 145.72 | M8: =IFERROR(AVERAGEIF('Preço Soja ESALQ'!$C:$C,'Modelo Soja'!$B8,'Preço Soja ESALQ'!AA:AA),NA()) -> 148.76857 | N8: =IFERROR(AVERAGEIF('Preço Soja ESALQ'!$C:$C,'Modelo Soja'!$B8,'Preço Soja ESALQ'!AB:AB),NA()) -> 148.68381 | O8: =IFERROR(AVERAGEIF('Preço Soja ESALQ'!$C:$C,'Modelo Soja'!$B8,'Preço Soja ESALQ'!AC:AC),NA()) -> #N/A | P8: =IFERROR(AVERAGEIF('Preço Soja ESALQ'!$C:$C,'Modelo Soja'!$B8,'Preço Soja ESALQ'!AD:AD),NA()) -> #N/A | Q8: =IFERROR(AVERAGEIF('Preço Soja ESALQ'!$C:$C,'Modelo Soja'!$B8,'Preço Soja ESALQ'!BI:BI),NA()) -> 151.0081 | R8: =IFERROR(AVERAGEIF('Preço Soja ESALQ'!$C:$C,'Modelo Soja'!$B8,'Preço Soja ESALQ'!BK:BK),NA()) -> 142.40824 | S8: =IFERROR(AVERAGEIF('Preço Soja ESALQ'!$C:$C,'Modelo Soja'!$B8,'Preço Soja ESALQ'!BL:BL),NA()) -> 142.99238 | T8: =IFERROR(AVERAGEIF('Preço Soja ESALQ'!$C:$C,'Modelo Soja'!$B8,'Preço Soja ESALQ'!BM:BM),NA()) -> #N/A | U8: =IFERROR(AVERAGEIF('Preço Soja ESALQ'!$C:$C,'Modelo Soja'!$B8,'Preço Soja ESALQ'!BN:BN),NA()) -> 142.8081 | AA8: =IFERROR(AVERAGEIF('Preço Soja ESALQ'!$C:$C,'Modelo Soja'!$B8,'Preço Soja ESALQ'!BA:BA),NA()) -> 151.94421 | AB8: =IFERROR(AVERAGEIF('Preço Soja ESALQ'!$C:$C,'Modelo Soja'!$B8,'Preço Soja ESALQ'!BB:BB),NA()) -> 158.25381 | AC8: =IFERROR(AVERAGEIF('Preço Soja ESALQ'!$C:$C,'Modelo Soja'!$B8,'Preço Soja ESALQ'!BC:BC),NA()) -> 156.6919 | AD8: =IFERROR(AVERAGEIF('Preço Soja ESALQ'!$C:$C,'Modelo Soja'!$B8,'Preço Soja ESALQ'!BD:BD),NA()) -> 154.17762 | AE8: =IFERROR(AVERAGEIF('Preço Soja ESALQ'!$C:$C,'Modelo Soja'!$B8,'Preço Soja ESALQ'!BE:BE),NA()) -> 155.32095 | AF8: =IFERROR(AVERAGEIF('Preço Soja ESALQ'!$C:$C,'Modelo Soja'!$B8,'Preço Soja ESALQ'!BF:BF),NA()) -> 155.53381 | AG8: =IFERROR(AVERAGEIF('Preço Soja ESALQ'!$C:$C,'Modelo Soja'!$B8,'Preço Soja ESALQ'!BG:BG),NA()) -> 156.83524 | AH8: =IFERROR(AVERAGEIF('Preço Soja ESALQ'!$C:$C,'Modelo Soja'!$B8,'Preço Soja ESALQ'!AE:AE),NA()) -> 156.31571 | AI8: =IFERROR(AVERAGEIF('Preço Soja ESALQ'!$C:$C,'Modelo Soja'!$B8,'Preço Soja ESALQ'!AF:AF),NA()) -> 154.49333 | AJ8: =+[2]summary!C20 -> 162.07571 | AK8: =+E8+BJ8 -> 148.4744 | AL8: =+AK8+0.5 -> 148.9744 | AN8: =+[3]FSORPRA!H7 -> 295.8325 | AO8: =+[3]FRONPRA!H7 -> 242.5 | AP8: =VLOOKUP(B8,'Frete ESALQ'!$C$6:$AL$132,36,FALSE) -> 96.49 | AQ8: =VLOOKUP(B8,'Frete ESALQ'!$C$6:$AW$132,47,FALSE) -> 84.57 | AR8: =VLOOKUP(B8,'Frete ESALQ'!$C$6:$BH$132,58,FALSE) -> 94.83 | AS8: =VLOOKUP(B8,'Frete ESALQ'!$C$6:$BH$132,32,FALSE) -> 84 | AT8: =+AJ8-(AN8*0.06) -> 144.32576 | AU8: =+AJ8-(AO8*0.06) -> 147.52571 | AV8: =+AJ8-AP8*0.06 -> 156.28631 | AW8: =+AJ8-AQ8*0.06 -> 157.00151 | AX8: =+AG8-AR8*0.06 -> 151.14544 | AY8: =+AH8-AS8*0.06 -> 151.27571 | AZ8: =MONTH(BA8) -> 6 | BA8: =+C8 -> 44348 | BB8: =+AB8-I8 -> 8.582381 | BC8: =+AC8-K8 -> 11.163333 | BD8: =+AE8-M8 -> 6.552381 | BE8: =+AF8-D8 -> 7.6928571 | BF8: =AH8-J8 -> 7.7519048 | BG8: =+AG8-N8 -> 8.1514286 | BH8: =AVERAGE(BB8:BG8) -> 8.3157143 | BI8: 6 | BJ8: =AVERAGEIF($AZ$3:$AZ$64,BI8,$BH$3:$BH$64) -> 7.9072587 | BL8: =+AN8-10 -> 285.8325 | BM8: =+AJ8-(BL8/1000*60) -> 144.92576
B9: =YEAR(C9)&MONTH(C9) -> 20217 | C9: =EDATE(C8,1) -> 44378 | D9: =IFERROR(AVERAGEIF('Preço Soja ESALQ'!$C:$C,'Modelo Soja'!$B9,'Preço Soja ESALQ'!$R:$R),NA()) -> 144.99136 | E9: =IFERROR(AVERAGEIF('Preço Soja ESALQ'!$C:$C,'Modelo Soja'!$B9,'Preço Soja ESALQ'!S:S),NA()) -> 148.32818 | F9: =IFERROR(AVERAGEIF('Preço Soja ESALQ'!$C:$C,'Modelo Soja'!$B9,'Preço Soja ESALQ'!T:T),NA()) -> 153.45591 | G9: =IFERROR(AVERAGEIF('Preço Soja ESALQ'!$C:$C,'Modelo Soja'!$B9,'Preço Soja ESALQ'!U:U),NA()) -> 155.86923 | H9: =IFERROR(AVERAGEIF('Preço Soja ESALQ'!$C:$C,'Modelo Soja'!$B9,'Preço Soja ESALQ'!V:V),NA()) -> 148.68818 | I9: =IFERROR(AVERAGEIF('Preço Soja ESALQ'!$C:$C,'Modelo Soja'!$B9,'Preço Soja ESALQ'!W:W),NA()) -> 153.06136 | J9: =IFERROR(AVERAGEIF('Preço Soja ESALQ'!$C:$C,'Modelo Soja'!$B9,'Preço Soja ESALQ'!X:X),NA()) -> 151.61682 | K9: =IFERROR(AVERAGEIF('Preço Soja ESALQ'!$C:$C,'Modelo Soja'!$B9,'Preço Soja ESALQ'!Y:Y),NA()) -> 150.88409 | L9: =IFERROR(AVERAGEIF('Preço Soja ESALQ'!$C:$C,'Modelo Soja'!$B9,'Preço Soja ESALQ'!Z:Z),NA()) -> 150.87545 | M9: =IFERROR(AVERAGEIF('Preço Soja ESALQ'!$C:$C,'Modelo Soja'!$B9,'Preço Soja ESALQ'!AA:AA),NA()) -> 147.11227 | N9: =IFERROR(AVERAGEIF('Preço Soja ESALQ'!$C:$C,'Modelo Soja'!$B9,'Preço Soja ESALQ'!AB:AB),NA()) -> 151.49818 | O9: =IFERROR(AVERAGEIF('Preço Soja ESALQ'!$C:$C,'Modelo Soja'!$B9,'Preço Soja ESALQ'!AC:AC),NA()) -> #N/A | P9: =IFERROR(AVERAGEIF('Preço Soja ESALQ'!$C:$C,'Modelo Soja'!$B9,'Preço Soja ESALQ'!AD:AD),NA()) -> #N/A | Q9: =IFERROR(AVERAGEIF('Preço Soja ESALQ'!$C:$C,'Modelo Soja'!$B9,'Preço Soja ESALQ'!BI:BI),NA()) -> 154.21 | R9: =IFERROR(AVERAGEIF('Preço Soja ESALQ'!$C:$C,'Modelo Soja'!$B9,'Preço Soja ESALQ'!BK:BK),NA()) -> 145.43 | S9: =IFERROR(AVERAGEIF('Preço Soja ESALQ'!$C:$C,'Modelo Soja'!$B9,'Preço Soja ESALQ'!BL:BL),NA()) -> 146.80136 | T9: =IFERROR(AVERAGEIF('Preço Soja ESALQ'!$C:$C,'Modelo Soja'!$B9,'Preço Soja ESALQ'!BM:BM),NA()) -> #N/A | U9: =IFERROR(AVERAGEIF('Preço Soja ESALQ'!$C:$C,'Modelo Soja'!$B9,'Preço Soja ESALQ'!BN:BN),NA()) -> 146.39955 | AA9: =IFERROR(AVERAGEIF('Preço Soja ESALQ'!$C:$C,'Modelo Soja'!$B9,'Preço Soja ESALQ'!BA:BA),NA()) -> 160.09818 | AB9: =IFERROR(AVERAGEIF('Preço Soja ESALQ'!$C:$C,'Modelo Soja'!$B9,'Preço Soja ESALQ'!BB:BB),NA()) -> 163.14773 | AC9: =IFERROR(AVERAGEIF('Preço Soja ESALQ'!$C:$C,'Modelo Soja'!$B9,'Preço Soja ESALQ'!BC:BC),NA()) -> 162.50227 | AD9: =IFERROR(AVERAGEIF('Preço Soja ESALQ'!$C:$C,'Modelo Soja'!$B9,'Preço Soja ESALQ'!BD:BD),NA()) -> 159.80136 | AE9: =IFERROR(AVERAGEIF('Preço Soja ESALQ'!$C:$C,'Modelo Soja'!$B9,'Preço Soja ESALQ'!BE:BE),NA()) -> 159.27318 | AF9: =IFERROR(AVERAGEIF('Preço Soja ESALQ'!$C:$C,'Modelo Soja'!$B9,'Preço Soja ESALQ'!BF:BF),NA()) -> 162.105 | AG9: =IFERROR(AVERAGEIF('Preço Soja ESALQ'!$C:$C,'Modelo Soja'!$B9,'Preço Soja ESALQ'!BG:BG),NA()) -> 161.71273 | AH9: =IFERROR(AVERAGEIF('Preço Soja ESALQ'!$C:$C,'Modelo Soja'!$B9,'Preço Soja ESALQ'!AE:AE),NA()) -> 161.29545 | AI9: =IFERROR(AVERAGEIF('Preço Soja ESALQ'!$C:$C,'Modelo Soja'!$B9,'Preço Soja ESALQ'!AF:AF),NA()) -> 158.79318 | AJ9: =+[2]summary!C21 -> 167.59682 | AK9: =+E9+BJ9 -> 157.62259 | AL9: =+AK9+0.5 -> 158.12259 | AN9: =+[3]FSORPRA!H8 -> 325 | AO9: =+[3]FRONPRA!H8 -> 270 | AP9: =VLOOKUP(B9,'Frete ESALQ'!$C$6:$AL$132,36,FALSE) -> 86.17 | AQ9: =VLOOKUP(B9,'Frete ESALQ'!$C$6:$AW$132,47,FALSE) -> 80.75 | AR9: =VLOOKUP(B9,'Frete ESALQ'!$C$6:$BH$132,58,FALSE) -> 77.68 | AS9: =VLOOKUP(B9,'Frete ESALQ'!$C$6:$BH$132,32,FALSE) -> 72 | AT9: =+AJ9-(AN9*0.06) -> 148.09682 | AU9: =+AJ9-(AO9*0.06) -> 151.39682 | AV9: =+AJ9-AP9*0.06 -> 162.42662 | AW9: =+AJ9-AQ9*0.06 -> 162.75182 | AX9: =+AG9-AR9*0.06 -> 157.05193 | AY9: =+AH9-AS9*0.06 -> 156.97545 | AZ9: =MONTH(BA9) -> 7 | BA9: =+C9 -> 44378 | BB9: =+AB9-I9 -> 10.086364 | BC9: =+AC9-K9 -> 11.618182 | BD9: =+AE9-M9 -> 12.160909 | BE9: =+AF9-D9 -> 17.113636 | BF9: =AH9-J9 -> 9.6786364 | BG9: =+AG9-N9 -> 10.214545 | BH9: =AVERAGE(BB9:BG9) -> 11.812045 | BI9: 7 | BJ9: =AVERAGEIF($AZ$3:$AZ$64,BI9,$BH$3:$BH$64) -> 9.2944043 | BL9: =+AN9-10 -> 315 | BM9: =+AJ9-(BL9/1000*60) -> 148.69682
B10: =YEAR(C10)&MONTH(C10) -> 20218 | C10: =EDATE(C9,1) -> 44409 | D10: =IFERROR(AVERAGEIF('Preço Soja ESALQ'!$C:$C,'Modelo Soja'!$B10,'Preço Soja ESALQ'!$R:$R),NA()) -> 150.31318 | E10: =IFERROR(AVERAGEIF('Preço Soja ESALQ'!$C:$C,'Modelo Soja'!$B10,'Preço Soja ESALQ'!S:S),NA()) -> 158.16318 | F10: =IFERROR(AVERAGEIF('Preço Soja ESALQ'!$C:$C,'Modelo Soja'!$B10,'Preço Soja ESALQ'!T:T),NA()) -> 158.63 | G10: =IFERROR(AVERAGEIF('Preço Soja ESALQ'!$C:$C,'Modelo Soja'!$B10,'Preço Soja ESALQ'!U:U),NA()) -> 160.70375 | H10: =IFERROR(AVERAGEIF('Preço Soja ESALQ'!$C:$C,'Modelo Soja'!$B10,'Preço Soja ESALQ'!V:V),NA()) -> 156.36864 | I10: =IFERROR(AVERAGEIF('Preço Soja ESALQ'!$C:$C,'Modelo Soja'!$B10,'Preço Soja ESALQ'!W:W),NA()) -> 159.61773 | J10: =IFERROR(AVERAGEIF('Preço Soja ESALQ'!$C:$C,'Modelo Soja'!$B10,'Preço Soja ESALQ'!X:X),NA()) -> 156.3 | K10: =IFERROR(AVERAGEIF('Preço Soja ESALQ'!$C:$C,'Modelo Soja'!$B10,'Preço Soja ESALQ'!Y:Y),NA()) -> 156.48273 | L10: =IFERROR(AVERAGEIF('Preço Soja ESALQ'!$C:$C,'Modelo Soja'!$B10,'Preço Soja ESALQ'!Z:Z),NA()) -> 156.60364 | M10: =IFERROR(AVERAGEIF('Preço Soja ESALQ'!$C:$C,'Modelo Soja'!$B10,'Preço Soja ESALQ'!AA:AA),NA()) -> 152.31864 | N10: =IFERROR(AVERAGEIF('Preço Soja ESALQ'!$C:$C,'Modelo Soja'!$B10,'Preço Soja ESALQ'!AB:AB),NA()) -> 156.47773 | O10: =IFERROR(AVERAGEIF('Preço Soja ESALQ'!$C:$C,'Modelo Soja'!$B10,'Preço Soja ESALQ'!AC:AC),NA()) -> #N/A | P10: =IFERROR(AVERAGEIF('Preço Soja ESALQ'!$C:$C,'Modelo Soja'!$B10,'Preço Soja ESALQ'!AD:AD),NA()) -> #N/A | Q10: =IFERROR(AVERAGEIF('Preço Soja ESALQ'!$C:$C,'Modelo Soja'!$B10,'Preço Soja ESALQ'!BI:BI),NA()) -> 159.12 | R10: =IFERROR(AVERAGEIF('Preço Soja ESALQ'!$C:$C,'Modelo Soja'!$B10,'Preço Soja ESALQ'!BK:BK),NA()) -> #N/A | S10: =IFERROR(AVERAGEIF('Preço Soja ESALQ'!$C:$C,'Modelo Soja'!$B10,'Preço Soja ESALQ'!BL:BL),NA()) -> 152.74045 | T10: =IFERROR(AVERAGEIF('Preço Soja ESALQ'!$C:$C,'Modelo Soja'!$B10,'Preço Soja ESALQ'!BM:BM),NA()) -> #N/A | U10: =IFERROR(AVERAGEIF('Preço Soja ESALQ'!$C:$C,'Modelo Soja'!$B10,'Preço Soja ESALQ'!BN:BN),NA()) -> 152.20864 | AA10: =IFERROR(AVERAGEIF('Preço Soja ESALQ'!$C:$C,'Modelo Soja'!$B10,'Preço Soja ESALQ'!BA:BA),NA()) -> 169.66273 | AB10: =IFERROR(AVERAGEIF('Preço Soja ESALQ'!$C:$C,'Modelo Soja'!$B10,'Preço Soja ESALQ'!BB:BB),NA()) -> 168.52591 | AC10: =IFERROR(AVERAGEIF('Preço Soja ESALQ'!$C:$C,'Modelo Soja'!$B10,'Preço Soja ESALQ'!BC:BC),NA()) -> 166.52773 | AD10: =IFERROR(AVERAGEIF('Preço Soja ESALQ'!$C:$C,'Modelo Soja'!$B10,'Preço Soja ESALQ'!BD:BD),NA()) -> 167.36682 | AE10: =IFERROR(AVERAGEIF('Preço Soja ESALQ'!$C:$C,'Modelo Soja'!$B10,'Preço Soja ESALQ'!BE:BE),NA()) -> 164.86909 | AF10: =IFERROR(AVERAGEIF('Preço Soja ESALQ'!$C:$C,'Modelo Soja'!$B10,'Preço Soja ESALQ'!BF:BF),NA()) -> 171.48136 | AG10: =IFERROR(AVERAGEIF('Preço Soja ESALQ'!$C:$C,'Modelo Soja'!$B10,'Preço Soja ESALQ'!BG:BG),NA()) -> 166.23455 | AH10: =IFERROR(AVERAGEIF('Preço Soja ESALQ'!$C:$C,'Modelo Soja'!$B10,'Preço Soja ESALQ'!AE:AE),NA()) -> 165.81182 | AI10: =IFERROR(AVERAGEIF('Preço Soja ESALQ'!$C:$C,'Modelo Soja'!$B10,'Preço Soja ESALQ'!AF:AF),NA()) -> 162.46105 | AJ10: =+[2]summary!C22 -> 171.05773 | AK10: =+E10+BJ10 -> 167.53059 | AL10: =+AK10+0.5 -> 168.03059 | AN10: =+[3]FSORPRA!H9 -> 310 | AO10: =+[3]FRONPRA!H9 -> 273.75 | AP10: =VLOOKUP(B10,'Frete ESALQ'!$C$6:$AL$132,36,FALSE) -> 80.27 | AQ10: =VLOOKUP(B10,'Frete ESALQ'!$C$6:$AW$132,47,FALSE) -> 67.33 | AR10: =VLOOKUP(B10,'Frete ESALQ'!$C$6:$BH$132,58,FALSE) -> 83.38 | AS10: =VLOOKUP(B10,'Frete ESALQ'!$C$6:$BH$132,32,FALSE) -> 87.23 | AT10: =+AJ10-(AN10*0.06) -> 152.45773 | AU10: =+AJ10-(AO10*0.06) -> 154.63273 | AV10: =+AJ10-AP10*0.06 -> 166.24153 | AW10: =+AJ10-AQ10*0.06 -> 167.01793 | AX10: =+AG10-AR10*0.06 -> 161.23175 | AY10: =+AH10-AS10*0.06 -> 160.57802 | AZ10: =MONTH(BA10) -> 8 | BA10: =+C10 -> 44409 | BB10: =+AB10-I10 -> 8.9081818 | BC10: =+AC10-K10 -> 10.045 | BD10: =+AE10-M10 -> 12.550455 | BE10: =+AF10-D10 -> 21.168182 | BF10: =AH10-J10 -> 9.5118182 | BG10: =+AG10-N10 -> 9.7568182 | BH10: =AVERAGE(BB10:BG10) -> 11.990076 | BI10: 8 | BJ10: =AVERAGEIF($AZ$3:$AZ$64,BI10,$BH$3:$BH$64) -> 9.3674127 | BL10: =+AN10-10 -> 300 | BM10: =+AJ10-(BL10/1000*60) -> 153.05773
B11: =YEAR(C11)&MONTH(C11) -> 20219 | C11: =EDATE(C10,1) -> 44440 | D11: =IFERROR(AVERAGEIF('Preço Soja ESALQ'!$C:$C,'Modelo Soja'!$B11,'Preço Soja ESALQ'!$R:$R),NA()) -> 151.04714 | E11: =IFERROR(AVERAGEIF('Preço Soja ESALQ'!$C:$C,'Modelo Soja'!$B11,'Preço Soja ESALQ'!S:S),NA()) -> 158.66571 | F11: =IFERROR(AVERAGEIF('Preço Soja ESALQ'!$C:$C,'Modelo Soja'!$B11,'Preço Soja ESALQ'!T:T),NA()) -> 159.9881 | G11: =IFERROR(AVERAGEIF('Preço Soja ESALQ'!$C:$C,'Modelo Soja'!$B11,'Preço Soja ESALQ'!U:U),NA()) -> 164.114 | H11: =IFERROR(AVERAGEIF('Preço Soja ESALQ'!$C:$C,'Modelo Soja'!$B11,'Preço Soja ESALQ'!V:V),NA()) -> 155.40952 | I11: =IFERROR(AVERAGEIF('Preço Soja ESALQ'!$C:$C,'Modelo Soja'!$B11,'Preço Soja ESALQ'!W:W),NA()) -> 159.18667 | J11: =IFERROR(AVERAGEIF('Preço Soja ESALQ'!$C:$C,'Modelo Soja'!$B11,'Preço Soja ESALQ'!X:X),NA()) -> 157.50952 | K11: =IFERROR(AVERAGEIF('Preço Soja ESALQ'!$C:$C,'Modelo Soja'!$B11,'Preço Soja ESALQ'!Y:Y),NA()) -> 157.94429 | L11: =IFERROR(AVERAGEIF('Preço Soja ESALQ'!$C:$C,'Modelo Soja'!$B11,'Preço Soja ESALQ'!Z:Z),NA()) -> 157.9819 | M11: =IFERROR(AVERAGEIF('Preço Soja ESALQ'!$C:$C,'Modelo Soja'!$B11,'Preço Soja ESALQ'!AA:AA),NA()) -> 152.52524 | N11: =IFERROR(AVERAGEIF('Preço Soja ESALQ'!$C:$C,'Modelo Soja'!$B11,'Preço Soja ESALQ'!AB:AB),NA()) -> 157.57952 | O11: =IFERROR(AVERAGEIF('Preço Soja ESALQ'!$C:$C,'Modelo Soja'!$B11,'Preço Soja ESALQ'!AC:AC),NA()) -> #N/A | P11: =IFERROR(AVERAGEIF('Preço Soja ESALQ'!$C:$C,'Modelo Soja'!$B11,'Preço Soja ESALQ'!AD:AD),NA()) -> #N/A | Q11: =IFERROR(AVERAGEIF('Preço Soja ESALQ'!$C:$C,'Modelo Soja'!$B11,'Preço Soja ESALQ'!BI:BI),NA()) -> 160.67238 | R11: =IFERROR(AVERAGEIF('Preço Soja ESALQ'!$C:$C,'Modelo Soja'!$B11,'Preço Soja ESALQ'!BK:BK),NA()) -> #N/A | S11: =IFERROR(AVERAGEIF('Preço Soja ESALQ'!$C:$C,'Modelo Soja'!$B11,'Preço Soja ESALQ'!BL:BL),NA()) -> 153.60619 | T11: =IFERROR(AVERAGEIF('Preço Soja ESALQ'!$C:$C,'Modelo Soja'!$B11,'Preço Soja ESALQ'!BM:BM),NA()) -> #N/A | U11: =IFERROR(AVERAGEIF('Preço Soja ESALQ'!$C:$C,'Modelo Soja'!$B11,'Preço Soja ESALQ'!BN:BN),NA()) -> 153.19476 | AA11: =IFERROR(AVERAGEIF('Preço Soja ESALQ'!$C:$C,'Modelo Soja'!$B11,'Preço Soja ESALQ'!BA:BA),NA()) -> 168.1819 | AB11: =IFERROR(AVERAGEIF('Preço Soja ESALQ'!$C:$C,'Modelo Soja'!$B11,'Preço Soja ESALQ'!BB:BB),NA()) -> 169.85952 | AC11: =IFERROR(AVERAGEIF('Preço Soja ESALQ'!$C:$C,'Modelo Soja'!$B11,'Preço Soja ESALQ'!BC:BC),NA()) -> 168.72333 | AD11: =IFERROR(AVERAGEIF('Preço Soja ESALQ'!$C:$C,'Modelo Soja'!$B11,'Preço Soja ESALQ'!BD:BD),NA()) -> 168.46667 | AE11: =IFERROR(AVERAGEIF('Preço Soja ESALQ'!$C:$C,'Modelo Soja'!$B11,'Preço Soja ESALQ'!BE:BE),NA()) -> 166.6619 | AF11: =IFERROR(AVERAGEIF('Preço Soja ESALQ'!$C:$C,'Modelo Soja'!$B11,'Preço Soja ESALQ'!BF:BF),NA()) -> 166.67619 | AG11: =IFERROR(AVERAGEIF('Preço Soja ESALQ'!$C:$C,'Modelo Soja'!$B11,'Preço Soja ESALQ'!BG:BG),NA()) -> 167.57857 | AH11: =IFERROR(AVERAGEIF('Preço Soja ESALQ'!$C:$C,'Modelo Soja'!$B11,'Preço Soja ESALQ'!AE:AE),NA()) -> 167.28905 | AI11: =IFERROR(AVERAGEIF('Preço Soja ESALQ'!$C:$C,'Modelo Soja'!$B11,'Preço Soja ESALQ'!AF:AF),NA()) -> 163.79 | AJ11: =+[2]summary!C23 -> 172.73429 | AK11: =+E11+BJ11 -> 168.74382 | AL11: =+AK11+0.5 -> 169.24382 | AN11: =+[3]FSORPRA!H10 -> 291.25 | AO11: =+[3]FRONPRA!H10 -> 255 | AP11: =VLOOKUP(B11,'Frete ESALQ'!$C$6:$AL$132,36,FALSE) -> 68 | AQ11: =VLOOKUP(B11,'Frete ESALQ'!$C$6:$AW$132,47,FALSE) -> 68 | AR11: =VLOOKUP(B11,'Frete ESALQ'!$C$6:$BH$132,58,FALSE) -> 91.24 | AS11: =VLOOKUP(B11,'Frete ESALQ'!$C$6:$BH$132,32,FALSE) -> 96.6 | AT11: =+AJ11-(AN11*0.06) -> 155.25929 | AU11: =+AJ11-(AO11*0.06) -> 157.43429 | AV11: =+AJ11-AP11*0.06 -> 168.65429 | AW11: =+AJ11-AQ11*0.06 -> 168.65429 | AX11: =+AG11-AR11*0.06 -> 162.10417 | AY11: =+AH11-AS11*0.06 -> 161.49305 | AZ11: =MONTH(BA11) -> 9 | BA11: =+C11 -> 44440 | BB11: =+AB11-I11 -> 10.672857 | BC11: =+AC11-K11 -> 10.779048 | BD11: =+AE11-M11 -> 14.136667 | BE11: =+AF11-D11 -> 15.629048 | BF11: =AH11-J11 -> 9.7795238 | BG11: =+AG11-N11 -> 9.9990476 | BH11: =AVERAGE(BB11:BG11) -> 11.832698 | BI11: 9 | BJ11: =AVERAGEIF($AZ$3:$AZ$64,BI11,$BH$3:$BH$64) -> 10.078101 | BL11: =+AN11-10 -> 281.25 | BM11: =+AJ11-(BL11/1000*60) -> 155.85929
B12: =YEAR(C12)&MONTH(C12) -> 202110 | C12: =EDATE(C11,1) -> 44470 | D12: =IFERROR(AVERAGEIF('Preço Soja ESALQ'!$C:$C,'Modelo Soja'!$B12,'Preço Soja ESALQ'!$R:$R),NA()) -> 153.382 | E12: =IFERROR(AVERAGEIF('Preço Soja ESALQ'!$C:$C,'Modelo Soja'!$B12,'Preço Soja ESALQ'!S:S),NA()) -> 153.918 | F12: =IFERROR(AVERAGEIF('Preço Soja ESALQ'!$C:$C,'Modelo Soja'!$B12,'Preço Soja ESALQ'!T:T),NA()) -> 159.3835 | G12: =IFERROR(AVERAGEIF('Preço Soja ESALQ'!$C:$C,'Modelo Soja'!$B12,'Preço Soja ESALQ'!U:U),NA()) -> #N/A | H12: =IFERROR(AVERAGEIF('Preço Soja ESALQ'!$C:$C,'Modelo Soja'!$B12,'Preço Soja ESALQ'!V:V),NA()) -> 155.5715 | I12: =IFERROR(AVERAGEIF('Preço Soja ESALQ'!$C:$C,'Modelo Soja'!$B12,'Preço Soja ESALQ'!W:W),NA()) -> 160.96 | J12: =IFERROR(AVERAGEIF('Preço Soja ESALQ'!$C:$C,'Modelo Soja'!$B12,'Preço Soja ESALQ'!X:X),NA()) -> 158.6865 | K12: =IFERROR(AVERAGEIF('Preço Soja ESALQ'!$C:$C,'Modelo Soja'!$B12,'Preço Soja ESALQ'!Y:Y),NA()) -> 159.5355 | L12: =IFERROR(AVERAGEIF('Preço Soja ESALQ'!$C:$C,'Modelo Soja'!$B12,'Preço Soja ESALQ'!Z:Z),NA()) -> 159.6085 | M12: =IFERROR(AVERAGEIF('Preço Soja ESALQ'!$C:$C,'Modelo Soja'!$B12,'Preço Soja ESALQ'!AA:AA),NA()) -> 154.395 | N12: =IFERROR(AVERAGEIF('Preço Soja ESALQ'!$C:$C,'Modelo Soja'!$B12,'Preço Soja ESALQ'!AB:AB),NA()) -> 158.939 | O12: =IFERROR(AVERAGEIF('Preço Soja ESALQ'!$C:$C,'Modelo Soja'!$B12,'Preço Soja ESALQ'!AC:AC),NA()) -> #N/A | P12: =IFERROR(AVERAGEIF('Preço Soja ESALQ'!$C:$C,'Modelo Soja'!$B12,'Preço Soja ESALQ'!AD:AD),NA()) -> #N/A | Q12: =IFERROR(AVERAGEIF('Preço Soja ESALQ'!$C:$C,'Modelo Soja'!$B12,'Preço Soja ESALQ'!BI:BI),NA()) -> 160.693 | R12: =IFERROR(AVERAGEIF('Preço Soja ESALQ'!$C:$C,'Modelo Soja'!$B12,'Preço Soja ESALQ'!BK:BK),NA()) -> 154.75571 | S12: =IFERROR(AVERAGEIF('Preço Soja ESALQ'!$C:$C,'Modelo Soja'!$B12,'Preço Soja ESALQ'!BL:BL),NA()) -> 154.794 | T12: =IFERROR(AVERAGEIF('Preço Soja ESALQ'!$C:$C,'Modelo Soja'!$B12,'Preço Soja ESALQ'!BM:BM),NA()) -> #N/A | U12: =IFERROR(AVERAGEIF('Preço Soja ESALQ'!$C:$C,'Modelo Soja'!$B12,'Preço Soja ESALQ'!BN:BN),NA()) -> 154.374 | AA12: =IFERROR(AVERAGEIF('Preço Soja ESALQ'!$C:$C,'Modelo Soja'!$B12,'Preço Soja ESALQ'!BA:BA),NA()) -> 162.7255 | AB12: =IFERROR(AVERAGEIF('Preço Soja ESALQ'!$C:$C,'Modelo Soja'!$B12,'Preço Soja ESALQ'!BB:BB),NA()) -> 169.1885 | AC12: =IFERROR(AVERAGEIF('Preço Soja ESALQ'!$C:$C,'Modelo Soja'!$B12,'Preço Soja ESALQ'!BC:BC),NA()) -> 167.5905 | AD12: =IFERROR(AVERAGEIF('Preço Soja ESALQ'!$C:$C,'Modelo Soja'!$B12,'Preço Soja ESALQ'!BD:BD),NA()) -> 166.6085 | AE12: =IFERROR(AVERAGEIF('Preço Soja ESALQ'!$C:$C,'Modelo Soja'!$B12,'Preço Soja ESALQ'!BE:BE),NA()) -> 164.3485 | AF12: =IFERROR(AVERAGEIF('Preço Soja ESALQ'!$C:$C,'Modelo Soja'!$B12,'Preço Soja ESALQ'!BF:BF),NA()) -> 164.884 | AG12: =IFERROR(AVERAGEIF('Preço Soja ESALQ'!$C:$C,'Modelo Soja'!$B12,'Preço Soja ESALQ'!BG:BG),NA()) -> 168.1475 | AH12: =IFERROR(AVERAGEIF('Preço Soja ESALQ'!$C:$C,'Modelo Soja'!$B12,'Preço Soja ESALQ'!AE:AE),NA()) -> 167.8675 | AI12: =IFERROR(AVERAGEIF('Preço Soja ESALQ'!$C:$C,'Modelo Soja'!$B12,'Preço Soja ESALQ'!AF:AF),NA()) -> 162.3955 | AJ12: =+[2]summary!C24 -> 171.167 | AK12: =+E12+BJ12 -> 163.51307 | AL12: =+AK12+0.5 -> 164.01307 | AN12: =+[3]FSORPRA!H11 -> 313 | AO12: =+[3]FRONPRA!H11 -> 232 | AP12: =VLOOKUP(B12,'Frete ESALQ'!$C$6:$AL$132,36,FALSE) -> 68 | AQ12: =VLOOKUP(B12,'Frete ESALQ'!$C$6:$AW$132,47,FALSE) -> 72 | AR12: =VLOOKUP(B12,'Frete ESALQ'!$C$6:$BH$132,58,FALSE) -> 85.59 | AS12: =VLOOKUP(B12,'Frete ESALQ'!$C$6:$BH$132,32,FALSE) -> 91.5 | AT12: =+AJ12-(AN12*0.06) -> 152.387 | AU12: =+AJ12-(AO12*0.06) -> 157.247 | AV12: =+AJ12-AP12*0.06 -> 167.087 | AW12: =+AJ12-AQ12*0.06 -> 166.847 | AX12: =+AG12-AR12*0.06 -> 163.0121 | AY12: =+AH12-AS12*0.06 -> 162.3775 | AZ12: =MONTH(BA12) -> 10 | BA12: =+C12 -> 44470 | BB12: =+AB12-I12 -> 8.2285 | BC12: =+AC12-K12 -> 8.055 | BD12: =+AE12-M12 -> 9.9535 | BE12: =+AF12-D12 -> 11.502 | BF12: =AH12-J12 -> 9.181 | BG12: =+AG12-N12 -> 9.2085 | BH12: =AVERAGE(BB12:BG12) -> 9.35475 | BI12: 10 | BJ12: =AVERAGEIF($AZ$3:$AZ$64,BI12,$BH$3:$BH$64) -> 9.5950675 | BL12: =+AN12-10 -> 303 | BM12: =+AJ12-(BL12/1000*60) -> 152.987
B13: =YEAR(C13)&MONTH(C13) -> 202111 | C13: =EDATE(C12,1) -> 44501 | D13: =IFERROR(AVERAGEIF('Preço Soja ESALQ'!$C:$C,'Modelo Soja'!$B13,'Preço Soja ESALQ'!$R:$R),NA()) -> 148.866 | E13: =IFERROR(AVERAGEIF('Preço Soja ESALQ'!$C:$C,'Modelo Soja'!$B13,'Preço Soja ESALQ'!S:S),NA()) -> 145.116 | F13: =IFERROR(AVERAGEIF('Preço Soja ESALQ'!$C:$C,'Modelo Soja'!$B13,'Preço Soja ESALQ'!T:T),NA()) -> 154.8485 | G13: =IFERROR(AVERAGEIF('Preço Soja ESALQ'!$C:$C,'Modelo Soja'!$B13,'Preço Soja ESALQ'!U:U),NA()) -> #N/A | H13: =IFERROR(AVERAGEIF('Preço Soja ESALQ'!$C:$C,'Modelo Soja'!$B13,'Preço Soja ESALQ'!V:V),NA()) -> 151.6055 | I13: =IFERROR(AVERAGEIF('Preço Soja ESALQ'!$C:$C,'Modelo Soja'!$B13,'Preço Soja ESALQ'!W:W),NA()) -> 155.6525 | J13: =IFERROR(AVERAGEIF('Preço Soja ESALQ'!$C:$C,'Modelo Soja'!$B13,'Preço Soja ESALQ'!X:X),NA()) -> 157.347 | K13: =IFERROR(AVERAGEIF('Preço Soja ESALQ'!$C:$C,'Modelo Soja'!$B13,'Preço Soja ESALQ'!Y:Y),NA()) -> 154.1505 | L13: =IFERROR(AVERAGEIF('Preço Soja ESALQ'!$C:$C,'Modelo Soja'!$B13,'Preço Soja ESALQ'!Z:Z),NA()) -> 154.2005 | M13: =IFERROR(AVERAGEIF('Preço Soja ESALQ'!$C:$C,'Modelo Soja'!$B13,'Preço Soja ESALQ'!AA:AA),NA()) -> 151.16 | N13: =IFERROR(AVERAGEIF('Preço Soja ESALQ'!$C:$C,'Modelo Soja'!$B13,'Preço Soja ESALQ'!AB:AB),NA()) -> 156.906 | O13: =IFERROR(AVERAGEIF('Preço Soja ESALQ'!$C:$C,'Modelo Soja'!$B13,'Preço Soja ESALQ'!AC:AC),NA()) -> #N/A | P13: =IFERROR(AVERAGEIF('Preço Soja ESALQ'!$C:$C,'Modelo Soja'!$B13,'Preço Soja ESALQ'!AD:AD),NA()) -> #N/A | Q13: =IFERROR(AVERAGEIF('Preço Soja ESALQ'!$C:$C,'Modelo Soja'!$B13,'Preço Soja ESALQ'!BI:BI),NA()) -> 157.927 | R13: =IFERROR(AVERAGEIF('Preço Soja ESALQ'!$C:$C,'Modelo Soja'!$B13,'Preço Soja ESALQ'!BK:BK),NA()) -> 153.39 | S13: =IFERROR(AVERAGEIF('Preço Soja ESALQ'!$C:$C,'Modelo Soja'!$B13,'Preço Soja ESALQ'!BL:BL),NA()) -> 149.823 | T13: =IFERROR(AVERAGEIF('Preço Soja ESALQ'!$C:$C,'Modelo Soja'!$B13,'Preço Soja ESALQ'!BM:BM),NA()) -> #N/A | U13: =IFERROR(AVERAGEIF('Preço Soja ESALQ'!$C:$C,'Modelo Soja'!$B13,'Preço Soja ESALQ'!BN:BN),NA()) -> 149.691 | AA13: =IFERROR(AVERAGEIF('Preço Soja ESALQ'!$C:$C,'Modelo Soja'!$B13,'Preço Soja ESALQ'!BA:BA),NA()) -> 153.7625 | AB13: =IFERROR(AVERAGEIF('Preço Soja ESALQ'!$C:$C,'Modelo Soja'!$B13,'Preço Soja ESALQ'!BB:BB),NA()) -> 162.591 | AC13: =IFERROR(AVERAGEIF('Preço Soja ESALQ'!$C:$C,'Modelo Soja'!$B13,'Preço Soja ESALQ'!BC:BC),NA()) -> 161.8695 | AD13: =IFERROR(AVERAGEIF('Preço Soja ESALQ'!$C:$C,'Modelo Soja'!$B13,'Preço Soja ESALQ'!BD:BD),NA()) -> 160.6065 | AE13: =IFERROR(AVERAGEIF('Preço Soja ESALQ'!$C:$C,'Modelo Soja'!$B13,'Preço Soja ESALQ'!BE:BE),NA()) -> 157.1925 | AF13: =IFERROR(AVERAGEIF('Preço Soja ESALQ'!$C:$C,'Modelo Soja'!$B13,'Preço Soja ESALQ'!BF:BF),NA()) -> 157.4295 | AG13: =IFERROR(AVERAGEIF('Preço Soja ESALQ'!$C:$C,'Modelo Soja'!$B13,'Preço Soja ESALQ'!BG:BG),NA()) -> 164.7465 | AH13: =IFERROR(AVERAGEIF('Preço Soja ESALQ'!$C:$C,'Modelo Soja'!$B13,'Preço Soja ESALQ'!AE:AE),NA()) -> 164.216 | AI13: =IFERROR(AVERAGEIF('Preço Soja ESALQ'!$C:$C,'Modelo Soja'!$B13,'Preço Soja ESALQ'!AF:AF),NA()) -> 158.295 | AJ13: =+[2]summary!C25 -> 165.7935 | AK13: =+E13+BJ13 -> 154.27313 | AL13: =+AK13+0.5 -> 154.77313 | AN13: =+[3]FSORPRA!H12 -> 318.75 | AO13: =+[3]FRONPRA!H12 -> 243.75 | AP13: =VLOOKUP(B13,'Frete ESALQ'!$C$6:$AL$132,36,FALSE) -> 68 | AQ13: =VLOOKUP(B13,'Frete ESALQ'!$C$6:$AW$132,47,FALSE) -> 70 | AR13: =VLOOKUP(B13,'Frete ESALQ'!$C$6:$BH$132,58,FALSE) -> 76.08 | AS13: =VLOOKUP(B13,'Frete ESALQ'!$C$6:$BH$132,32,FALSE) -> 73.5 | AT13: =+AJ13-(AN13*0.06) -> 146.6685 | AU13: =+AJ13-(AO13*0.06) -> 151.1685 | AV13: =+AJ13-AP13*0.06 -> 161.7135 | AW13: =+AJ13-AQ13*0.06 -> 161.5935 | AX13: =+AG13-AR13*0.06 -> 160.1817 | AY13: =+AH13-AS13*0.06 -> 159.806 | AZ13: =MONTH(BA13) -> 11 | BA13: =+C13 -> 44501 | BB13: =+AB13-I13 -> 6.9385 | BC13: =+AC13-K13 -> 7.719 | BD13: =+AE13-M13 -> 6.0325 | BE13: =+AF13-D13 -> 8.5635 | BF13: =AH13-J13 -> 6.869 | BG13: =+AG13-N13 -> 7.8405 | BH13: =AVERAGE(BB13:BG13) -> 7.3271667 | BI13: 11 | BJ13: =AVERAGEIF($AZ$3:$AZ$64,BI13,$BH$3:$BH$64) -> 9.1571329 | BL13: =+AN13-10 -> 308.75 | BM13: =+AJ13-(BL13/1000*60) -> 147.2685
B14: =YEAR(C14)&MONTH(C14) -> 202112 | C14: =EDATE(C13,1) -> 44531 | D14: =IFERROR(AVERAGEIF('Preço Soja ESALQ'!$C:$C,'Modelo Soja'!$B14,'Preço Soja ESALQ'!$R:$R),NA()) -> 147.99762 | E14: =IFERROR(AVERAGEIF('Preço Soja ESALQ'!$C:$C,'Modelo Soja'!$B14,'Preço Soja ESALQ'!S:S),NA()) -> 143.005 | F14: =IFERROR(AVERAGEIF('Preço Soja ESALQ'!$C:$C,'Modelo Soja'!$B14,'Preço Soja ESALQ'!T:T),NA()) -> 158.50524 | G14: =IFERROR(AVERAGEIF('Preço Soja ESALQ'!$C:$C,'Modelo Soja'!$B14,'Preço Soja ESALQ'!U:U),NA()) -> #N/A | H14: =IFERROR(AVERAGEIF('Preço Soja ESALQ'!$C:$C,'Modelo Soja'!$B14,'Preço Soja ESALQ'!V:V),NA()) -> 152.33381 | I14: =IFERROR(AVERAGEIF('Preço Soja ESALQ'!$C:$C,'Modelo Soja'!$B14,'Preço Soja ESALQ'!W:W),NA()) -> 158.88095 | J14: =IFERROR(AVERAGEIF('Preço Soja ESALQ'!$C:$C,'Modelo Soja'!$B14,'Preço Soja ESALQ'!X:X),NA()) -> 161.57762 | K14: =IFERROR(AVERAGEIF('Preço Soja ESALQ'!$C:$C,'Modelo Soja'!$B14,'Preço Soja ESALQ'!Y:Y),NA()) -> 158.45619 | L14: =IFERROR(AVERAGEIF('Preço Soja ESALQ'!$C:$C,'Modelo Soja'!$B14,'Preço Soja ESALQ'!Z:Z),NA()) -> 158.54714 | M14: =IFERROR(AVERAGEIF('Preço Soja ESALQ'!$C:$C,'Modelo Soja'!$B14,'Preço Soja ESALQ'!AA:AA),NA()) -> 155.00857 | N14: =IFERROR(AVERAGEIF('Preço Soja ESALQ'!$C:$C,'Modelo Soja'!$B14,'Preço Soja ESALQ'!AB:AB),NA()) -> 161.47524 | O14: =IFERROR(AVERAGEIF('Preço Soja ESALQ'!$C:$C,'Modelo Soja'!$B14,'Preço Soja ESALQ'!AC:AC),NA()) -> 159.79 | P14: =IFERROR(AVERAGEIF('Preço Soja ESALQ'!$C:$C,'Modelo Soja'!$B14,'Preço Soja ESALQ'!AD:AD),NA()) -> #N/A | Q14: =IFERROR(AVERAGEIF('Preço Soja ESALQ'!$C:$C,'Modelo Soja'!$B14,'Preço Soja ESALQ'!BI:BI),NA()) -> 160.89571 | R14: =IFERROR(AVERAGEIF('Preço Soja ESALQ'!$C:$C,'Modelo Soja'!$B14,'Preço Soja ESALQ'!BK:BK),NA()) -> 149.5125 | S14: =IFERROR(AVERAGEIF('Preço Soja ESALQ'!$C:$C,'Modelo Soja'!$B14,'Preço Soja ESALQ'!BL:BL),NA()) -> 154.3281 | T14: =IFERROR(AVERAGEIF('Preço Soja ESALQ'!$C:$C,'Modelo Soja'!$B14,'Preço Soja ESALQ'!BM:BM),NA()) -> #N/A | U14: =IFERROR(AVERAGEIF('Preço Soja ESALQ'!$C:$C,'Modelo Soja'!$B14,'Preço Soja ESALQ'!BN:BN),NA()) -> 154.23524 | AA14: =IFERROR(AVERAGEIF('Preço Soja ESALQ'!$C:$C,'Modelo Soja'!$B14,'Preço Soja ESALQ'!BA:BA),NA()) -> 153.44524 | AB14: =IFERROR(AVERAGEIF('Preço Soja ESALQ'!$C:$C,'Modelo Soja'!$B14,'Preço Soja ESALQ'!BB:BB),NA()) -> 166.92429 | AC14: =IFERROR(AVERAGEIF('Preço Soja ESALQ'!$C:$C,'Modelo Soja'!$B14,'Preço Soja ESALQ'!BC:BC),NA()) -> 165.89095 | AD14: =IFERROR(AVERAGEIF('Preço Soja ESALQ'!$C:$C,'Modelo Soja'!$B14,'Preço Soja ESALQ'!BD:BD),NA()) -> 165.33524 | AE14: =IFERROR(AVERAGEIF('Preço Soja ESALQ'!$C:$C,'Modelo Soja'!$B14,'Preço Soja ESALQ'!BE:BE),NA()) -> 160.60095 | AF14: =IFERROR(AVERAGEIF('Preço Soja ESALQ'!$C:$C,'Modelo Soja'!$B14,'Preço Soja ESALQ'!BF:BF),NA()) -> 155.61421 | AG14: =IFERROR(AVERAGEIF('Preço Soja ESALQ'!$C:$C,'Modelo Soja'!$B14,'Preço Soja ESALQ'!BG:BG),NA()) -> 168.95952 | AH14: =IFERROR(AVERAGEIF('Preço Soja ESALQ'!$C:$C,'Modelo Soja'!$B14,'Preço Soja ESALQ'!AE:AE),NA()) -> 167.73524 | AI14: =IFERROR(AVERAGEIF('Preço Soja ESALQ'!$C:$C,'Modelo Soja'!$B14,'Preço Soja ESALQ'!AF:AF),NA()) -> 161.51 | AJ14: =+[2]summary!C26 -> 170.2519 | AK14: =+E14+BJ14 -> 152.74386 | AL14: =+AK14+0.5 -> 153.24386 | AN14: =+[3]FSORPRA!H13 -> 352 | AO14: =+[3]FRONPRA!H13 -> 266 | AP14: =VLOOKUP(B14,'Frete ESALQ'!$C$6:$AL$132,36,FALSE) -> 76.2 | AQ14: =VLOOKUP(B14,'Frete ESALQ'!$C$6:$AW$132,47,FALSE) -> 67.67 | AR14: =VLOOKUP(B14,'Frete ESALQ'!$C$6:$BH$132,58,FALSE) -> 92.96 | AS14: =VLOOKUP(B14,'Frete ESALQ'!$C$6:$BH$132,32,FALSE) -> 91.67 | AT14: =+AJ14-(AN14*0.06) -> 149.1319 | AU14: =+AJ14-(AO14*0.06) -> 154.2919 | AV14: =+AJ14-AP14*0.06 -> 165.6799 | AW14: =+AJ14-AQ14*0.06 -> 166.1917 | AX14: =+AG14-AR14*0.06 -> 163.38192 | AY14: =+AH14-AS14*0.06 -> 162.23504 | AZ14: =MONTH(BA14) -> 12 | BA14: =+C14 -> 44531 | BB14: =+AB14-I14 -> 8.0433333 | BC14: =+AC14-K14 -> 7.4347619 | BD14: =+AE14-M14 -> 5.592381 | BE14: =+AF14-D14 -> 7.6165915 | BF14: =AH14-J14 -> 6.157619 | BG14: =+AG14-N14 -> 7.4842857 | BH14: =AVERAGE(BB14:BG14) -> 7.0548287 | BI14: 12 | BJ14: =AVERAGEIF($AZ$3:$AZ$64,BI14,$BH$3:$BH$64) -> 9.7388588 | BL14: =+AN14-10 -> 342 | BM14: =+AJ14-(BL14/1000*60) -> 149.7319
B15: =YEAR(C15)&MONTH(C15) -> 20221 | C15: =EDATE(C14,1) -> 44562 | D15: =IFERROR(AVERAGEIF('Preço Soja ESALQ'!$C:$C,'Modelo Soja'!$B15,'Preço Soja ESALQ'!$R:$R),NA()) -> 161.93476 | E15: =IFERROR(AVERAGEIF('Preço Soja ESALQ'!$C:$C,'Modelo Soja'!$B15,'Preço Soja ESALQ'!S:S),NA()) -> 155.61238 | F15: =IFERROR(AVERAGEIF('Preço Soja ESALQ'!$C:$C,'Modelo Soja'!$B15,'Preço Soja ESALQ'!T:T),NA()) -> 167.26714 | G15: =IFERROR(AVERAGEIF('Preço Soja ESALQ'!$C:$C,'Modelo Soja'!$B15,'Preço Soja ESALQ'!U:U),NA()) -> #N/A | H15: =IFERROR(AVERAGEIF('Preço Soja ESALQ'!$C:$C,'Modelo Soja'!$B15,'Preço Soja ESALQ'!V:V),NA()) -> 160.92714 | I15: =IFERROR(AVERAGEIF('Preço Soja ESALQ'!$C:$C,'Modelo Soja'!$B15,'Preço Soja ESALQ'!W:W),NA()) -> 167.65429 | J15: =IFERROR(AVERAGEIF('Preço Soja ESALQ'!$C:$C,'Modelo Soja'!$B15,'Preço Soja ESALQ'!X:X),NA()) -> 175.10476 | K15: =IFERROR(AVERAGEIF('Preço Soja ESALQ'!$C:$C,'Modelo Soja'!$B15,'Preço Soja ESALQ'!Y:Y),NA()) -> 166.45476 | L15: =IFERROR(AVERAGEIF('Preço Soja ESALQ'!$C:$C,'Modelo Soja'!$B15,'Preço Soja ESALQ'!Z:Z),NA()) -> 166.59333 | M15: =IFERROR(AVERAGEIF('Preço Soja ESALQ'!$C:$C,'Modelo Soja'!$B15,'Preço Soja ESALQ'!AA:AA),NA()) -> 165.09857 | N15: =IFERROR(AVERAGEIF('Preço Soja ESALQ'!$C:$C,'Modelo Soja'!$B15,'Preço Soja ESALQ'!AB:AB),NA()) -> 175.07048 | O15: =IFERROR(AVERAGEIF('Preço Soja ESALQ'!$C:$C,'Modelo Soja'!$B15,'Preço Soja ESALQ'!AC:AC),NA()) -> 162.02412 | P15: =IFERROR(AVERAGEIF('Preço Soja ESALQ'!$C:$C,'Modelo Soja'!$B15,'Preço Soja ESALQ'!AD:AD),NA()) -> #N/A | Q15: =IFERROR(AVERAGEIF('Preço Soja ESALQ'!$C:$C,'Modelo Soja'!$B15,'Preço Soja ESALQ'!BI:BI),NA()) -> 168.58 | R15: =IFERROR(AVERAGEIF('Preço Soja ESALQ'!$C:$C,'Modelo Soja'!$B15,'Preço Soja ESALQ'!BK:BK),NA()) -> #N/A | S15: =IFERROR(AVERAGEIF('Preço Soja ESALQ'!$C:$C,'Modelo Soja'!$B15,'Preço Soja ESALQ'!BL:BL),NA()) -> 161.627 | T15: =IFERROR(AVERAGEIF('Preço Soja ESALQ'!$C:$C,'Modelo Soja'!$B15,'Preço Soja ESALQ'!BM:BM),NA()) -> #N/A | U15: =IFERROR(AVERAGEIF('Preço Soja ESALQ'!$C:$C,'Modelo Soja'!$B15,'Preço Soja ESALQ'!BN:BN),NA()) -> 161.32762 | AA15: =IFERROR(AVERAGEIF('Preço Soja ESALQ'!$C:$C,'Modelo Soja'!$B15,'Preço Soja ESALQ'!BA:BA),NA()) -> 166.47722 | AB15: =IFERROR(AVERAGEIF('Preço Soja ESALQ'!$C:$C,'Modelo Soja'!$B15,'Preço Soja ESALQ'!BB:BB),NA()) -> 177.30905 | AC15: =IFERROR(AVERAGEIF('Preço Soja ESALQ'!$C:$C,'Modelo Soja'!$B15,'Preço Soja ESALQ'!BC:BC),NA()) -> 175.35619 | AD15: =IFERROR(AVERAGEIF('Preço Soja ESALQ'!$C:$C,'Modelo Soja'!$B15,'Preço Soja ESALQ'!BD:BD),NA()) -> 174.68381 | AE15: =IFERROR(AVERAGEIF('Preço Soja ESALQ'!$C:$C,'Modelo Soja'!$B15,'Preço Soja ESALQ'!BE:BE),NA()) -> 169.8681 | AF15: =IFERROR(AVERAGEIF('Preço Soja ESALQ'!$C:$C,'Modelo Soja'!$B15,'Preço Soja ESALQ'!BF:BF),NA()) -> 168.42333 | AG15: =IFERROR(AVERAGEIF('Preço Soja ESALQ'!$C:$C,'Modelo Soja'!$B15,'Preço Soja ESALQ'!BG:BG),NA()) -> 184.06238 | AH15: =IFERROR(AVERAGEIF('Preço Soja ESALQ'!$C:$C,'Modelo Soja'!$B15,'Preço Soja ESALQ'!AE:AE),NA()) -> 183.01048 | AI15: =IFERROR(AVERAGEIF('Preço Soja ESALQ'!$C:$C,'Modelo Soja'!$B15,'Preço Soja ESALQ'!AF:AF),NA()) -> 169.78619 | AJ15: =+[2]summary!C27 -> 179.66524 | AK15: =+E15+BJ15 -> 164.10516 | AL15: =+AK15+0.5 -> 164.60516 | AN15: =+[3]FSORPRA!H14 -> 375.625 | AO15: =+[3]FRONPRA!H14 -> 285 | AP15: =VLOOKUP(B15,'Frete ESALQ'!$C$6:$AL$132,36,FALSE) -> 74.85 | AQ15: =VLOOKUP(B15,'Frete ESALQ'!$C$6:$AW$132,47,FALSE) -> 71.75 | AR15: =VLOOKUP(B15,'Frete ESALQ'!$C$6:$BH$132,58,FALSE) -> 121.72 | AS15: =VLOOKUP(B15,'Frete ESALQ'!$C$6:$BH$132,32,FALSE) -> 127.6 | AT15: =+AJ15-(AN15*0.06) -> 157.12774 | AU15: =+AJ15-(AO15*0.06) -> 162.56524 | AV15: =+AJ15-AP15*0.06 -> 175.17424 | AW15: =+AJ15-AQ15*0.06 -> 175.36024 | AX15: =+AG15-AR15*0.06 -> 176.75918 | AY15: =+AH15-AS15*0.06 -> 175.35448 | AZ15: =MONTH(BA15) -> 1 | BA15: =+C15 -> 44562 | BB15: =+AB15-I15 -> 9.6547619 | BC15: =+AC15-K15 -> 8.9014286 | BD15: =+AE15-M15 -> 4.7695238 | BE15: =+AF15-D15 -> 6.4885714 | BF15: =AH15-J15 -> 7.9057143 | BG15: =+AG15-N15 -> 8.9919048 | BH15: =AVERAGE(BB15:BG15) -> 7.7853175 | BJ15: =+BJ3 -> 8.4927779 | BL15: =+AN15-10 -> 365.625 | BM15: =+AJ15-(BL15/1000*60) -> 157.72774
B16: =YEAR(C16)&MONTH(C16) -> 20222 | C16: =EDATE(C15,1) -> 44593 | D16: =IFERROR(AVERAGEIF('Preço Soja ESALQ'!$C:$C,'Modelo Soja'!$B16,'Preço Soja ESALQ'!$R:$R),NA()) -> 178.27263 | E16: =IFERROR(AVERAGEIF('Preço Soja ESALQ'!$C:$C,'Modelo Soja'!$B16,'Preço Soja ESALQ'!S:S),NA()) -> 169.05632 | F16: =IFERROR(AVERAGEIF('Preço Soja ESALQ'!$C:$C,'Modelo Soja'!$B16,'Preço Soja ESALQ'!T:T),NA()) -> 184.49 | G16: =IFERROR(AVERAGEIF('Preço Soja ESALQ'!$C:$C,'Modelo Soja'!$B16,'Preço Soja ESALQ'!U:U),NA()) -> 179.76 | H16: =IFERROR(AVERAGEIF('Preço Soja ESALQ'!$C:$C,'Modelo Soja'!$B16,'Preço Soja ESALQ'!V:V),NA()) -> 177.49579 | I16: =IFERROR(AVERAGEIF('Preço Soja ESALQ'!$C:$C,'Modelo Soja'!$B16,'Preço Soja ESALQ'!W:W),NA()) -> 185.69316 | J16: =IFERROR(AVERAGEIF('Preço Soja ESALQ'!$C:$C,'Modelo Soja'!$B16,'Preço Soja ESALQ'!X:X),NA()) -> 192.15316 | K16: =IFERROR(AVERAGEIF('Preço Soja ESALQ'!$C:$C,'Modelo Soja'!$B16,'Preço Soja ESALQ'!Y:Y),NA()) -> 186.10421 | L16: =IFERROR(AVERAGEIF('Preço Soja ESALQ'!$C:$C,'Modelo Soja'!$B16,'Preço Soja ESALQ'!Z:Z),NA()) -> 186.49789 | M16: =IFERROR(AVERAGEIF('Preço Soja ESALQ'!$C:$C,'Modelo Soja'!$B16,'Preço Soja ESALQ'!AA:AA),NA()) -> 180.49211 | N16: =IFERROR(AVERAGEIF('Preço Soja ESALQ'!$C:$C,'Modelo Soja'!$B16,'Preço Soja ESALQ'!AB:AB),NA()) -> 191.77474 | O16: =IFERROR(AVERAGEIF('Preço Soja ESALQ'!$C:$C,'Modelo Soja'!$B16,'Preço Soja ESALQ'!AC:AC),NA()) -> 173.17308 | P16: =IFERROR(AVERAGEIF('Preço Soja ESALQ'!$C:$C,'Modelo Soja'!$B16,'Preço Soja ESALQ'!AD:AD),NA()) -> #N/A | Q16: =IFERROR(AVERAGEIF('Preço Soja ESALQ'!$C:$C,'Modelo Soja'!$B16,'Preço Soja ESALQ'!BI:BI),NA()) -> 184.69895 | R16: =IFERROR(AVERAGEIF('Preço Soja ESALQ'!$C:$C,'Modelo Soja'!$B16,'Preço Soja ESALQ'!BK:BK),NA()) -> 183.80625 | S16: =IFERROR(AVERAGEIF('Preço Soja ESALQ'!$C:$C,'Modelo Soja'!$B16,'Preço Soja ESALQ'!BL:BL),NA()) -> 180.26368 | T16: =IFERROR(AVERAGEIF('Preço Soja ESALQ'!$C:$C,'Modelo Soja'!$B16,'Preço Soja ESALQ'!BM:BM),NA()) -> #N/A | U16: =IFERROR(AVERAGEIF('Preço Soja ESALQ'!$C:$C,'Modelo Soja'!$B16,'Preço Soja ESALQ'!BN:BN),NA()) -> 179.36368 | AA16: =IFERROR(AVERAGEIF('Preço Soja ESALQ'!$C:$C,'Modelo Soja'!$B16,'Preço Soja ESALQ'!BA:BA),NA()) -> 181.20105 | AB16: =IFERROR(AVERAGEIF('Preço Soja ESALQ'!$C:$C,'Modelo Soja'!$B16,'Preço Soja ESALQ'!BB:BB),NA()) -> 192.25684 | AC16: =IFERROR(AVERAGEIF('Preço Soja ESALQ'!$C:$C,'Modelo Soja'!$B16,'Preço Soja ESALQ'!BC:BC),NA()) -> 192.11421 | AD16: =IFERROR(AVERAGEIF('Preço Soja ESALQ'!$C:$C,'Modelo Soja'!$B16,'Preço Soja ESALQ'!BD:BD),NA()) -> 189.49895 | AE16: =IFERROR(AVERAGEIF('Preço Soja ESALQ'!$C:$C,'Modelo Soja'!$B16,'Preço Soja ESALQ'!BE:BE),NA()) -> 186.18368 | AF16: =IFERROR(AVERAGEIF('Preço Soja ESALQ'!$C:$C,'Modelo Soja'!$B16,'Preço Soja ESALQ'!BF:BF),NA()) -> 181.84158 | AG16: =IFERROR(AVERAGEIF('Preço Soja ESALQ'!$C:$C,'Modelo Soja'!$B16,'Preço Soja ESALQ'!BG:BG),NA()) -> 201.24053 | AH16: =IFERROR(AVERAGEIF('Preço Soja ESALQ'!$C:$C,'Modelo Soja'!$B16,'Preço Soja ESALQ'!AE:AE),NA()) -> 200.36 | AI16: =IFERROR(AVERAGEIF('Preço Soja ESALQ'!$C:$C,'Modelo Soja'!$B16,'Preço Soja ESALQ'!AF:AF),NA()) -> 185.99053 | AJ16: =+[2]summary!C28 -> 195.02 | AK16: =+E16+BJ16 -> 174.66631 | AL16: =+AK16+0.5 -> 175.16631 | AN16: =+[3]FSORPRA!H15 -> 396.25 | AO16: =+[3]FRONPRA!H15 -> 293.75 | AP16: =VLOOKUP(B16,'Frete ESALQ'!$C$6:$AL$132,36,FALSE) -> 99.95 | AQ16: =VLOOKUP(B16,'Frete ESALQ'!$C$6:$AW$132,47,FALSE) -> 70 | AR16: =VLOOKUP(B16,'Frete ESALQ'!$C$6:$BH$132,58,FALSE) -> 92.53 | AS16: =VLOOKUP(B16,'Frete ESALQ'!$C$6:$BH$132,32,FALSE) -> 102.79 | AT16: =+AJ16-(AN16*0.06) -> 171.245 | AU16: =+AJ16-(AO16*0.06) -> 177.395 | AV16: =+AJ16-AP16*0.06 -> 189.023 | AW16: =+AJ16-AQ16*0.06 -> 190.82 | AX16: =+AG16-AR16*0.06 -> 195.68873 | AY16: =+AH16-AS16*0.06 -> 194.1926 | AZ16: =MONTH(BA16) -> 2 | BA16: =+C16 -> 44593 | BB16: =+AB16-I16 -> 6.5636842 | BC16: =+AC16-K16 -> 6.01 | BD16: =+AE16-M16 -> 5.6915789 | BE16: =+AF16-D16 -> 3.5689474 | BF16: =AH16-J16 -> 8.2068421 | BG16: =+AG16-N16 -> 9.4657895 | BH16: =AVERAGE(BB16:BG16) -> 6.5844737 | BJ16: =+BJ4 -> 5.6099991 | BL16: =+AN16-10 -> 386.25 | BM16: =+AJ16-(BL16/1000*60) -> 171.845
B17: =YEAR(C17)&MONTH(C17) -> 20223 | C17: =EDATE(C16,1) -> 44621 | D17: =IFERROR(AVERAGEIF('Preço Soja ESALQ'!$C:$C,'Modelo Soja'!$B17,'Preço Soja ESALQ'!$R:$R),NA()) -> 181.88091 | E17: =IFERROR(AVERAGEIF('Preço Soja ESALQ'!$C:$C,'Modelo Soja'!$B17,'Preço Soja ESALQ'!S:S),NA()) -> 171.88773 | F17: =IFERROR(AVERAGEIF('Preço Soja ESALQ'!$C:$C,'Modelo Soja'!$B17,'Preço Soja ESALQ'!T:T),NA()) -> 189.63455 | G17: =IFERROR(AVERAGEIF('Preço Soja ESALQ'!$C:$C,'Modelo Soja'!$B17,'Preço Soja ESALQ'!U:U),NA()) -> #N/A | H17: =IFERROR(AVERAGEIF('Preço Soja ESALQ'!$C:$C,'Modelo Soja'!$B17,'Preço Soja ESALQ'!V:V),NA()) -> 180.18682 | I17: =IFERROR(AVERAGEIF('Preço Soja ESALQ'!$C:$C,'Modelo Soja'!$B17,'Preço Soja ESALQ'!W:W),NA()) -> 193.20682 | J17: =IFERROR(AVERAGEIF('Preço Soja ESALQ'!$C:$C,'Modelo Soja'!$B17,'Preço Soja ESALQ'!X:X),NA()) -> 197.81136 | K17: =IFERROR(AVERAGEIF('Preço Soja ESALQ'!$C:$C,'Modelo Soja'!$B17,'Preço Soja ESALQ'!Y:Y),NA()) -> 191.34545 | L17: =IFERROR(AVERAGEIF('Preço Soja ESALQ'!$C:$C,'Modelo Soja'!$B17,'Preço Soja ESALQ'!Z:Z),NA()) -> 192.12136 | M17: =IFERROR(AVERAGEIF('Preço Soja ESALQ'!$C:$C,'Modelo Soja'!$B17,'Preço Soja ESALQ'!AA:AA),NA()) -> 184.23455 | N17: =IFERROR(AVERAGEIF('Preço Soja ESALQ'!$C:$C,'Modelo Soja'!$B17,'Preço Soja ESALQ'!AB:AB),NA()) -> 197.51 | O17: =IFERROR(AVERAGEIF('Preço Soja ESALQ'!$C:$C,'Modelo Soja'!$B17,'Preço Soja ESALQ'!AC:AC),NA()) -> 180.668 | P17: =IFERROR(AVERAGEIF('Preço Soja ESALQ'!$C:$C,'Modelo Soja'!$B17,'Preço Soja ESALQ'!AD:AD),NA()) -> #N/A | Q17: =IFERROR(AVERAGEIF('Preço Soja ESALQ'!$C:$C,'Modelo Soja'!$B17,'Preço Soja ESALQ'!BI:BI),NA()) -> 194.41591 | R17: =IFERROR(AVERAGEIF('Preço Soja ESALQ'!$C:$C,'Modelo Soja'!$B17,'Preço Soja ESALQ'!BK:BK),NA()) -> 186.76778 | S17: =IFERROR(AVERAGEIF('Preço Soja ESALQ'!$C:$C,'Modelo Soja'!$B17,'Preço Soja ESALQ'!BL:BL),NA()) -> 185.88591 | T17: =IFERROR(AVERAGEIF('Preço Soja ESALQ'!$C:$C,'Modelo Soja'!$B17,'Preço Soja ESALQ'!BM:BM),NA()) -> #N/A | U17: =IFERROR(AVERAGEIF('Preço Soja ESALQ'!$C:$C,'Modelo Soja'!$B17,'Preço Soja ESALQ'!BN:BN),NA()) -> 185.10591 | AA17: =IFERROR(AVERAGEIF('Preço Soja ESALQ'!$C:$C,'Modelo Soja'!$B17,'Preço Soja ESALQ'!BA:BA),NA()) -> 183.58409 | AB17: =IFERROR(AVERAGEIF('Preço Soja ESALQ'!$C:$C,'Modelo Soja'!$B17,'Preço Soja ESALQ'!BB:BB),NA()) -> 196.94 | AC17: =IFERROR(AVERAGEIF('Preço Soja ESALQ'!$C:$C,'Modelo Soja'!$B17,'Preço Soja ESALQ'!BC:BC),NA()) -> 195.18773 | AD17: =IFERROR(AVERAGEIF('Preço Soja ESALQ'!$C:$C,'Modelo Soja'!$B17,'Preço Soja ESALQ'!BD:BD),NA()) -> 193.66773 | AE17: =IFERROR(AVERAGEIF('Preço Soja ESALQ'!$C:$C,'Modelo Soja'!$B17,'Preço Soja ESALQ'!BE:BE),NA()) -> 188.65182 | AF17: =IFERROR(AVERAGEIF('Preço Soja ESALQ'!$C:$C,'Modelo Soja'!$B17,'Preço Soja ESALQ'!BF:BF),NA()) -> 184.48182 | AG17: =IFERROR(AVERAGEIF('Preço Soja ESALQ'!$C:$C,'Modelo Soja'!$B17,'Preço Soja ESALQ'!BG:BG),NA()) -> 203.21364 | AH17: =IFERROR(AVERAGEIF('Preço Soja ESALQ'!$C:$C,'Modelo Soja'!$B17,'Preço Soja ESALQ'!AE:AE),NA()) -> 202.68409 | AI17: =IFERROR(AVERAGEIF('Preço Soja ESALQ'!$C:$C,'Modelo Soja'!$B17,'Preço Soja ESALQ'!AF:AF),NA()) -> 190.23909 | AJ17: =+[2]summary!C29 -> 199.60227 | AK17: =+E17+BJ17 -> 176.62106 | AL17: =+AK17+0.5 -> 177.12106 | AN17: =+[3]FSORPRA!H16 -> 420.625 | AO17: =+[3]FRONPRA!H16 -> 320 | AP17: =VLOOKUP(B17,'Frete ESALQ'!$C$6:$AL$132,36,FALSE) -> 146.59 | AQ17: =VLOOKUP(B17,'Frete ESALQ'!$C$6:$AW$132,47,FALSE) -> 118.4 | AR17: =VLOOKUP(B17,'Frete ESALQ'!$C$6:$BH$132,58,FALSE) -> 102.63 | AS17: =VLOOKUP(B17,'Frete ESALQ'!$C$6:$BH$132,32,FALSE) -> 110.96 | AT17: =+AJ17-(AN17*0.06) -> 174.36477 | AU17: =+AJ17-(AO17*0.06) -> 180.40227 | AV17: =+AJ17-AP17*0.06 -> 190.80687 | AW17: =+AJ17-AQ17*0.06 -> 192.49827 | AX17: =+AG17-AR17*0.06 -> 197.05584 | AY17: =+AH17-AS17*0.06 -> 196.02649 | AZ17: =MONTH(BA17) -> 3 | BA17: =+C17 -> 44621 | BB17: =+AB17-I17 -> 3.7331818 | BC17: =+AC17-K17 -> 3.8422727 | BD17: =+AE17-M17 -> 4.4172727 | BE17: =+AF17-D17 -> 2.6009091 | BF17: =AH17-J17 -> 4.8727273 | BG17: =+AG17-N17 -> 5.7036364 | BH17: =AVERAGE(BB17:BG17) -> 4.195 | BJ17: =+BJ5 -> 4.7333335 | BL17: =+AN17-10 -> 410.625 | BM17: =+AJ17-(BL17/1000*60) -> 174.96477
